Workbook

Sheet References
A1: Study ID | B1: Author | C1: Year | D1: Title | E1: Peer-Review Status | F1: Meta-Analysis
A2: a24 | B2: Agusti, C., et al. | C2: 2022 | D2: Feasibility of an online antigen self-testing strategy for SARS-CoV-2 addressed to health care and education professionals in Catalonia (Spain). The TESTA’T- COVID Project | E2: PR | F2: yes
A3: a25 | B3: Bresser, M., et al | C3: 2023 | D3: Evaluation of Covid-19 Ag-RDTs self-testing in Lesotho and Zambia | E3: PR | F3: yes
A4: a26 | B4: Chan, H.K. et al. | C4: 2024 | D4: Implementation pilot study of community self-testing for COVID-19 among employees of manufacturing industries and their household members in 2022 to 2023 | E4: PR | F4: yes
A5: a27 | B5: Chen, S.H., et al. | C5: 2023 | D5: Differential clinical characteristics and performance of home antigen tests between parents and children after household transmission of SARS-CoV-2 during the Omicron variant pandemic | E5: PR | F5: no
A6: a28 | B6: Chong, S.J. et al. | C6: 2023 | D6: Assessment of COVID-19 Positive Rates Amongst COVID-19 Close Contacts Through the Health Risk Warning System | E6: PR | F6: yes
A7: a29 | B7: D'Agostino, E.M., et al. | C7: 2022 | D7: Increasing access and uptake of SARS-CoV-2 at-home test using a community-engaged approach | E7: PR | F7: yes
A8: a30 | B8: Downs, L. O., et al | C8: 2021 | D8: Home-based SARS-CoV-2 lateral flow antigen testing in hospital workers | E8: PR | F8: yes
A9: a31 | B9: Du, Z., et al. | C9: 2022 | D9: Understanding the impact of rapid antigen tests on SARS-CoV-2 transmission in the fifth wave of COVID-19 in Hong Kong in early 2022 | E9: PR | F9: no
A10: a32 | B10: Engels, G., et al. | C10: 2022 | D10: Acceptance of different self-sampling methods for semiweekly SARS-CoV-2 testing in asymptomatic children and childcare workers at German day care centers | E10: PR | F10: yes
A11: a33 | B11: Gorgels, K.M.F. et al. | C11: 2024 | D11: Estimating infection prevalence using the positive predictive value of self-administered rapid antigen diagnostic tests: An exploration of SARS-CoV-2 surveillance data in the Netherlands from May 2021 to April 2022 | E11: PR | F11: no
A12: a34 | B12: Harmon, A. et al. | C12: 2021 | D12: Validation of an At-Home Direct Antigen Rapid Test for COVID-19 | E12: PR | F12: yes
A13: a35 | B13: Herbert, C., et al. (a) | C13: 2022 | D13: Design and Preliminary Findings of Adherence to the Self-Testing for Our Protection From COVID-19 (STOP COVID-19) Risk-Based Testing Protocol: Prospective Digital Study | E13: PR | F13: no
... A66: ## | B66: Pudasaini, S. et al. | C66: 2022 | D66: Feasibility of school music trips with safe cohorts during high SARS-CoV-2 incidence rates: a longitudinal observation study | E66: PP | F66: addition to a58 (Pudasaini et al.)

Sheet Quality assessment
A1: Identification | D1: Question 1 | G1: Question 2 | J1: Question 3 | M1: Question 4 | P1: Question 5 | S1: Question 6 | X1: Question 7 | AA1: Question 8 | AF1: Question 9 | AJ1: Summary of questions
A2: Study ID | B2: Sub_1 | C2: Author | D2: Test positivity | E2: Confirmat. Testing | F2: Partici-pation | G2: Test positivity | H2: Confirmat. Testing | I2: Partici-pation | J2: Test positivity | K2: Confirmat. Testing | L2: Partici-pation | M2: Test positivity | N2: Confirmat. Testing | O2: Partici-pation | P2: Test positivity | Q2: Confirmat. Testing | R2: Partici-pation | S2: Test positivity | T2: Confirmat. Testing | V2: Participation | X2: Test positivity | Y2: Confirmat. Testing | Z2: Partici-pation | AA2: Test positivity | AB2: Confirmat. Testing | AD2: Participation | AF2: Test positivity | AG2: Confirmat. Testing | AH2: Partici-pation | AJ2: Test positivity | AK2: Confirmat. Testing | AL2: Participation | AM2: Average
T3: Missed cases | U3: FP proportion | V3: Testing | W3: Reporting | AB3: Missed cases | AC3: FP proportion | AD3: Testing | AE3: Reporting
A4: a24 | B4: 1 | C4: Agusti, C., et al. | D4: yes | E4: n/a | F4: yes | G4: unclear | H4: n/a | I4: unclear | J4: unclear | K4: n/a | L4: unclear | M4: yes | N4: n/a | O4: yes | P4: no | Q4: n/a | R4: n/a | S4: yes | T4: n/a | U4: n/a | V4: yes | W4: yes | X4: yes | Y4: n/a | Z4: n/a | AA4: yes | AB4: n/a | AC4: n/a | AD4: yes | AE4: yes | AF4: yes | AG4: n/a | AH4: yes | AJ4: =IF(D4<>"n/a",(COUNTIF(D4,"yes")+COUNTIF(G4,"yes")+COUNTIF(J4,"yes")+COUNTIF(M4,"yes")+COUNTIF(P4,"yes")+COUNTIF(S4,"yes")+COUNTIF(X4,"yes")+COUNTIF(AA4,"yes")+COUNTIF(AF4,"yes"))/9,"#") -> 0.66666667 | AK4: =IF(E4<>"n/a",(COUNTIF(E4,"yes")+COUNTIF(H4,"yes")+COUNTIF(K4,"yes")+COUNTIF(N4,"yes")+COUNTIF(Q4,"yes")+IF(COUNTIF(T4:U4,"yes")>=1,1,0)+COUNTIF(Y4,"yes")+IF(COUNTIF(AB4:AC4,"yes")>=1,1,0)+COUNTIF(AG4,"yes"))/8,"#") -> # | AL4: =IF(F4<>"n/a",(COUNTIF(F4,"yes")+COUNTIF(I4,"yes")+COUNTIF(L4,"yes")+COUNTIF(O4,"yes")+COUNTIF(R4,"yes")+IF(COUNTIF(V4:W4,"yes")>=1,1,0)+COUNTIF(Z4,"yes")+IF(COUNTIF(AD4:AE4,"yes")>=1,1,0)+COUNTIF(AH4,"yes"))/7,"#") -> 0.71428571 | AM4: =AVERAGE(AJ4:AL4) -> 0.69047619
A5: a24 | B5: 2 | C5: Agusti, C., et al. | D5: yes | E5: n/a | F5: yes | G5: unclear | H5: n/a | I5: unclear | J5: unclear | K5: n/a | L5: unclear | M5: yes | N5: n/a | O5: yes | P5: no | Q5: n/a | R5: n/a | S5: yes | T5: n/a | U5: n/a | V5: yes | W5: yes | X5: yes | Y5: n/a | Z5: n/a | AA5: yes | AB5: n/a | AC5: n/a | AD5: yes | AE5: yes | AF5: yes | AG5: n/a | AH5: yes | AJ5: =IF(D5<>"n/a",(COUNTIF(D5,"yes")+COUNTIF(G5,"yes")+COUNTIF(J5,"yes")+COUNTIF(M5,"yes")+COUNTIF(P5,"yes")+COUNTIF(S5,"yes")+COUNTIF(X5,"yes")+COUNTIF(AA5,"yes")+COUNTIF(AF5,"yes"))/9,"#") -> 0.66666667 | AK5: =IF(E5<>"n/a",(COUNTIF(E5,"yes")+COUNTIF(H5,"yes")+COUNTIF(K5,"yes")+COUNTIF(N5,"yes")+COUNTIF(Q5,"yes")+IF(COUNTIF(T5:U5,"yes")>=1,1,0)+COUNTIF(Y5,"yes")+IF(COUNTIF(AB5:AC5,"yes")>=1,1,0)+COUNTIF(AG5,"yes"))/8,"#") -> # | AL5: =IF(F5<>"n/a",(COUNTIF(F5,"yes")+COUNTIF(I5,"yes")+COUNTIF(L5,"yes")+COUNTIF(O5,"yes")+COUNTIF(R5,"yes")+IF(COUNTIF(V5:W5,"yes")>=1,1,0)+COUNTIF(Z5,"yes")+IF(COUNTIF(AD5:AE5,"yes")>=1,1,0)+COUNTIF(AH5,"yes"))/7,"#") -> 0.71428571 | AM5: =AVERAGE(AJ5:AL5) -> 0.69047619
A6: a25 | B6: 0 | C6: Bresser, M., et al. | D6: yes | E6: n/a | F6: n/a | G6: unclear | H6: n/a | I6: n/a | J6: unclear | K6: n/a | L6: n/a | M6: yes | N6: n/a | O6: n/a | P6: no | Q6: n/a | R6: n/a | S6: yes | T6: n/a | U6: n/a | V6: n/a | W6: n/a | X6: yes | Y6: n/a | Z6: n/a | AA6: yes | AB6: n/a | AC6: n/a | AD6: n/a | AE6: n/a | AF6: yes | AG6: n/a | AH6: n/a | AJ6: =IF(D6<>"n/a",(COUNTIF(D6,"yes")+COUNTIF(G6,"yes")+COUNTIF(J6,"yes")+COUNTIF(M6,"yes")+COUNTIF(P6,"yes")+COUNTIF(S6,"yes")+COUNTIF(X6,"yes")+COUNTIF(AA6,"yes")+COUNTIF(AF6,"yes"))/9,"#") -> 0.66666667 | AK6: =IF(E6<>"n/a",(COUNTIF(E6,"yes")+COUNTIF(H6,"yes")+COUNTIF(K6,"yes")+COUNTIF(N6,"yes")+COUNTIF(Q6,"yes")+IF(COUNTIF(T6:U6,"yes")>=1,1,0)+COUNTIF(Y6,"yes")+IF(COUNTIF(AB6:AC6,"yes")>=1,1,0)+COUNTIF(AG6,"yes"))/8,"#") -> # | AL6: =IF(F6<>"n/a",(COUNTIF(F6,"yes")+COUNTIF(I6,"yes")+COUNTIF(L6,"yes")+COUNTIF(O6,"yes")+COUNTIF(R6,"yes")+IF(COUNTIF(V6:W6,"yes")>=1,1,0)+COUNTIF(Z6,"yes")+IF(COUNTIF(AD6:AE6,"yes")>=1,1,0)+COUNTIF(AH6,"yes"))/7,"#") -> # | AM6: =AVERAGE(AJ6:AL6) -> 0.66666667
A7: a26 | B7: 0 | C7: Chan, H.K., et al. | D7: yes | E7: n/a | F7: yes | G7: unclear | H7: n/a | I7: unclear | J7: unclear | K7: n/a | L7: unclear | M7: yes | N7: n/a | O7: yes | P7: unclear | Q7: n/a | R7: n/a | S7: yes | T7: n/a | U7: n/a | V7: yes | W7: yes | X7: no | Y7: n/a | Z7: n/a | AA7: no | AB7: n/a | AC7: n/a | AD7: yes | AE7: no | AF7: yes | AG7: n/a | AH7: yes | AJ7: =IF(D7<>"n/a",(COUNTIF(D7,"yes")+COUNTIF(G7,"yes")+COUNTIF(J7,"yes")+COUNTIF(M7,"yes")+COUNTIF(P7,"yes")+COUNTIF(S7,"yes")+COUNTIF(X7,"yes")+COUNTIF(AA7,"yes")+COUNTIF(AF7,"yes"))/9,"#") -> 0.44444444 | AK7: =IF(E7<>"n/a",(COUNTIF(E7,"yes")+COUNTIF(H7,"yes")+COUNTIF(K7,"yes")+COUNTIF(N7,"yes")+COUNTIF(Q7,"yes")+IF(COUNTIF(T7:U7,"yes")>=1,1,0)+COUNTIF(Y7,"yes")+IF(COUNTIF(AB7:AC7,"yes")>=1,1,0)+COUNTIF(AG7,"yes"))/8,"#") -> # | AL7: =IF(F7<>"n/a",(COUNTIF(F7,"yes")+COUNTIF(I7,"yes")+COUNTIF(L7,"yes")+COUNTIF(O7,"yes")+COUNTIF(R7,"yes")+IF(COUNTIF(V7:W7,"yes")>=1,1,0)+COUNTIF(Z7,"yes")+IF(COUNTIF(AD7:AE7,"yes")>=1,1,0)+COUNTIF(AH7,"yes"))/7,"#") -> 0.71428571 | AM7: =AVERAGE(AJ7:AL7) -> 0.57936508
A8: a28 | B8: 1 | C8: Chong, S.J., et al. | D8: yes | E8: n/a | F8: n/a | G8: unclear | H8: n/a | I8: n/a | J8: unclear | K8: n/a | L8: n/a | M8: yes | N8: n/a | O8: n/a | P8: yes | Q8: n/a | R8: n/a | S8: unclear | T8: n/a | U8: n/a | V8: n/a | W8: n/a | X8: no | Y8: n/a | Z8: n/a | AA8: unclear | AB8: n/a | AC8: n/a | AD8: n/a | AE8: n/a | AF8: yes | AG8: n/a | AH8: n/a | AJ8: =IF(D8<>"n/a",(COUNTIF(D8,"yes")+COUNTIF(G8,"yes")+COUNTIF(J8,"yes")+COUNTIF(M8,"yes")+COUNTIF(P8,"yes")+COUNTIF(S8,"yes")+COUNTIF(X8,"yes")+COUNTIF(AA8,"yes")+COUNTIF(AF8,"yes"))/9,"#") -> 0.44444444 | AK8: =IF(E8<>"n/a",(COUNTIF(E8,"yes")+COUNTIF(H8,"yes")+COUNTIF(K8,"yes")+COUNTIF(N8,"yes")+COUNTIF(Q8,"yes")+IF(COUNTIF(T8:U8,"yes")>=1,1,0)+COUNTIF(Y8,"yes")+IF(COUNTIF(AB8:AC8,"yes")>=1,1,0)+COUNTIF(AG8,"yes"))/8,"#") -> # | AL8: =IF(F8<>"n/a",(COUNTIF(F8,"yes")+COUNTIF(I8,"yes")+COUNTIF(L8,"yes")+COUNTIF(O8,"yes")+COUNTIF(R8,"yes")+IF(COUNTIF(V8:W8,"yes")>=1,1,0)+COUNTIF(Z8,"yes")+IF(COUNTIF(AD8:AE8,"yes")>=1,1,0)+COUNTIF(AH8,"yes"))/7,"#") -> # | AM8: =AVERAGE(AJ8:AL8) -> 0.44444444
A9: a28 | B9: 2 | C9: Chong, S.J., et al. | D9: yes | E9: n/a | F9: n/a | G9: unclear | H9: n/a | I9: n/a | J9: unclear | K9: n/a | L9: n/a | M9: yes | N9: n/a | O9: n/a | P9: yes | Q9: n/a | R9: n/a | S9: unclear | T9: n/a | U9: n/a | V9: n/a | W9: n/a | X9: no | Y9: n/a | Z9: n/a | AA9: unclear | AB9: n/a | AC9: n/a | AD9: n/a | AE9: n/a | AF9: yes | AG9: n/a | AH9: n/a | AJ9: =IF(D9<>"n/a",(COUNTIF(D9,"yes")+COUNTIF(G9,"yes")+COUNTIF(J9,"yes")+COUNTIF(M9,"yes")+COUNTIF(P9,"yes")+COUNTIF(S9,"yes")+COUNTIF(X9,"yes")+COUNTIF(AA9,"yes")+COUNTIF(AF9,"yes"))/9,"#") -> 0.44444444 | AK9: =IF(E9<>"n/a",(COUNTIF(E9,"yes")+COUNTIF(H9,"yes")+COUNTIF(K9,"yes")+COUNTIF(N9,"yes")+COUNTIF(Q9,"yes")+IF(COUNTIF(T9:U9,"yes")>=1,1,0)+COUNTIF(Y9,"yes")+IF(COUNTIF(AB9:AC9,"yes")>=1,1,0)+COUNTIF(AG9,"yes"))/8,"#") -> # | AL9: =IF(F9<>"n/a",(COUNTIF(F9,"yes")+COUNTIF(I9,"yes")+COUNTIF(L9,"yes")+COUNTIF(O9,"yes")+COUNTIF(R9,"yes")+IF(COUNTIF(V9:W9,"yes")>=1,1,0)+COUNTIF(Z9,"yes")+IF(COUNTIF(AD9:AE9,"yes")>=1,1,0)+COUNTIF(AH9,"yes"))/7,"#") -> # | AM9: =AVERAGE(AJ9:AL9) -> 0.44444444
A10: a28 | B10: 3 | C10: Chong, S.J., et al. | D10: yes | E10: n/a | F10: n/a | G10: unclear | H10: n/a | I10: n/a | J10: unclear | K10: n/a | L10: n/a | M10: yes | N10: n/a | O10: n/a | P10: yes | Q10: n/a | R10: n/a | S10: unclear | T10: n/a | U10: n/a | V10: n/a | W10: n/a | X10: no | Y10: n/a | Z10: n/a | AA10: unclear | AB10: n/a | AC10: n/a | AD10: n/a | AE10: n/a | AF10: yes | AG10: n/a | AH10: n/a | AJ10: =IF(D10<>"n/a",(COUNTIF(D10,"yes")+COUNTIF(G10,"yes")+COUNTIF(J10,"yes")+COUNTIF(M10,"yes")+COUNTIF(P10,"yes")+COUNTIF(S10,"yes")+COUNTIF(X10,"yes")+COUNTIF(AA10,"yes")+COUNTIF(AF10,"yes"))/9,"#") -> 0.44444444 | AK10: =IF(E10<>"n/a",(COUNTIF(E10,"yes")+COUNTIF(H10,"yes")+COUNTIF(K10,"yes")+COUNTIF(N10,"yes")+COUNTIF(Q10,"yes")+IF(COUNTIF(T10:U10,"yes")>=1,1,0)+COUNTIF(Y10,"yes")+IF(COUNTIF(AB10:AC10,"yes")>=1,1,0)+COUNTIF(AG10,"yes"))/8,"#") -> # | AL10: =IF(F10<>"n/a",(COUNTIF(F10,"yes")+COUNTIF(I10,"yes")+COUNTIF(L10,"yes")+COUNTIF(O10,"yes")+COUNTIF(R10,"yes")+IF(COUNTIF(V10:W10,"yes")>=1,1,0)+COUNTIF(Z10,"yes")+IF(COUNTIF(AD10:AE10,"yes")>=1,1,0)+COUNTIF(AH10,"yes"))/7,"#") -> # | AM10: =AVERAGE(AJ10:AL10) -> 0.44444444
A11: a28 | B11: 4 | C11: Chong, S.J., et al. | D11: yes | E11: n/a | F11: n/a | G11: unclear | H11: n/a | I11: n/a | J11: unclear | K11: n/a | L11: n/a | M11: yes | N11: n/a | O11: n/a | P11: yes | Q11: n/a | R11: n/a | S11: unclear | T11: n/a | U11: n/a | V11: n/a | W11: n/a | X11: no | Y11: n/a | Z11: n/a | AA11: no | AB11: n/a | AC11: n/a | AD11: n/a | AE11: n/a | AF11: yes | AG11: n/a | AH11: n/a | AJ11: =IF(D11<>"n/a",(COUNTIF(D11,"yes")+COUNTIF(G11,"yes")+COUNTIF(J11,"yes")+COUNTIF(M11,"yes")+COUNTIF(P11,"yes")+COUNTIF(S11,"yes")+COUNTIF(X11,"yes")+COUNTIF(AA11,"yes")+COUNTIF(AF11,"yes"))/9,"#") -> 0.44444444 | AK11: =IF(E11<>"n/a",(COUNTIF(E11,"yes")+COUNTIF(H11,"yes")+COUNTIF(K11,"yes")+COUNTIF(N11,"yes")+COUNTIF(Q11,"yes")+IF(COUNTIF(T11:U11,"yes")>=1,1,0)+COUNTIF(Y11,"yes")+IF(COUNTIF(AB11:AC11,"yes")>=1,1,0)+COUNTIF(AG11,"yes"))/8,"#") -> # | AL11: =IF(F11<>"n/a",(COUNTIF(F11,"yes")+COUNTIF(I11,"yes")+COUNTIF(L11,"yes")+COUNTIF(O11,"yes")+COUNTIF(R11,"yes")+IF(COUNTIF(V11:W11,"yes")>=1,1,0)+COUNTIF(Z11,"yes")+IF(COUNTIF(AD11:AE11,"yes")>=1,1,0)+COUNTIF(AH11,"yes"))/7,"#") -> # | AM11: =AVERAGE(AJ11:AL11) -> 0.44444444
A12: a29 | B12: 0 | C12: D'Agostino, E.M., et al. | D12: yes | E12: n/a | F12: n/a | G12: unclear | H12: n/a | I12: n/a | J12: unclear | K12: n/a | L12: n/a | M12: yes | N12: n/a | O12: n/a | P12: unclear | Q12: n/a | R12: n/a | S12: yes | T12: n/a | U12: n/a | V12: n/a | W12: n/a | X12: unclear | Y12: n/a | Z12: n/a | AA12: unclear | AB12: n/a | AC12: n/a | AD12: n/a | AE12: n/a | AF12: yes | AG12: n/a | AH12: n/a | AJ12: =IF(D12<>"n/a",(COUNTIF(D12,"yes")+COUNTIF(G12,"yes")+COUNTIF(J12,"yes")+COUNTIF(M12,"yes")+COUNTIF(P12,"yes")+COUNTIF(S12,"yes")+COUNTIF(X12,"yes")+COUNTIF(AA12,"yes")+COUNTIF(AF12,"yes"))/9,"#") -> 0.44444444 | AK12: =IF(E12<>"n/a",(COUNTIF(E12,"yes")+COUNTIF(H12,"yes")+COUNTIF(K12,"yes")+COUNTIF(N12,"yes")+COUNTIF(Q12,"yes")+IF(COUNTIF(T12:U12,"yes")>=1,1,0)+COUNTIF(Y12,"yes")+IF(COUNTIF(AB12:AC12,"yes")>=1,1,0)+COUNTIF(AG12,"yes"))/8,"#") -> # | AL12: =IF(F12<>"n/a",(COUNTIF(F12,"yes")+COUNTIF(I12,"yes")+COUNTIF(L12,"yes")+COUNTIF(O12,"yes")+COUNTIF(R12,"yes")+IF(COUNTIF(V12:W12,"yes")>=1,1,0)+COUNTIF(Z12,"yes")+IF(COUNTIF(AD12:AE12,"yes")>=1,1,0)+COUNTIF(AH12,"yes"))/7,"#") -> # | AM12: =AVERAGE(AJ12:AL12) -> 0.44444444
A13: a30 | B13: 0 | C13: Downs, L.O., et al | D13: yes | E13: n/a | F13: yes | G13: unclear | H13: n/a | I13: unclear | J13: unclear | K13: n/a | L13: unclear | M13: yes | N13: n/a | O13: yes | P13: yes | Q13: n/a | R13: n/a | S13: yes | T13: n/a | U13: n/a | V13: n/a | W13: yes | X13: no | Y13: n/a | Z13: n/a | AA13: unclear | AB13: n/a | AC13: n/a | AD13: n/a | AE13: no | AF13: yes | AG13: n/a | AH13: yes | AJ13: =IF(D13<>"n/a",(COUNTIF(D13,"yes")+COUNTIF(G13,"yes")+COUNTIF(J13,"yes")+COUNTIF(M13,"yes")+COUNTIF(P13,"yes")+COUNTIF(S13,"yes")+COUNTIF(X13,"yes")+COUNTIF(AA13,"yes")+COUNTIF(AF13,"yes"))/9,"#") -> 0.55555556 | AK13: =IF(E13<>"n/a",(COUNTIF(E13,"yes")+COUNTIF(H13,"yes")+COUNTIF(K13,"yes")+COUNTIF(N13,"yes")+COUNTIF(Q13,"yes")+IF(COUNTIF(T13:U13,"yes")>=1,1,0)+COUNTIF(Y13,"yes")+IF(COUNTIF(AB13:AC13,"yes")>=1,1,0)+COUNTIF(AG13,"yes"))/8,"#") -> # | AL13: =IF(F13<>"n/a",(COUNTIF(F13,"yes")+COUNTIF(I13,"yes")+COUNTIF(L13,"yes")+COUNTIF(O13,"yes")+COUNTIF(R13,"yes")+IF(COUNTIF(V13:W13,"yes")>=1,1,0)+COUNTIF(Z13,"yes")+IF(COUNTIF(AD13:AE13,"yes")>=1,1,0)+COUNTIF(AH13,"yes"))/7,"#") -> 0.57142857 | AM13: =AVERAGE(AJ13:AL13) -> 0.56349206
A14: a32 | B14: 1 | C14: Engels, G., et al. | D14: yes | E14: n/a | F14: yes | G14: unclear | H14: n/a | I14: unclear | J14: unclear | K14: n/a | L14: unclear | M14: yes | N14: n/a | O14: yes | P14: yes | Q14: n/a | R14: n/a | S14: yes | T14: n/a | U14: n/a | V14: yes | W14: yes | X14: no | Y14: n/a | Z14: n/a | AA14: no | AB14: n/a | AC14: n/a | AD14: unclear | AE14: unclear | AF14: yes | AG14: n/a | AH14: yes | AJ14: =IF(D14<>"n/a",(COUNTIF(D14,"yes")+COUNTIF(G14,"yes")+COUNTIF(J14,"yes")+COUNTIF(M14,"yes")+COUNTIF(P14,"yes")+COUNTIF(S14,"yes")+COUNTIF(X14,"yes")+COUNTIF(AA14,"yes")+COUNTIF(AF14,"yes"))/9,"#") -> 0.55555556 | AK14: =IF(E14<>"n/a",(COUNTIF(E14,"yes")+COUNTIF(H14,"yes")+COUNTIF(K14,"yes")+COUNTIF(N14,"yes")+COUNTIF(Q14,"yes")+IF(COUNTIF(T14:U14,"yes")>=1,1,0)+COUNTIF(Y14,"yes")+IF(COUNTIF(AB14:AC14,"yes")>=1,1,0)+COUNTIF(AG14,"yes"))/8,"#") -> # | AL14: =IF(F14<>"n/a",(COUNTIF(F14,"yes")+COUNTIF(I14,"yes")+COUNTIF(L14,"yes")+COUNTIF(O14,"yes")+COUNTIF(R14,"yes")+IF(COUNTIF(V14:W14,"yes")>=1,1,0)+COUNTIF(Z14,"yes")+IF(COUNTIF(AD14:AE14,"yes")>=1,1,0)+COUNTIF(AH14,"yes"))/7,"#") -> 0.57142857 | AM14: =AVERAGE(AJ14:AL14) -> 0.56349206
A15: a32 | B15: 2 | C15: Engels, G., et al. | D15: yes | E15: n/a | F15: yes | G15: unclear | H15: n/a | I15: unclear | J15: unclear | K15: n/a | L15: unclear | M15: yes | N15: n/a | O15: yes | P15: yes | Q15: n/a | R15: n/a | S15: yes | T15: n/a | U15: n/a | V15: yes | W15: yes | X15: no | Y15: n/a | Z15: n/a | AA15: no | AB15: n/a | AC15: n/a | AD15: unclear | AE15: unclear | AF15: yes | AG15: n/a | AH15: yes | AJ15: =IF(D15<>"n/a",(COUNTIF(D15,"yes")+COUNTIF(G15,"yes")+COUNTIF(J15,"yes")+COUNTIF(M15,"yes")+COUNTIF(P15,"yes")+COUNTIF(S15,"yes")+COUNTIF(X15,"yes")+COUNTIF(AA15,"yes")+COUNTIF(AF15,"yes"))/9,"#") -> 0.55555556 | AK15: =IF(E15<>"n/a",(COUNTIF(E15,"yes")+COUNTIF(H15,"yes")+COUNTIF(K15,"yes")+COUNTIF(N15,"yes")+COUNTIF(Q15,"yes")+IF(COUNTIF(T15:U15,"yes")>=1,1,0)+COUNTIF(Y15,"yes")+IF(COUNTIF(AB15:AC15,"yes")>=1,1,0)+COUNTIF(AG15,"yes"))/8,"#") -> # | AL15: =IF(F15<>"n/a",(COUNTIF(F15,"yes")+COUNTIF(I15,"yes")+COUNTIF(L15,"yes")+COUNTIF(O15,"yes")+COUNTIF(R15,"yes")+IF(COUNTIF(V15:W15,"yes")>=1,1,0)+COUNTIF(Z15,"yes")+IF(COUNTIF(AD15:AE15,"yes")>=1,1,0)+COUNTIF(AH15,"yes"))/7,"#") -> 0.57142857 | AM15: =AVERAGE(AJ15:AL15) -> 0.56349206
... A77: a84 | B77: 0 | C77: Qasmieh, S.A. et al. (c) | D77: n/a | E77: n/a | F77: yes | G77: n/a | H77: n/a | I77: unclear | J77: n/a | K77: n/a | L77: unclear | M77: n/a | N77: n/a | O77: yes | P77: n/a | Q77: n/a | R77: n/a | S77: n/a | T77: n/a | U77: n/a | V77: yes | W77: n/a | X77: n/a | Y77: n/a | Z77: n/a | AA77: n/a | AB77: n/a | AC77: n/a | AD77: unclear | AE77: n/a | AF77: n/a | AG77: n/a | AH77: yes | AJ77: =IF(D77<>"n/a",(COUNTIF(D77,"yes")+COUNTIF(G77,"yes")+COUNTIF(J77,"yes")+COUNTIF(M77,"yes")+COUNTIF(P77,"yes")+COUNTIF(S77,"yes")+COUNTIF(X77,"yes")+COUNTIF(AA77,"yes")+COUNTIF(AF77,"yes"))/9,"#") -> # | AK77: =IF(E77<>"n/a",(COUNTIF(E77,"yes")+COUNTIF(H77,"yes")+COUNTIF(K77,"yes")+COUNTIF(N77,"yes")+COUNTIF(Q77,"yes")+IF(COUNTIF(T77:U77,"yes")>=1,1,0)+COUNTIF(Y77,"yes")+IF(COUNTIF(AB77:AC77,"yes")>=1,1,0)+COUNTIF(AG77,"yes"))/8,"#") -> # | AL77: =IF(F77<>"n/a",(COUNTIF(F77,"yes")+COUNTIF(I77,"yes")+COUNTIF(L77,"yes")+COUNTIF(O77,"yes")+COUNTIF(R77,"yes")+IF(COUNTIF(V77:W77,"yes")>=1,1,0)+COUNTIF(Z77,"yes")+IF(COUNTIF(AD77:AE77,"yes")>=1,1,0)+COUNTIF(AH77,"yes"))/7,"#") -> 0.57142857 | AM77: =AVERAGE(AJ77:AL77) -> 0.57142857
A80: No meta-analyzable outcome
A81: a27 | B81: 1 | C81: Chen, S.H., et al. | AJ81: =AVERAGE(AJ4:AJ77) -> 0.53571429 | AK81: =AVERAGE(AK4:AK77) -> 0.75 | AL81: =AVERAGE(AL4:AL77) -> 0.61185984 | AM81: =AVERAGE(AM4:AM77) -> 0.57564708 | AN81: # of data sets
A82: a27 | B82: 2 | C82: Chen, S.H., et al.
A83: a31 | B83: 0 | C83: Du, Z., et al.
A84: a33 | B84: 0 | C84: Gorgels, K.M.F., et al. | AI84: # <60% | AJ84: =COUNTIF(AJ$4:AJ$77,"<0.6")/COUNT(AJ$4:AJ$77) -> 0.71428571 | AK84: =COUNTIF(AK$4:AK$77,"<0.6")/COUNT(AK$4:AK$77) -> 0 | AL84: =COUNTIF(AL$4:AL$77,"<0.6")/COUNT(AL$4:AL$77) -> 0.62264151 | AM84: =COUNTIF(AM$4:AM$77,"<0.6")/COUNT(AM$4:AM$77) -> 0.63513514 | AN84: =COUNT(AM4:AM77)*AM84 -> 47
A85: a35 | B85: 2 | C85: Herbert, C., et al. (a) | AI85: # 60-80% | AJ85: =COUNTIF(AJ$4:AJ$77,"<=0.8")/COUNT(AJ$4:AJ$77)-AJ$84 -> 0.28571429 | AK85: =COUNTIF(AK$4:AK$77,"<=0.8")/COUNT(AK$4:AK$77)-AK$84 -> 1 | AL85: =COUNTIF(AL$4:AL$77,"<=0.8")/COUNT(AL$4:AL$77)-AL$84 -> 0.37735849 | AM85: =COUNTIF(AM$4:AM$77,"<=0.8")/COUNT(AM$4:AM$77)-AM$84 -> 0.36486486 | AN85: =COUNT(AM4:AM77)*AM85 -> 27
A86: a42 | B86: 0 | C86: Kheiroddin, P., et al. | AI86: # >80% | AJ86: =COUNTIF(AJ$4:AJ$77,">0.8")/COUNT(AJ$4:AJ$77) -> 0 | AK86: =COUNTIF(AK$4:AK$77,">0.8")/COUNT(AK$4:AK$77) -> 0 | AL86: =COUNTIF(AL$4:AL$77,">0.8")/COUNT(AL$4:AL$77) -> 0 | AM86: =COUNTIF(AM$4:AM$77,">0.8")/COUNT(AM$4:AM$77) -> 0 | AN86: =COUNT(AM4:AM77)*AM86 -> 0
A87: a53 | B87: 0 | C87: Moonan, P.K., et al.
A88: a54 | B88: 0 | C88: Nagasawa, M., et al. | AI88: # <60% | AJ88: =COUNTIF(AJ$4:AJ$77,"<0.6") -> 40 | AK88: =COUNTIF(AK$4:AK$77,"<0.6") -> 0 | AL88: =COUNTIF(AL$4:AL$77,"<0.6") -> 33 | AM88: =COUNTIF(AM$4:AM$77,"<0.6") -> 47 | AN88: =AM88 -> 47
A89: a61 | B89: 0 | C89: Soni, A., et al. (a) | AI89: # 60-80% | AJ89: =COUNTIF(AJ$4:AJ$77,"<=0.8")-AJ88 -> 16 | AK89: =COUNTIF(AK$4:AK$77,"<=0.8")-AK88 -> 11 | AL89: =COUNTIF(AL$4:AL$77,"<=0.8")-AL88 -> 20 | AM89: =COUNTIF(AM$4:AM$77,"<=0.8")-AM88 -> 27 | AN89: =AM89 -> 27
A90: a70 | B90: 2 | C90: U. o. Liverpool | AI90: # >80% | AJ90: =COUNTIF(AJ$4:AJ$77,">0.8") -> 0 | AK90: =COUNTIF(AK$4:AK$77,">0.8") -> 0 | AL90: =COUNTIF(AL$4:AL$77,">0.8") -> 0 | AM90: =COUNTIF(AM$4:AM$77,">0.8") -> 0 | AN90: =AM90 -> 0
A91: a73 | B91: 0 | C91: Wong, S.C., et al.
A92: a81 | B92: 1 | C92: Stirrup, O. et al. | AI92: SUM | AJ92: =SUM(AJ88:AJ90) -> 56 | AK92: =SUM(AK88:AK90) -> 11 | AL92: =SUM(AL88:AL90) -> 53 | AM92: =SUM(AM88:AM90) -> 74 | AN92: =SUM(AN88:AN90) -> 74
A93: a81 | B93: 2 | C93: Stirrup, O. et al.

Sheet Data extracted
A1: Identification | C1: Study Characteristics | AJ1: Testing Characteristics | BY1: Individual level health outcome | CK1: Community level health outcome | DE1: Include in analysis | DG1: Sensitivity analyses
C2: General | K2: Number of study participants | P2: Characteristics study population | AJ2: Ag-RDT implementation | AY2: Ag-RDT result - in number of tests | BD2: Confirmatory testing - in number of tests | BL2: Ag-RDT result - in number of people | BQ2: Confirmatory testing - in number of people | BY2: Actions after Ag-RDT result | CE2: Undesirable Effects | CI2: Individual level health impact | CK2: Transmission | CS2: Population health benefits | CU2: Health system effects | CX2: Broader societal effects
A3: Study ID | B3: Author | C3: Type | D3: Start Date | E3: End Date | F3: Location | G3: Location details | H3: Community | I3: 2025 GDP per Capita | J3: Costs for study participants | K3: Number of people eligible / invited for self-testing | L3: Number of people that collected / were sent self-tests | M3: Number of people that reported self-testing results | N3: Max | O3: Population included in study based on … | P3: Age (mean) | Q3: Age (SD) | R3: Age (median) | S3: Age (Q1) | T3: Age (Q3) | U3: Age (u range) | V3: Age (l range) | W3: Females | X3: Males | Y3: Other / unknown sex | Z3: Target population | AA3: Symptomatic individuals | AB3: Asymptomatic individuals | AC3: Unknown symptom status | AD3: Overview symptom status | AE3: Risk Factors | AF3: SARS-CoV-2 Exposure | AG3: SARS-CoV-2 status | AH3: Vaccination status | AI3: Seroconvalescence status | AJ3: Ag-RDT name | AK3: Reader | AL3: Sample Type | AM3: Test distributer | AN3: Testing site | AO3: Frequency of Testing | AP3: Times per week | AQ3: Duration in weeks | AR3: Optimal # of tests performed as per testing scheme | AS3: Number of self-tests performed | AT3: Number of results reported | AU3: Assistance | AV3: Supervision | AW3: Additional interventions | AX3: Continue after positive confirmatory test result? | AY3: Ag-RDT_n tests_SUM | AZ3: Ag-RDT_n tests_Positive | BA3: Ag-RDT_n tests_Negative | BB3: Ag-RDT_n tests_Invalid | BC3: Ag-RDT_n tests_False Interpretation | BD3: Confirm_n tests_Type | BE3: Confirm_n tests_Sample type | BF3: Confirm_n tests_Total | BG3: Confirm_n tests_TP | BH3: Confirm_n tests_FN | BI3: Confirm_n tests_TN | BJ3: Confirm_n tests_FP | BK3: Confirm_n_tests_FP_ref | BL3: Ag-RDT_n people_SUM | BM3: Ag-RDT_n people_Positive | BN3: Ag-RDT_n people_Negative | BO3: Ag-RDT_n people_Invalid | BP3: Ag-RDT_n people_False Interpretation | BQ3: Confirm_n people_Type | BR3: Confirm_n people_Sample type | BS3: Confirm_n people_Total | BT3: Confirm_n people_TP | BU3: Confirm_n people_FN | BV3: Confirm_n people_TN | BW3: Confirm_n people_FP | BX3: Confirm_n people_FN_ref | BY3: Tool to diagnose | BZ3: Time to diagnosis | CA3: Time to decision | CB3: Ag-RDT positive result | CC3: RT-PCR follow up | CD3: Ag-RDT negative result | CE3: Use out of the intended | CF3: Fabrication of Data | CG3: Social Harm | CH3: Adverse Events | CI3: Hospitalization | CJ3: Disease Severity | CK3: Incidence | CL3: Prevalence | CM3: Cases Averted | CN3: Tertiary cases | CO3: Tertiary cases_denominator | CP3: Tertiary cases_comparator | CQ3: Tertiary cases_denominator_comparator | CR3: Tertiary contacts | CS3: Deaths Averted | CT3: Morbidity Averted | CU3: Hospitalization | CV3: ICU occupancy | CW3: Transmission within health care workers | CX3: School / Work Operations | CY3: Quarantine Duration | CZ3: Wellbeing | DA3: Absenteeism | DB3: Resource Usage | DC3: User Costs | DD3: Time Savings | DE3: FP_analysis | DF3: Missed_analysis | DG3: SA_Uptake | DH3: SA_Reporting | DI3: Behaviour change
A4: a24_1 | B4: Agusti, C., et al. | C4: prosp. cohort | D4: 44545 | E4: 44607 | F4: Spain | G4: EU; Staff of the Catalan Institute of Oncology | H4: City; semi-dense | I4: 38039.876 | J4: unclear | K4: 1400 | L4: 195 | M4: 111 | N4: =MAX(K4:M4) -> 1400 | O4: Number of people that reported self-testing results | P4: # | Q4: # | R4: 42.8 | S4: 32.4 | T4: 53.2 | U4: # | V4: # | W4: 91 | X4: 20 | Y4: 0 | Z4: Healthcare Professionals | AA4: 21 | AB4: 89 | AC4: 1 | AD4: =IF(AND(AA4=0,AC4=0),1,0) -> 0 | AE4: # | AF4: # | AG4: unknown | AH4: 110 are vaccinated, 1 not | AI4: # | AJ4: Panbio Antigen self-test, Abbot | AK4: no | AL4: AN / MT | AM4: unclear | AN4: Home | AO4: Single | AP4: # | AQ4: # | AR4: 195 | AS4: # | AT4: 111 | AU4: no | AV4: no | AW4: unclear | AX4: # | AY4: =SUM(AZ4:BC4) -> 111 | AZ4: 4 | BA4: =111-AZ4 -> 107 | BB4: 0 | BC4: # | BD4: # | BE4: # | BF4: =SUM(BG4:BJ4) -> 0 | BG4: # | BH4: # | BI4: # | BJ4: # | BK4: =IFERROR(IF(BJ4<>"#",BJ4+BI4,"#"),"#") -> # | BL4: =SUM(BM4:BP4) -> 111 | BM4: 4 | BN4: =111-BM4 -> 107 | BO4: 0 | BP4: # | BQ4: # | BR4: # | BS4: =SUM(BT4:BW4) -> 0 | BT4: # | BU4: # | BV4: # | BW4: # | BX4: =IFERROR(IF(BU4<>"#",BU4+BT4,"#"),"#") -> # | BY4: # | BZ4: # | CA4: test result available within a few minutes | CB4: Recommendation to self-isolate and contact general practitioner (GP) as soon as possible | CC4: # | CD4: # | CE4: # | CF4: # | CG4: # | CH4: # | CI4: # | CJ4: # | CK4: # | CL4: # | CM4: # | CN4: # | CO4: # | CP4: # | CQ4: # | CR4: # | CS4: # | CT4: # | CU4: # | CV4: # | CW4: # | CX4: # | CY4: # | CZ4: 81.1% (90) of participants felt self-test can improve security and protection of COVID-19 in the workplace and 44.1% (49) found the option to perform self-testing in privat / confidentially an advantage | DA4: # | DB4: # | DC4: 61.3% (68) of study participants found self-testing being availbae for free to be an advantage of self-testing | DD4: # | DE4: # | DF4: # | DG4: # | DH4: # | DI4: #
A5: a24_2 | B5: Agusti, C., et al. | C5: prosp. cohort | D5: 44545 | E5: 44607 | F5: Spain | G5: EU; Staff of the schools belonging to the COVID Sentinel School Network of Catalonia | H5: City; semi-dense | I5: 38039.876 | J5: unclear | K5: 700 | L5: 297 | M5: 192 | N5: =MAX(K5:M5) -> 700 | O5: Number of people that reported self-testing results | P5: # | Q5: # | R5: 42.1 | S5: 31.8 | T5: 52.4 | U5: # | V5: # | W5: 155 | X5: 39 | Y5: 2 | Z5: K-12 students and staff | AA5: 42 | AB5: 152 | AC5: 2 | AD5: =IF(AND(AA5=0,AC5=0),1,0) -> 0 | AE5: # | AF5: # | AG5: unknown | AH5: 193 are vaccinated, 2 not, 1 unclear | AI5: # | AJ5: Panbio Antigen self-test, Abbot | AK5: no | AL5: AN / MT | AM5: unclear | AN5: Home | AO5: Single | AP5: # | AQ5: # | AR5: 297 | AS5: # | AT5: 192 | AU5: no | AV5: no | AW5: unclear | AX5: # | AY5: =SUM(AZ5:BC5) -> 192 | AZ5: 14 | BA5: =192-AZ5 -> 178 | BB5: 0 | BC5: # | BD5: # | BE5: # | BF5: =SUM(BG5:BJ5) -> 0 | BG5: # | BH5: # | BI5: # | BJ5: # | BK5: =IFERROR(IF(BJ5<>"#",BJ5+BI5,"#"),"#") -> # | BL5: =SUM(BM5:BP5) -> 192 | BM5: 14 | BN5: =192-BM5 -> 178 | BO5: 0 | BP5: # | BQ5: # | BR5: # | BS5: =SUM(BT5:BW5) -> 0 | BT5: # | BU5: # | BV5: # | BW5: # | BX5: =IFERROR(IF(BU5<>"#",BU5+BT5,"#"),"#") -> # | BY5: # | BZ5: # | CA5: test result available within a few minutes | CB5: Recommendation to self-isolate and contact general practitioner (GP) as soon as possible | CC5: # | CD5: # | CE5: # | CF5: # | CG5: # | CH5: # | CI5: # | CJ5: # | CK5: # | CL5: # | CM5: # | CN5: # | CO5: # | CP5: # | CQ5: # | CR5: # | CS5: # | CT5: # | CU5: # | CV5: # | CW5: # | CX5: # | CY5: # | CZ5: 86.7% (170) of participants felt self-test can improve security and protection of COVID-19 in the workplace and 31.6% (62) found the option to perform self-testing in privat / confidentially an advantage | DA5: # | DB5: # | DC5: 64.8% (127) of study participants found self-testing being availbae for free to be an advantage of self-testing | DD5: # | DE5: # | DF5: # | DG5: # | DH5: # | DI5: #
A6: a25_0 | B6: Bresser, M., et al. | C6: prosp. cohort | D6: 44607 | E6: 44666 | F6: Zambia | G6: Other; Individuals near Kabwe town in Central Province | H6: Semi-dense | I6: 1352.989 | J6: unclear | K6: # | L6: # | M6: 1123 | N6: =MAX(K6:M6) -> 1123 | O6: Number of people that collected / were sent self-tests | P6: # | Q6: # | R6: 27 | S6: 21 | T6: 37 | U6: # | V6: # | W6: 432 | X6: # | Y6: # | Z6: General population | AA6: 199 | AB6: 937 | AC6: 0 | AD6: =IF(AND(AA6=0,AC6=0),1,0) -> 0 | AE6: 50 are PLHIV, of which 41 are on ART; 1059 are HIV negative and 4 have unknown HIV status; 4 on TB treatment | AF6: # | AG6: unknown | AH6: # | AI6: # | AJ6: Standard Q | AK6: no | AL6: AN / MT | AM6: Testing Site | AN6: Home / Testing Site | AO6: Single | AP6: # | AQ6: # | AR6: # | AS6: # | AT6: 1121 | AU6: no | AV6: yes | AW6: # | AX6: # | AY6: =SUM(AZ6:BC6) -> 1123 | AZ6: 9 | BA6: 1109 | BB6: 5 | BC6: # | BD6: Professional Ag-RDT testing | BE6: # | BF6: =SUM(BG6:BJ6) -> 1118 | BG6: 9 | BH6: 2 | BI6: 1107 | BJ6: 0 | BK6: =IFERROR(IF(BJ6<>"#",BJ6+BI6,"#"),"#") -> 1107 | BL6: =SUM(BM6:BP6) -> 1123 | BM6: 9 | BN6: 1109 | BO6: 5 | BP6: # | BQ6: Professional Ag-RDT testing | BR6: # | BS6: =SUM(BT6:BW6) -> 1118 | BT6: 9 | BU6: 2 | BV6: 1107 | BW6: # | BX6: =IFERROR(IF(BU6<>"#",BU6+BT6,"#"),"#") -> 11 | BY6: C19ST or Ag-RDT professional test | BZ6: 15 min | CA6: # | CB6: Follow national COVID-19 guideline | CC6: # | CD6: # | CE6: # | CF6: # | CG6: # | CH6: # | CI6: # | CJ6: # | CK6: # | CL6: # | CM6: # | CN6: # | CO6: # | CP6: # | CQ6: # | CR6: # | CS6: # | CT6: # | CU6: # | CV6: # | CW6: # | CX6: # | CY6: # | CZ6: # | DA6: # | DB6: # | DC6: # | DD6: # | DE6: # | DF6: # | DG6: # | DH6: # | DI6: #
A7: a26_0 | B7: Chan, H.K., et al. | C7: prosp. cohort | D7: 44880 | E7: 44978 | F7: Malaysia | G7: AS; Manufacturing employees / household members in Kedah | H7: unclear | I7: 13900.839 | J7: unclear | K7: 2959 | L7: 1768 | M7: 396 | N7: =MAX(K7:M7) -> 2959 | O7: Number of people that collected / were sent self-tests | P7: # | Q7: # | R7: # | S7: # | T7: # | U7: # | V7: # | W7: 1017 | X7: 740 | Y7: 6 | Z7: Manufacturing employees | AA7: # | AB7: # | AC7: # | AD7: =IF(AND(AA7=0,AC7=0),1,0) -> 0 | AE7: # | AF7: # | AG7: unknown | AH7: # | AI7: # | AJ7: FlowFlex SARS-CoV-2 antigen rapid test | AK7: no | AL7: AN / MT | AM7: Workplace | AN7: Home | AO7: Unclear | AP7: # | AQ7: =ROUND(('Data extracted'!E7-'Data extracted'!D7)/7,0) -> 14 | AR7: # | AS7: # | AT7: # | AU7: no | AV7: no | AW7: Ag-RDT training at begin of the study; satisfaction surveys | AX7: # | AY7: # | AZ7: # | BA7: # | BB7: # | BC7: # | BD7: # | BE7: # | BF7: =SUM(BG7:BJ7) -> 0 | BG7: # | BH7: # | BI7: # | BJ7: # | BK7: =IFERROR(IF(BJ7<>"#",BJ7+BI7,"#"),"#") -> # | BL7: =SUM(BM7:BP7) -> 396 | BM7: 40 | BN7: 329 | BO7: 27 | BP7: # | BQ7: # | BR7: # | BS7: =SUM(BT7:BW7) -> 0 | BT7: # | BU7: # | BV7: # | BW7: # | BX7: =IFERROR(IF(BU7<>"#",BU7+BT7,"#"),"#") -> # | BY7: # | BZ7: # | CA7: # | CB7: Report result to employer; follow national COVID-19 guideline | CC7: # | CD7: # | CE7: # | CF7: # | CG7: # | CH7: # | CI7: # | CJ7: # | CK7: # | CL7: # | CM7: # | CN7: # | CO7: # | CP7: # | CQ7: # | CR7: # | CS7: # | CT7: # | CU7: # | CV7: # | CW7: # | CX7: # | CY7: More willing to self-isolate as much as possible | CZ7: Less worried about COVID-19 | DA7: # | DB7: # | DC7: # | DD7: # | DE7: # | DF7: # | DG7: # | DH7: # | DI7: #
A8: a27_1 | B8: Chen, S.H., et al. | C8: retrosp. cohort | D8: 44692 | E8: 44722 | F8: Taiwan | G8: AS; Patients of the National Taiwan University Children’s Hospital | H8: City | I8: 37826.616 | J8: regulated, country wide price | K8: 426 | L8: # | M8: # | N8: =MAX(K8:M8) -> 426 | O8: Number of people eligible for self-testing | P8: # | Q8: # | R8: 5 | S8: 2 | T8: 8 | U8: # | V8: # | W8: # | X8: 227 | Y8: # | Z8: General population | AA8: 389 | AB8: 37 | AC8: 0 | AD8: =IF(AND(AA8=0,AC8=0),1,0) -> 0 | AE8: 22 | AF8: 330 | AG8: unknown | AH8: 25 | AI8: # | AJ8: Unclear | AK8: # | AL8: unclear | AM8: Purchase at free market (pharmacy etc.) | AN8: Home | AO8: Single | AP8: # | AQ8: =ROUND(('Data extracted'!E8-'Data extracted'!D8)/7,0) -> 4 | AR8: # | AS8: # | AT8: # | AU8: no | AV8: no | AW8: unclear | AX8: STOPP self-testing since testing was only done once | AY8: # | AZ8: # | BA8: # | BB8: # | BC8: # | BD8: RT-PCR | BE8: NP | BF8: =SUM(BG8:BJ8) -> 249 | BG8: 186 | BH8: 38 | BI8: 24 | BJ8: 1 | BK8: =IFERROR(IF(BJ8<>"#",BJ8+BI8,"#"),"#") -> 25 | BL8: # | BM8: # | BN8: # | BO8: # | BP8: # | BQ8: RT-PCR | BR8: NP | BS8: =SUM(BT8:BW8) -> 249 | BT8: 186 | BU8: 38 | BV8: 24 | BW8: 1 | BX8: =IFERROR(IF(BU8<>"#",BU8+BT8,"#"),"#") -> 224 | BY8: C19ST or RT-PCR | BZ8: 30min | CA8: # | CB8: # | CC8: # | CD8: # | CE8: # | CF8: # | CG8: # | CH8: # | CI8: # | CJ8: # | CK8: # | CL8: # | CM8: # | CN8: # | CO8: # | CP8: # | CQ8: # | CR8: # | CS8: # | CT8: # | CU8: # | CV8: # | CW8: # | CX8: # | CY8: # | CZ8: # | DA8: # | DB8: # | DC8: # | DD8: # | DE8: # | DF8: # | DG8: # | DH8: # | DI8: #
A9: a27_2 | B9: Chen, S.H., et al. | C9: retrosp. cohort | D9: 44692 | E9: 44722 | F9: Taiwan | G9: AS; Patients of the National Taiwan University Children’s Hospital | H9: City | I9: 37826.616 | J9: regulated, country wide price | K9: 201 | L9: # | M9: # | N9: =MAX(K9:M9) -> 201 | O9: Number of people eligible for self-testing | P9: # | Q9: # | R9: 40 | S9: 36 | T9: 44 | U9: # | V9: # | W9: # | X9: 66 | Y9: # | Z9: General population | AA9: 154 | AB9: 48 | AC9: 0 | AD9: =IF(AND(AA9=0,AC9=0),1,0) -> 0 | AE9: 13 | AF9: 154 | AG9: unknown | AH9: 198 | AI9: # | AJ9: Unclear | AK9: # | AL9: unclear | AM9: Purchase at free market (pharmacy etc.) | AN9: Home | AO9: Single | AP9: # | AQ9: =ROUND(('Data extracted'!E9-'Data extracted'!D9)/7,0) -> 4 | AR9: # | AS9: # | AT9: # | AU9: no | AV9: no | AW9: unclear | AX9: STOPP self-testing since testing was only done once | AY9: # | AZ9: # | BA9: # | BB9: # | BC9: # | BD9: RT-PCR | BE9: NP | BF9: =SUM(BG9:BJ9) -> 148 | BG9: 78 | BH9: 29 | BI9: 36 | BJ9: 5 | BK9: =IFERROR(IF(BJ9<>"#",BJ9+BI9,"#"),"#") -> 41 | BL9: # | BM9: # | BN9: # | BO9: # | BP9: # | BQ9: RT-PCR | BR9: NP | BS9: =SUM(BT9:BW9) -> 148 | BT9: 78 | BU9: 29 | BV9: 36 | BW9: 5 | BX9: =IFERROR(IF(BU9<>"#",BU9+BT9,"#"),"#") -> 107 | BY9: C19ST or RT-PCR | BZ9: 30min | CA9: # | CB9: # | CC9: # | CD9: # | CE9: # | CF9: # | CG9: # | CH9: # | CI9: # | CJ9: # | CK9: # | CL9: # | CM9: # | CN9: # | CO9: # | CP9: # | CQ9: # | CR9: # | CS9: # | CT9: # | CU9: # | CV9: # | CW9: # | CX9: # | CY9: # | CZ9: # | DA9: # | DB9: # | DC9: # | DD9: # | DE9: # | DF9: # | DG9: # | DH9: # | DI9: #
A10: a28_1 | B10: Chong, S.J., et al. | C10: prosp. cohort | D10: 44567 | E10: 44609 | F10: Singapore | G10: AS; Adults across Singapore | H10: City | I10: 94480.797 | J10: unclear | K10: # | L10: # | M10: 342302 | N10: =MAX(K10:M10) -> 342302 | O10: Number of people that reported self-testing results | P10: # | Q10: # | R10: # | S10: # | T10: # | U10: # | V10: # | W10: # | X10: # | Y10: # | Z10: General population | AA10: # | AB10: # | AC10: # | AD10: =IF(AND(AA10=0,AC10=0),1,0) -> 0 | AE10: # | AF10: Close contact | AG10: unknown | AH10: # | AI10: # | AJ10: Unclear | AK10: # | AL10: # | AM10: Government | AN10: Home | AO10: Routine | AP10: 7 | AQ10: 1 | AR10: =AQ10*AP10*M10 -> 2396114 | AS10: # | AT10: # | AU10: no | AV10: no | AW10: # | AX10: # | AY10: # | AZ10: # | BA10: # | BB10: # | BC10: # | BD10: # | BE10: # | BF10: =SUM(BG10:BJ10) -> 0 | BG10: # | BH10: # | BI10: # | BJ10: # | BK10: =IFERROR(IF(BJ10<>"#",BJ10+BI10,"#"),"#") -> # | BL10: =SUM(BM10:BP10) -> 342302 | BM10: 37220 | BN10: 305082 | BO10: # | BP10: # | BQ10: RT-PCR | BR10: # | BS10: 8767 | BT10: # | BU10: # | BV10: # | BW10: # | BX10: =IFERROR(IF(BU10<>"#",BU10+BT10,"#"),"#") -> # | BY10: # | BZ10: # | CA10: # | CB10: Notify government authorities (visit specific website to understand exact steps) | CC10: # | CD10: Leave self-isolation and continue daily acitivities; re-test daily ; notify authorities if test was taken on last day of isolation period (day 7) | CE10: # | CF10: # | CG10: # | CH10: # | CI10: # | CJ10: # | CK10: # | CL10: # | CM10: # | CN10: # | CO10: # | CP10: # | CQ10: # | CR10: # | CS10: # | CT10: # | CU10: # | CV10: # | CW10: # | CX10: # | CY10: # | CZ10: # | DA10: # | DB10: # | DC10: # | DD10: # | DE10: # | DF10: # | DG10: # | DH10: # | DI10: #
A11: a28_2 | B11: Chong, S.J., et al. | C11: prosp. cohort | D11: 44567 | E11: 44609 | F11: Singapore | G11: AS; Adults across Singapore | H11: City | I11: 94480.797 | J11: unclear | K11: # | L11: # | M11: 297340 | N11: =MAX(K11:M11) -> 297340 | O11: Number of people that reported self-testing results | P11: # | Q11: # | R11: # | S11: # | T11: # | U11: # | V11: # | W11: # | X11: # | Y11: # | Z11: General population | AA11: # | AB11: # | AC11: # | AD11: =IF(AND(AA11=0,AC11=0),1,0) -> 0 | AE11: # | AF11: Close contact | AG11: unknown | AH11: # | AI11: # | AJ11: Unclear | AK11: # | AL11: # | AM11: Government | AN11: Home | AO11: Routine | AP11: 6 | AQ11: 1 | AR11: =AQ11*AP11*M11 -> 1784040 | AS11: # | AT11: # | AU11: no | AV11: no | AW11: # | AX11: # | AY11: # | AZ11: # | BA11: # | BB11: # | BC11: # | BD11: # | BE11: # | BF11: =SUM(BG11:BJ11) -> 0 | BG11: # | BH11: # | BI11: # | BJ11: # | BK11: =IFERROR(IF(BJ11<>"#",BJ11+BI11,"#"),"#") -> # | BL11: =SUM(BM11:BP11) -> 297340 | BM11: 11577 | BN11: 285763 | BO11: # | BP11: # | BQ11: RT-PCR | BR11: # | BS11: 4925 | BT11: # | BU11: # | BV11: # | BW11: # | BX11: =IFERROR(IF(BU11<>"#",BU11+BT11,"#"),"#") -> # | BY11: # | BZ11: # | CA11: # | CB11: Notify government authorities (visit specific website to understand exact steps) | CC11: # | CD11: Leave self-isolation and continue daily acitivities; re-test daily ; notify authorities if test was taken on last day of isolation period (day 7) | CE11: # | CF11: # | CG11: # | CH11: # | CI11: # | CJ11: # | CK11: # | CL11: # | CM11: # | CN11: # | CO11: # | CP11: # | CQ11: # | CR11: # | CS11: # | CT11: # | CU11: # | CV11: # | CW11: # | CX11: # | CY11: # | CZ11: # | DA11: # | DB11: # | DC11: # | DD11: # | DE11: # | DF11: # | DG11: # | DH11: # | DI11: #
A12: a28_3 | B12: Chong, S.J., et al. | C12: prosp. cohort | D12: 44567 | E12: 44609 | F12: Singapore | G12: AS; Adults across Singapore | H12: City | I12: 94480.797 | J12: unclear | K12: # | L12: # | M12: 73259 | N12: =MAX(K12:M12) -> 73259 | O12: Number of people that reported self-testing results | P12: # | Q12: # | R12: # | S12: # | T12: # | U12: # | V12: # | W12: # | X12: # | Y12: # | Z12: General population | AA12: # | AB12: # | AC12: # | AD12: =IF(AND(AA12=0,AC12=0),1,0) -> 0 | AE12: # | AF12: Close contact | AG12: unknown | AH12: # | AI12: # | AJ12: Unclear | AK12: # | AL12: # | AM12: Government | AN12: Home | AO12: Routine | AP12: 6 | AQ12: 1 | AR12: =AQ12*AP12*M12 -> 439554 | AS12: # | AT12: # | AU12: no | AV12: no | AW12: # | AX12: # | AY12: # | AZ12: # | BA12: # | BB12: # | BC12: # | BD12: # | BE12: # | BF12: =SUM(BG12:BJ12) -> 0 | BG12: # | BH12: # | BI12: # | BJ12: # | BK12: =IFERROR(IF(BJ12<>"#",BJ12+BI12,"#"),"#") -> # | BL12: =SUM(BM12:BP12) -> 73259 | BM12: 1369 | BN12: 71890 | BO12: # | BP12: # | BQ12: RT-PCR | BR12: # | BS12: 649 | BT12: # | BU12: # | BV12: # | BW12: # | BX12: =IFERROR(IF(BU12<>"#",BU12+BT12,"#"),"#") -> # | BY12: # | BZ12: # | CA12: # | CB12: Notify government authorities (visit specific website to understand exact steps) | CC12: # | CD12: Leave self-isolation and continue daily acitivities; re-test daily ; notify authorities if test was taken on last day of isolation period (day 7) | CE12: # | CF12: # | CG12: # | CH12: # | CI12: # | CJ12: # | CK12: # | CL12: # | CM12: # | CN12: # | CO12: # | CP12: # | CQ12: # | CR12: # | CS12: # | CT12: # | CU12: # | CV12: # | CW12: # | CX12: # | CY12: # | CZ12: # | DA12: # | DB12: # | DC12: # | DD12: # | DE12: # | DF12: # | DG12: # | DH12: # | DI12: #
A13: a28_4 | B13: Chong, S.J., et al. | C13: prosp. cohort | D13: 44567 | E13: 44609 | F13: Singapore | G13: AS; Adults across Singapore | H13: City | I13: 94480.797 | J13: unclear | K13: # | L13: # | M13: 564 | N13: =MAX(K13:M13) -> 564 | O13: Number of people that reported self-testing results | P13: # | Q13: # | R13: # | S13: # | T13: # | U13: # | V13: # | W13: # | X13: # | Y13: # | Z13: General population | AA13: # | AB13: # | AC13: # | AD13: =IF(AND(AA13=0,AC13=0),1,0) -> 0 | AE13: # | AF13: Close contact | AG13: unknown | AH13: # | AI13: # | AJ13: Unclear | AK13: # | AL13: # | AM13: Government | AN13: Home | AO13: Routine | AP13: 6 | AQ13: 1 | AR13: =AQ13*AP13*M13 -> 3384 | AS13: # | AT13: # | AU13: no | AV13: no | AW13: # | AX13: # | AY13: # | AZ13: # | BA13: # | BB13: # | BC13: # | BD13: # | BE13: # | BF13: =SUM(BG13:BJ13) -> 0 | BG13: # | BH13: # | BI13: # | BJ13: # | BK13: =IFERROR(IF(BJ13<>"#",BJ13+BI13,"#"),"#") -> # | BL13: =SUM(BM13:BP13) -> 564 | BM13: 15 | BN13: 549 | BO13: # | BP13: # | BQ13: RT-PCR | BR13: # | BS13: 1561 | BT13: # | BU13: # | BV13: # | BW13: # | BX13: =IFERROR(IF(BU13<>"#",BU13+BT13,"#"),"#") -> # | BY13: # | BZ13: # | CA13: # | CB13: Notify government authorities (visit specific website to understand exact steps) | CC13: # | CD13: Leave self-isolation and continue daily acitivities; re-test daily ; notify authorities if test was taken on last day of isolation period (day 7) | CE13: # | CF13: # | CG13: # | CH13: # | CI13: # | CJ13: # | CK13: # | CL13: # | CM13: # | CN13: # | CO13: # | CP13: # | CQ13: # | CR13: # | CS13: # | CT13: # | CU13: # | CV13: # | CW13: # | CX13: # | CY13: # | CZ13: # | DA13: # | DB13: # | DC13: # | DD13: # | DE13: # | DF13: # | DG13: # | DH13: # | DI13: #
A14: a29_0 | B14: D'Agostino, E.M., et al. | C14: prosp. cohort | D14: 44518 | E14: 44561 | F14: United States | G14: NA; Individuals across Merced County, California | H14: City; semi-dense | I14: 89598.86 | J14: free | K14: # | L14: # | M14: 2469 | N14: =MAX(K14:M14) -> 2469 | O14: n/a | P14: # | Q14: # | R14: # | S14: # | T14: # | U14: # | V14: # | W14: # | X14: # | Y14: # | Z14: General population | AA14: # | AB14: # | AC14: # | AD14: =IF(AND(AA14=0,AC14=0),1,0) -> 0 | AE14: # | AF14: 319 | AG14: unknown | AH14: 2058 | AI14: # | AJ14: QuickVue | AK14: no | AL14: AN / MT | AM14: Community workers | AN14: Home | AO14: Unclear | AP14: # | AQ14: # | AR14: # | AS14: 3262 | AT14: 2469 | AU14: no | AV14: no | AW14: # | AX14: # | AY14: =SUM(AZ14:BC14) -> 2469 | AZ14: 235 | BA14: 2234 | BB14: 0 | BC14: # | BD14: # | BE14: # | BF14: =SUM(BG14:BJ14) -> 0 | BG14: # | BH14: # | BI14: # | BJ14: # | BK14: =IFERROR(IF(BJ14<>"#",BJ14+BI14,"#"),"#") -> # | BL14: =SUM(BM14:BP14) -> 0 | BM14: # | BN14: # | BO14: # | BP14: # | BQ14: # | BR14: # | BS14: =SUM(BT14:BW14) -> 0 | BT14: # | BU14: # | BV14: # | BW14: # | BX14: =IFERROR(IF(BU14<>"#",BU14+BT14,"#"),"#") -> # | BY14: # | BZ14: # | CA14: # | CB14: # | CC14: # | CD14: # | CE14: # | CF14: # | CG14: # | CH14: # | CI14: # | CJ14: # | CK14: # | CL14: # | CM14: # | CN14: # | CO14: # | CP14: # | CQ14: # | CR14: # | CS14: # | CT14: # | CU14: # | CV14: # | CW14: # | CX14: # | CY14: # | CZ14: # | DA14: # | DB14: # | DC14: # | DD14: # | DE14: # | DF14: # | DG14: # | DH14: # | DI14: #
A15: a30_0 | B15: Downs, L.O., et al | C15: prosp. cohort | D15: 44158 | E15: 44205 | F15: United Kingdom | G15: UK; Oxford University Hospital | H15: City | I15: 56660.868 | J15: unclear | K15: # | L15: 8657 | M15: 7567 | N15: =MAX(K15:M15) -> 8657 | O15: Number of people that collected self-tests | P15: # | Q15: # | R15: # | S15: # | T15: # | U15: # | V15: # | W15: # | X15: # | Y15: # | Z15: Healthcare Professionals | AA15: 0 | AB15: 7567 | AC15: 0 | AD15: =IF(AND(AA15=0,AC15=0),1,0) -> 1 | AE15: # | AF15: unclear | AG15: unknown | AH15: # | AI15: # | AJ15: Innova LFD | AK15: no | AL15: AN / MT | AM15: Employer | AN15: Home | AO15: Routine | AP15: 2 | AQ15: =ROUND(('Data extracted'!E15-'Data extracted'!D15)/7,0) -> 7 | AR15: =AQ15*AP15*M15 -> 105938 | AS15: # | AT15: 46503 | AU15: no | AV15: no | AW15: RT-PCR screening of asymptomatic persons | AX15: # | AY15: =SUM(AZ15:BC15) -> 46503 | AZ15: 328 | BA15: 45710 | BB15: 465 | BC15: # | BD15: RT-PCR | BE15: NP / OP | BF15: =SUM(BG15:BJ15) -> 169 | BG15: 161 | BH15: # | BI15: # | BJ15: 8 | BK15: =IFERROR(IF(BJ15<>"#",BJ15+BI15,"#"),"#") -> # | BL15: =SUM(BM15:BP15) -> 295 | BM15: 295 | BN15: # | BO15: # | BP15: # | BQ15: # | BR15: # | BS15: =SUM(BT15:BW15) -> 0 | BT15: # | BU15: # | BV15: # | BW15: # | BX15: =IFERROR(IF(BU15<>"#",BU15+BT15,"#"),"#") -> # | BY15: # | BZ15: # | CA15: # | CB15: Some individuals received confirmatory testing, but unclear by which means it was determined whether individuals would receive confirmatory testing or not | CC15: unclear - some individuals received confirmatory testing, but unclear by which means it was determined whether individuals would receive confirmatory testing or not | CD15: # | CE15: # | CF15: # | CG15: # | CH15: # | CI15: # | CJ15: # | CK15: # | CL15: # | CM15: # | CN15: # | CO15: # | CP15: # | CQ15: # | CR15: # | CS15: # | CT15: # | CU15: # | CV15: # | CW15: # | CX15: # | CY15: # | CZ15: # | DA15: # | DB15: # | DC15: # | DD15: # | DE15: # | DF15: # | DG15: # | DH15: # | DI15: #
A16: a31_0 | B16: Du, Z., et al. | C16: retrospective | D16: 44618 | E16: 44646 | F16: Hong Kong | G16: AS; Individuals across Hong Kong | H16: City | I16: 56843.908 | J16: unclear | K16: # | L16: # | M16: # | N16: # | O16: n/a | P16: # | Q16: # | R16: # | S16: # | T16: # | U16: # | V16: # | W16: # | X16: # | Y16: # | Z16: General population | AA16: # | AB16: # | AC16: # | AD16: =IF(AND(AA16=0,AC16=0),1,0) -> 0 | AE16: # | AF16: # | AG16: unknown | AH16: # | AI16: # | AJ16: Unclear | AK16: # | AL16: # | AM16: # | AN16: Unclear | AO16: Unclear | AP16: # | AQ16: # | AR16: # | AS16: # | AT16: # | AU16: # | AV16: # | AW16: RT-PCR testing and COVID-19 Stringency Index | AX16: # | AY16: # | AZ16: # | BA16: # | BB16: # | BC16: # | BD16: # | BE16: # | BF16: =SUM(BG16:BJ16) -> 0 | BG16: # | BH16: # | BI16: # | BJ16: # | BK16: =IFERROR(IF(BJ16<>"#",BJ16+BI16,"#"),"#") -> # | BL16: =SUM(BM16:BP16) -> 0 | BM16: # | BN16: # | BO16: # | BP16: # | BQ16: # | BR16: # | BS16: =SUM(BT16:BW16) -> 0 | BT16: # | BU16: # | BV16: # | BW16: # | BX16: =IFERROR(IF(BU16<>"#",BU16+BT16,"#"),"#") -> # | BY16: C19ST | BZ16: 30min | CA16: # | CB16: # | CC16: # | CD16: # | CE16: # | CF16: # | CG16: # | CH16: # | CI16: # | CJ16: # | CK16: # | CL16: # | CM16: # | CN16: # | CO16: # | CP16: # | CQ16: # | CR16: # | CS16: ="lower case fatality ratio (CFR), which declined substantially from 0.005 on 25 February to 0.003 on 26 February 2022, when the programme of RAT testing was initiated in Hong Kong on 26 February 2022" -> lower case fatality ratio (CFR), which declined substantially from 0.005 on 25 February to 0.003 on 26 February 2022, when the programme of RAT testing was initiated in Hong Kong on 26 February 2022 | CT16: # | CU16: # | CV16: # | CW16: # | CX16: # | CY16: # | CZ16: # | DA16: # | DB16: # | DC16: # | DD16: # | DE16: # | DF16: # | DG16: # | DH16: # | DI16: #
A17: a32_1 | B17: Engels, G., et al. | C17: prosp. cohort | D17: 44319 | E17: 44400 | F17: Germany | G17: EU; Daycare centers in Wuerzburg, Bavaria | H17: City | I17: 59925.317 | J17: unclear | K17: 836 | L17: 280 | M17: 280 | N17: =MAX(K17:M17) -> 836 | O17: Number of people that reported self-testing results | P17: # | Q17: # | R17: # | S17: # | T17: # | U17: # | V17: # | W17: =94+31 -> 125 | X17: =121+34 -> 155 | Y17: # | Z17: K-12 students and staff | AA17: 0 | AB17: 280 | AC17: 0 | AD17: =IF(AND(AA17=0,AC17=0),1,0) -> 1 | AE17: 37 | AF17: # | AG17: unknown | AH17: # | AI17: 5 | AJ17: AST | AK17: no | AL17: AN / MT | AM17: unclear | AN17: Home | AO17: Routine | AP17: 2 | AQ17: =ROUND(('Data extracted'!E17-'Data extracted'!D17)/7,0) -> 12 | AR17: =AQ17*AP17*M17 -> 6720 | AS17: # | AT17: 2896 | AU17: yes | AV17: no | AW17: saliva (self-sampled) pooled RT-PCR testing | AX17: ANTIBODY testing at the beginning and end of study period | AY17: =SUM(AZ17:BC17) -> 2896 | AZ17: 0 | BA17: 2896 | BB17: 0 | BC17: 0 | BD17: RT-PCR | BE17: # | BF17: =SUM(BG17:BJ17) -> 0 | BG17: # | BH17: # | BI17: # | BJ17: # | BK17: =IFERROR(IF(BJ17<>"#",BJ17+BI17,"#"),"#") -> # | BL17: =SUM(BM17:BP17) -> 280 | BM17: 0 | BN17: 280 | BO17: # | BP17: # | BQ17: Antibodies | BR17: # | BS17: =SUM(BT17:BW17) -> 0 | BT17: # | BU17: 0 | BV17: # | BW17: # | BX17: =IFERROR(IF(BU17<>"#",BU17+BT17,"#"),"#") -> # | BY17: # | BZ17: # | CA17: # | CB17: # | CC17: # | CD17: # | CE17: # | CF17: # | CG17: # | CH17: testing was perceived as uncomfortable by some; testing discomfort causing interactive problems parents-kids | CI17: # | CJ17: # | CK17: # | CL17: # | CM17: # | CN17: # | CO17: # | CP17: # | CQ17: # | CR17: # | CS17: # | CT17: # | CU17: # | CV17: # | CW17: # | CX17: # | CY17: # | CZ17: Insecurity in regards to test accuracy and performing the test correctly; some children were interested in testing, others refused having test performed; felt that C19ST increased sense of safety because of reduced TAT | DA17: # | DB17: # | DC17: # | DD17: Positive acknowledgement of little time required to perform tests | DE17: # | DF17: # | DG17: # | DH17: # | DI17: #
A18: a32_2 | B18: Engels, G., et al. | C18: prosp. cohort | D18: 44319 | E18: 44400 | F18: Germany | G18: EU; Daycare centers in Wuerzburg, Bavaria | H18: City | I18: 59925.317 | J18: unclear | K18: 190 | L18: 110 | M18: 110 | N18: =MAX(K18:M18) -> 190 | O18: Number of people that reported self-testing results | P18: # | Q18: # | R18: # | S18: # | T18: # | U18: # | V18: # | W18: =74+10 -> 84 | X18: =4+2 -> 6 | Y18: # | Z18: K-12 students and staff | AA18: 0 | AB18: 110 | AC18: 0 | AD18: =IF(AND(AA18=0,AC18=0),1,0) -> 1 | AE18: 20 | AF18: # | AG18: unknown | AH18: # | AI18: 3 | AJ18: AST | AK18: no | AL18: AN / MT | AM18: unclear | AN18: Home | AO18: Routine | AP18: 2 | AQ18: =ROUND(('Data extracted'!E18-'Data extracted'!D18)/7,0) -> 12 | AR18: =AQ18*AP18*M18 -> 2640 | AS18: # | AT18: 1022 | AU18: no | AV18: no | AW18: saliva (self-sampled) pooled RT-PCR testing | AX18: # | AY18: =SUM(AZ18:BC18) -> 1022 | AZ18: 0 | BA18: 1022 | BB18: 0 | BC18: 0 | BD18: RT-PCR | BE18: # | BF18: =SUM(BG18:BJ18) -> 0 | BG18: # | BH18: # | BI18: # | BJ18: # | BK18: =IFERROR(IF(BJ18<>"#",BJ18+BI18,"#"),"#") -> # | BL18: =SUM(BM18:BP18) -> 110 | BM18: 0 | BN18: 110 | BO18: # | BP18: # | BQ18: RT-PCR | BR18: # | BS18: =SUM(BT18:BW18) -> 0 | BT18: # | BU18: # | BV18: # | BW18: # | BX18: =IFERROR(IF(BU18<>"#",BU18+BT18,"#"),"#") -> # | BY18: # | BZ18: # | CA18: # | CB18: # | CC18: # | CD18: # | CE18: # | CF18: # | CG18: # | CH18: testing was perceived as uncomfortable by some; testing discomfort causing interactive problems parents-kids | CI18: # | CJ18: # | CK18: # | CL18: # | CM18: # | CN18: # | CO18: # | CP18: # | CQ18: # | CR18: # | CS18: # | CT18: # | CU18: # | CV18: # | CW18: # | CX18: # | CY18: # | CZ18: Insecurity in regards to test accuracy and performing the test correctly; some children were interested in testing, others refused having test performed; felt that C19ST increased sense of safety because of reduced TAT | DA18: # | DB18: # | DC18: # | DD18: Positive acknowledgement of little time required to perform tests | DE18: # | DF18: # | DG18: # | DH18: # | DI18: #
A19: a33_0 | B19: Gorgels, K.M.F., et al. | C19: retrosp. cohort | D19: 44319 | E19: 44661 | F19: Netherlands | G19: EU; All public health services facilities in the Netherlands | H19: unclear | I19: 73173.715 | J19: unclear | K19: # | L19: # | M19: # | N19: 3599894 | O19: Number of people that reported self-testing results | P19: # | Q19: # | R19: # | S19: # | T19: # | U19: # | V19: # | W19: 1863909 | X19: 1734482 | Y19: 1503 | Z19: General population | AA19: 3195409 | AB19: 404485 | AC19: 0 | AD19: =IF(AND(AA19=0,AC19=0),1,0) -> 0 | AE19: # | AF19: # | AG19: unknown | AH19: Booster: 957,443; Fully vaccinated: 888,199; Partly vaccinated: 153,579; Unvaccinated: 1,057,391; Unknown: 543,282 | AI19: # | AJ19: Unclear | AK19: # | AL19: # | AM19: # | AN19: Unclear | AO19: Unclear | AP19: # | AQ19: # | AR19: # | AS19: # | AT19: # | AU19: no | AV19: no | AW19: # | AX19: # | AY19: # | AZ19: # | BA19: # | BB19: # | BC19: # | BD19: # | BE19: # | BF19: =SUM(BG19:BJ19) -> 0 | BG19: # | BH19: # | BI19: # | BJ19: # | BK19: =IFERROR(IF(BJ19<>"#",BJ19+BI19,"#"),"#") -> # | BL19: =SUM(BM19:BP19) -> 3599894 | BM19: 3599894 | BN19: # | BO19: # | BP19: # | BQ19: RT-PCR | BR19: # | BS19: =SUM(BT19:BW19) -> 3599894 | BT19: 3291877 | BU19: # | BV19: # | BW19: 308017 | BX19: =IFERROR(IF(BU19<>"#",BU19+BT19,"#"),"#") -> # | BY19: RT-PCR | BZ19: # | CA19: # | CB19: Follow national COVID-19 guideline, i.e., perform an RT-PCR for confirmatory testing | CC19: compulsory (by goverment guidance) | CD19: # | CE19: # | CF19: # | CG19: # | CH19: # | CI19: # | CJ19: # | CK19: # | CL19: # | CM19: # | CN19: # | CO19: # | CP19: # | CQ19: # | CR19: # | CS19: # | CT19: # | CU19: # | CV19: # | CW19: # | CX19: # | CY19: Unnecessary social isolation if false-positive | CZ19: Unnecessary social isolation if false-positive | DA19: # | DB19: # | DC19: # | DD19: # | DE19: # | DF19: # | DG19: # | DH19: # | DI19: #
A20: a34_0 | B20: Harmon, A., et al. | C20: prosp. cohort | D20: # | E20: # | F20: United States | G20: NA; Affiliates of co-working laboratories in Boston + Cambridge, MA | H20: City | I20: 89598.86 | J20: unclear | K20: # | L20: # | M20: 257 | N20: =MAX(K20:M20) -> 257 | O20: Number of people that reported self-testing results | P20: # | Q20: # | R20: 35 | S20: # | T20: # | U20: 21 | V20: 72 | W20: 120 | X20: # | Y20: 137 | Z20: General population | AA20: # | AB20: # | AC20: # | AD20: =IF(AND(AA20=0,AC20=0),1,0) -> 0 | AE20: # | AF20: # | AG20: unknown | AH20: # | AI20: # | AJ20: E25Bio | AK20: # | AL20: AN / MT | AM20: Study | AN20: Home | AO20: Routine | AP20: 2 | AQ20: # | AR20: # | AS20: # | AT20: 2951 | AU20: no | AV20: no | AW20: RT-PCR for every specimen | AX20: CONTINUE | AY20: =SUM(AZ20:BA20) -> 2951 | AZ20: 144 | BA20: 2807 | BB20: # | BC20: # | BD20: RT-PCR | BE20: AN / MT | BF20: =SUM(BG20:BJ20) -> 2951 | BG20: 60 | BH20: 16 | BI20: 2791 | BJ20: 84 | BK20: =IFERROR(IF(BJ20<>"#",BJ20+BI20,"#"),"#") -> 2875 | BL20: 257 | BM20: 15 | BN20: 242 | BO20: # | BP20: # | BQ20: RT-PCR | BR20: AN / MT | BS20: =SUM(BT20:BW20) -> 257 | BT20: 15 | BU20: 0 | BV20: 242 | BW20: 0 | BX20: =IFERROR(IF(BU20<>"#",BU20+BT20,"#"),"#") -> 15 | BY20: RT-PCR | BZ20: # | CA20: 30 min. | CB20: Confirm result through RT-PCR or professional Ag-RDT; do not go to school | CC20: compulsory (by study design) | CD20: Continue work and routine testing | CE20: # | CF20: # | CG20: # | CH20: # | CI20: # | CJ20: # | CK20: # | CL20: # | CM20: # | CN20: # | CO20: # | CP20: # | CQ20: # | CR20: # | CS20: # | CT20: # | CU20: # | CV20: # | CW20: # | CX20: allowed work activities to continue safely | CY20: # | CZ20: # | DA20: # | DB20: # | DC20: # | DD20: # | DE20: include | DF20: include | DG20: # | DH20: # | DI20: #
A21: a35_1 | B21: Herbert, C., et al. (a) | C21: prosp. cohort | D21: 44423 | E21: 44607 | F21: United States | G21: NA; Individuals across Michigan (1st part of study) and the entire US (2nd part) | H21: unclear | I21: 89598.86 | J21: unclear | K21: # | L21: 1083 | M21: 1016 | N21: =MAX(K21:M21) -> 1083 | O21: Number of people eligible for self-testing | P21: # | Q21: # | R21: # | S21: # | T21: # | U21: # | V21: # | W21: # | X21: # | Y21: # | Z21: General population | AA21: 102 | AB21: 981 | AC21: 0 | AD21: =IF(AND(AA21=0,AC21=0),1,0) -> 0 | AE21: # | AF21: 262 people had close contact with a SARS-CoV-2 case | AG21: unknown | AH21: # | AI21: # | AJ21: QuickVue | AK21: no | AL21: AN / MT | AM21: Study | AN21: Home | AO21: Routine | AP21: 2 | AQ21: 12 | AR21: =AQ21*AP21*622 -> 14928 | AS21: # | AT21: 6580 | AU21: no | AV21: no | AW21: Weekly surveillance questionnaire, RT-PCR in case of two ro more sympoms or exposure | AX21: CONTINUE | AY21: # | AZ21: # | BA21: # | BB21: # | BC21: # | BD21: # | BE21: # | BF21: =SUM(BG21:BJ21) -> 0 | BG21: # | BH21: # | BI21: # | BJ21: # | BK21: =IFERROR(IF(BJ21<>"#",BJ21+BI21,"#"),"#") -> # | BL21: =SUM(BM21:BP21) -> 76 | BM21: =ROUND(1016*0.075,0) -> 76 | BN21: # | BO21: # | BP21: # | BQ21: # | BR21: # | BS21: =SUM(BT21:BW21) -> 0 | BT21: # | BU21: # | BV21: # | BW21: # | BX21: =IFERROR(IF(BU21<>"#",BU21+BT21,"#"),"#") -> # | BY21: # | BZ21: # | CA21: 10 min. | CB21: Upload image of test strip; repeat antigen test on the same day or after 1 day; perform confirmatory test using at-home RT-PCR collection kit; care directed by participant's primary or urgent care provider | CC21: compulsory (by study design) | CD21: continue to test twice-weekly until end of 12-week period | CE21: # | CF21: # | CG21: # | CH21: # | CI21: # | CJ21: # | CK21: # | CL21: # | CM21: # | CN21: # | CO21: # | CP21: # | CQ21: # | CR21: # | CS21: # | CT21: # | CU21: # | CV21: # | CW21: # | CX21: # | CY21: # | CZ21: # | DA21: # | DB21: # | DC21: # | DD21: # | DE21: # | DF21: # | DG21: # | DH21: # | DI21: #
A22: a35_2 | B22: Herbert, C., et al. (a) | C22: prosp. cohort | D22: 44423 | E22: 44607 | F22: United States | G22: NA; Individuals across Michigan (1st part of study) and the entire US (2nd part) | H22: unclear | I22: 89598.86 | J22: unclear | K22: # | L22: # | M22: 801 | N22: =MAX(K22:M22) -> 801 | O22: Number of people eligible for self-testing | P22: # | Q22: # | R22: # | S22: # | T22: # | U22: # | V22: # | W22: # | X22: # | Y22: # | Z22: General population | AA22: # | AB22: # | AC22: # | AD22: =IF(AND(AA22=0,AC22=0),1,0) -> 0 | AE22: # | AF22: # | AG22: unknown | AH22: # | AI22: # | AJ22: QuickVue | AK22: no | AL22: AN / MT | AM22: Study | AN22: Home | AO22: Routine | AP22: 2 | AQ22: 2 | AR22: # | AS22: # | AT22: # | AU22: no | AV22: no | AW22: Weekly surveillance questionnaire | AX22: # | AY22: # | AZ22: # | BA22: # | BB22: # | BC22: # | BD22: # | BE22: # | BF22: =SUM(BG22:BJ22) -> 0 | BG22: # | BH22: # | BI22: # | BJ22: # | BK22: =IFERROR(IF(BJ22<>"#",BJ22+BI22,"#"),"#") -> # | BL22: =SUM(BM22:BP22) -> 0 | BM22: # | BN22: # | BO22: # | BP22: # | BQ22: # | BR22: # | BS22: =SUM(BT22:BW22) -> 0 | BT22: # | BU22: # | BV22: # | BW22: # | BX22: =IFERROR(IF(BU22<>"#",BU22+BT22,"#"),"#") -> # | BY22: # | BZ22: # | CA22: 10 min. | CB22: Upload image of test strip; repeat antigen test on the same day or after 1 day; perform confirmatory test using at-home RT-PCR collection kit; care directed by participant's primary or urgent care provider | CC22: compulsory (by study design) | CD22: continue to test twice-weekly until end of 2-week period, then continue weekly symptom survey | CE22: # | CF22: # | CG22: # | CH22: # | CI22: # | CJ22: # | CK22: # | CL22: # | CM22: # | CN22: # | CO22: # | CP22: # | CQ22: # | CR22: # | CS22: # | CT22: # | CU22: # | CV22: # | CW22: # | CX22: # | CY22: # | CZ22: # | DA22: # | DB22: # | DC22: # | DD22: # | DE22: # | DF22: # | DG22: # | DH22: # | DI22: #
A23: a36_1 | B23: Herbert, C., et al. (b) | C23: prosp. cohort | D23: 44287 | E23: 44399 | F23: United States | G23: NA; Individuals across Chattanooga, Tennessee | H23: City | I23: 89598.86 | J23: free | K23: # | L23: # | M23: 1366 | N23: =MAX(K23:M23) -> 1366 | O23: Number of people that reported self-testing results | P23: # | Q23: # | R23: # | S23: # | T23: # | U23: # | V23: # | W23: # | X23: # | Y23: # | Z23: General population | AA23: # | AB23: # | AC23: # | AD23: =IF(AND(AA23=0,AC23=0),1,0) -> 0 | AE23: # | AF23: # | AG23: unknown | AH23: # | AI23: # | AJ23: Unclear | AK23: no | AL23: # | AM23: Study | AN23: Home | AO23: Unclear | AP23: # | AQ23: # | AR23: 2722 | AS23: # | AT23: 1900 | AU23: no | AV23: no | AW23: # | AX23: # | AY23: # | AZ23: # | BA23: # | BB23: # | BC23: # | BD23: # | BE23: # | BF23: =SUM(BG23:BJ23) -> 0 | BG23: # | BH23: # | BI23: # | BJ23: # | BK23: =IFERROR(IF(BJ23<>"#",BJ23+BI23,"#"),"#") -> # | BL23: =SUM(BM23:BP23) -> 0 | BM23: # | BN23: # | BO23: # | BP23: # | BQ23: # | BR23: # | BS23: =SUM(BT23:BW23) -> 0 | BT23: # | BU23: # | BV23: # | BW23: # | BX23: =IFERROR(IF(BU23<>"#",BU23+BT23,"#"),"#") -> # | BY23: # | BZ23: # | CA23: # | CB23: # | CC23: # | CD23: # | CE23: # | CF23: # | CG23: # | CH23: # | CI23: # | CJ23: # | CK23: # | CL23: # | CM23: # | CN23: # | CO23: # | CP23: # | CQ23: # | CR23: # | CS23: # | CT23: # | CU23: # | CV23: # | CW23: # | CX23: # | CY23: # | CZ23: # | DA23: # | DB23: # | DC23: # | DD23: # | DE23: # | DF23: # | DG23: # | DH23: # | DI23: #
A24: a36_2 | B24: Herbert, C., et al. (b) | C24: prosp. cohort | D24: 44459 | E24: 44501 | F24: United States | G24: NA; Individuals across Fulton County, Georgia | H24: City; semi-dense | I24: 89598.86 | J24: free | K24: # | L24: # | M24: 2012 | N24: =MAX(K24:M24) -> 2012 | O24: Number of people that reported self-testing results | P24: # | Q24: # | R24: # | S24: # | T24: # | U24: # | V24: # | W24: # | X24: # | Y24: # | Z24: General population | AA24: # | AB24: # | AC24: # | AD24: =IF(AND(AA24=0,AC24=0),1,0) -> 0 | AE24: # | AF24: # | AG24: unknown | AH24: # | AI24: # | AJ24: Unclear | AK24: no | AL24: # | AM24: Study | AN24: Home | AO24: Unclear | AP24: # | AQ24: # | AR24: 4763 | AS24: # | AT24: 3742 | AU24: no | AV24: no | AW24: # | AX24: # | AY24: # | AZ24: # | BA24: # | BB24: # | BC24: # | BD24: # | BE24: # | BF24: =SUM(BG24:BJ24) -> 0 | BG24: # | BH24: # | BI24: # | BJ24: # | BK24: =IFERROR(IF(BJ24<>"#",BJ24+BI24,"#"),"#") -> # | BL24: =SUM(BM24:BP24) -> 0 | BM24: # | BN24: # | BO24: # | BP24: # | BQ24: # | BR24: # | BS24: =SUM(BT24:BW24) -> 0 | BT24: # | BU24: # | BV24: # | BW24: # | BX24: =IFERROR(IF(BU24<>"#",BU24+BT24,"#"),"#") -> # | BY24: # | BZ24: # | CA24: # | CB24: # | CC24: # | CD24: # | CE24: # | CF24: # | CG24: # | CH24: # | CI24: # | CJ24: # | CK24: # | CL24: # | CM24: # | CN24: # | CO24: # | CP24: # | CQ24: # | CR24: # | CS24: # | CT24: # | CU24: # | CV24: # | CW24: # | CX24: # | CY24: # | CZ24: # | DA24: # | DB24: # | DC24: # | DD24: # | DE24: # | DF24: # | DG24: # | DH24: # | DI24: #
A25: a36_3 | B25: Herbert, C., et al. (b) | C25: prosp. cohort | D25: 44458 | E25: 44468 | F25: United States | G25: NA; Individuals across O’ahu, Hawaii | H25: City; semi-dense | I25: 89598.86 | J25: free | K25: # | L25: # | M25: 5007 | N25: =MAX(K25:M25) -> 5007 | O25: Number of people that reported self-testing results | P25: # | Q25: # | R25: # | S25: # | T25: # | U25: # | V25: # | W25: # | X25: # | Y25: # | Z25: General population | AA25: # | AB25: # | AC25: # | AD25: =IF(AND(AA25=0,AC25=0),1,0) -> 0 | AE25: # | AF25: # | AG25: unknown | AH25: # | AI25: # | AJ25: Unclear | AK25: no | AL25: # | AM25: Study | AN25: Home | AO25: Unclear | AP25: # | AQ25: # | AR25: 17140 | AS25: # | AT25: 11154 | AU25: no | AV25: no | AW25: # | AX25: # | AY25: # | AZ25: # | BA25: # | BB25: # | BC25: # | BD25: # | BE25: # | BF25: =SUM(BG25:BJ25) -> 0 | BG25: # | BH25: # | BI25: # | BJ25: # | BK25: =IFERROR(IF(BJ25<>"#",BJ25+BI25,"#"),"#") -> # | BL25: =SUM(BM25:BP25) -> 0 | BM25: # | BN25: # | BO25: # | BP25: # | BQ25: # | BR25: # | BS25: =SUM(BT25:BW25) -> 0 | BT25: # | BU25: # | BV25: # | BW25: # | BX25: =IFERROR(IF(BU25<>"#",BU25+BT25,"#"),"#") -> # | BY25: # | BZ25: # | CA25: # | CB25: # | CC25: # | CD25: # | CE25: # | CF25: # | CG25: # | CH25: # | CI25: # | CJ25: # | CK25: # | CL25: # | CM25: # | CN25: # | CO25: # | CP25: # | CQ25: # | CR25: # | CS25: # | CT25: # | CU25: # | CV25: # | CW25: # | CX25: # | CY25: # | CZ25: # | DA25: # | DB25: # | DC25: # | DD25: # | DE25: # | DF25: # | DG25: # | DH25: # | DI25: #
A26: a36_4 | B26: Herbert, C., et al. (b) | C26: prosp. cohort | D26: 44487 | E26: 44520 | F26: United States | G26: NA; Individuals across Indianapolis, Indiana | H26: City | I26: 89598.86 | J26: free | K26: # | L26: # | M26: 1856 | N26: =MAX(K26:M26) -> 1856 | O26: Number of people that reported self-testing results | P26: # | Q26: # | R26: # | S26: # | T26: # | U26: # | V26: # | W26: # | X26: # | Y26: # | Z26: General population | AA26: # | AB26: # | AC26: # | AD26: =IF(AND(AA26=0,AC26=0),1,0) -> 0 | AE26: # | AF26: # | AG26: unknown | AH26: # | AI26: # | AJ26: Unclear | AK26: no | AL26: # | AM26: Study | AN26: Home | AO26: Unclear | AP26: # | AQ26: # | AR26: 5724 | AS26: # | AT26: 5199 | AU26: no | AV26: no | AW26: # | AX26: # | AY26: # | AZ26: # | BA26: # | BB26: # | BC26: # | BD26: # | BE26: # | BF26: =SUM(BG26:BJ26) -> 0 | BG26: # | BH26: # | BI26: # | BJ26: # | BK26: =IFERROR(IF(BJ26<>"#",BJ26+BI26,"#"),"#") -> # | BL26: =SUM(BM26:BP26) -> 0 | BM26: # | BN26: # | BO26: # | BP26: # | BQ26: # | BR26: # | BS26: =SUM(BT26:BW26) -> 0 | BT26: # | BU26: # | BV26: # | BW26: # | BX26: =IFERROR(IF(BU26<>"#",BU26+BT26,"#"),"#") -> # | BY26: # | BZ26: # | CA26: # | CB26: # | CC26: # | CD26: # | CE26: # | CF26: # | CG26: # | CH26: # | CI26: # | CJ26: # | CK26: # | CL26: # | CM26: # | CN26: # | CO26: # | CP26: # | CQ26: # | CR26: # | CS26: # | CT26: # | CU26: # | CV26: # | CW26: # | CX26: # | CY26: # | CZ26: # | DA26: # | DB26: # | DC26: # | DD26: # | DE26: # | DF26: # | DG26: # | DH26: # | DI26: #
A27: a36_5 | B27: Herbert, C., et al. (b) | C27: prosp. cohort | D27: 44480 | E27: 44513 | F27: United States | G27: NA; Individuals across Louisville, Kentucky | H27: City | I27: 89598.86 | J27: free | K27: # | L27: # | M27: 954 | N27: =MAX(K27:M27) -> 954 | O27: Number of people that reported self-testing results | P27: # | Q27: # | R27: # | S27: # | T27: # | U27: # | V27: # | W27: # | X27: # | Y27: # | Z27: General population | AA27: # | AB27: # | AC27: # | AD27: =IF(AND(AA27=0,AC27=0),1,0) -> 0 | AE27: # | AF27: # | AG27: unknown | AH27: # | AI27: # | AJ27: Unclear | AK27: no | AL27: # | AM27: Study | AN27: Home | AO27: Unclear | AP27: # | AQ27: # | AR27: 2918 | AS27: # | AT27: 2626 | AU27: no | AV27: no | AW27: # | AX27: # | AY27: # | AZ27: # | BA27: # | BB27: # | BC27: # | BD27: # | BE27: # | BF27: =SUM(BG27:BJ27) -> 0 | BG27: # | BH27: # | BI27: # | BJ27: # | BK27: =IFERROR(IF(BJ27<>"#",BJ27+BI27,"#"),"#") -> # | BL27: =SUM(BM27:BP27) -> 0 | BM27: # | BN27: # | BO27: # | BP27: # | BQ27: # | BR27: # | BS27: =SUM(BT27:BW27) -> 0 | BT27: # | BU27: # | BV27: # | BW27: # | BX27: =IFERROR(IF(BU27<>"#",BU27+BT27,"#"),"#") -> # | BY27: # | BZ27: # | CA27: # | CB27: # | CC27: # | CD27: # | CE27: # | CF27: # | CG27: # | CH27: # | CI27: # | CJ27: # | CK27: # | CL27: # | CM27: # | CN27: # | CO27: # | CP27: # | CQ27: # | CR27: # | CS27: # | CT27: # | CU27: # | CV27: # | CW27: # | CX27: # | CY27: # | CZ27: # | DA27: # | DB27: # | DC27: # | DD27: # | DE27: # | DF27: # | DG27: # | DH27: # | DI27: #
A28: a37_1 | B28: Hirst, J.A., et al. | C28: prosp. cohort | D28: 44133 | E28: 44214 | F28: United Kingdom | G28: UK; University of Oxford | H28: City | I28: 56660.868 | J28: unclear | K28: 2132 | L28: 664 | M28: 551 | N28: =MAX(K28:M28) -> 2132 | O28: Number of people eligible for self-testing | P28: 29.3 | Q28: 10.7 | R28: # | S28: # | T28: # | U28: # | V28: # | W28: # | X28: 244 | Y28: # | Z28: University students and staff | AA28: 17 | AB28: 534 | AC28: 0 | AD28: =IF(AND(AA28=0,AC28=0),1,0) -> 0 | AE28: # | AF28: # | AG28: unknown | AH28: # | AI28: # | AJ28: Innova LFD | AK28: no | AL28: # | AM28: University | AN28: Home / Testing Site | AO28: Routine | AP28: Unclear | AQ28: # | AR28: # | AS28: # | AT28: 2731 | AU28: no | AV28: unclear | AW28: App-based, daily symptom tracking; self-isolation and RT-PCR in case of symptoms | AX28: Unclear | AY28: =SUM(AZ28:BC28) -> 2731 | AZ28: 9 | BA28: 2711 | BB28: 8 | BC28: 3 | BD28: # | BE28: # | BF28: =SUM(BG28:BJ28) -> 0 | BG28: # | BH28: # | BI28: # | BJ28: # | BK28: =IFERROR(IF(BJ28<>"#",BJ28+BI28,"#"),"#") -> # | BL28: =SUM(BM28:BP28) -> 8 | BM28: 8 | BN28: # | BO28: # | BP28: # | BQ28: # | BR28: # | BS28: =SUM(BT28:BW28) -> 10 | BT28: 3 | BU28: 5 | BV28: # | BW28: 2 | BX28: =IFERROR(IF(BU28<>"#",BU28+BT28,"#"),"#") -> 8 | BY28: RT-PCR | BZ28: # | CA28: 30min | CB28: PCR confirmatory testing, self-isolate | CC28: compulsory (by study design) | CD28: continue to follow COVID-19 rules | CE28: # | CF28: # | CG28: # | CH28: # | CI28: # | CJ28: # | CK28: # | CL28: # | CM28: # | CN28: # | CO28: # | CP28: # | CQ28: # | CR28: # | CS28: # | CT28: # | CU28: # | CV28: # | CW28: # | CX28: # | CY28: # | CZ28: # | DA28: # | DB28: # | DC28: # | DD28: # | DE28: # | DF28: # | DG28: # | DH28: # | DI28: #
A29: a37_2 | B29: Hirst, J.A., et al. | C29: prosp. cohort | D29: 44133 | E29: 44214 | F29: United Kingdom | G29: UK; University of Oxford | H29: City | I29: 56660.868 | J29: unclear | K29: # | L29: # | M29: 183 | N29: =MAX(K29:M29) -> 183 | O29: Number of people that reported self-testing results | P29: 27.5 | Q29: 10.7 | R29: # | S29: # | T29: # | U29: # | V29: # | W29: # | X29: 83 | Y29: # | Z29: University students and staff | AA29: 0 | AB29: 0 | AC29: 183 | AD29: =IF(AND(AA29=0,AC29=0),1,0) -> 0 | AE29: # | AF29: # | AG29: unknown | AH29: # | AI29: # | AJ29: Innova LFD | AK29: no | AL29: # | AM29: University | AN29: Home / Testing Site | AO29: Routine | AP29: Unclear | AQ29: # | AR29: # | AS29: # | AT29: 459 | AU29: no | AV29: unclear | AW29: App-based, daily symptom tracking; self-isolation and RT-PCR in case of symptoms | AX29: # | AY29: =SUM(AZ29:BC29) -> 459 | AZ29: 0 | BA29: 459 | BB29: 0 | BC29: 0 | BD29: # | BE29: # | BF29: =SUM(BG29:BJ29) -> 0 | BG29: # | BH29: # | BI29: # | BJ29: # | BK29: =IFERROR(IF(BJ29<>"#",BJ29+BI29,"#"),"#") -> # | BL29: =SUM(BM29:BP29) -> 183 | BM29: # | BN29: 183 | BO29: # | BP29: # | BQ29: # | BR29: # | BS29: =SUM(BT29:BW29) -> 0 | BT29: # | BU29: # | BV29: # | BW29: # | BX29: =IFERROR(IF(BU29<>"#",BU29+BT29,"#"),"#") -> # | BY29: RT-PCR | BZ29: # | CA29: 30min | CB29: PCR confirmatory testing, self-isolate | CC29: compulsory (by study design) | CD29: continue to follow COVID-19 rules | CE29: # | CF29: # | CG29: # | CH29: # | CI29: # | CJ29: # | CK29: # | CL29: # | CM29: # | CN29: # | CO29: # | CP29: # | CQ29: # | CR29: # | CS29: # | CT29: # | CU29: # | CV29: # | CW29: # | CX29: # | CY29: # | CZ29: # | DA29: # | DB29: # | DC29: # | DD29: # | DE29: # | DF29: # | DG29: # | DH29: # | DI29: #
A30: a38_0 | B30: Hoehl, S., et al. | C30: prosp. cohort | D30: # | E30: # | F30: Germany | G30: EU; Teachers across the state Hesse | H30: unclear | I30: 59925.317 | J30: unclear | K30: # | L30: 711 | M30: 635 | N30: =MAX(K30:M30) -> 711 | O30: Number of people invited to self-test | P30: # | Q30: # | R30: # | S30: # | T30: # | U30: # | V30: # | W30: # | X30: # | Y30: # | Z30: K-12 students and staff | AA30: 10 | AB30: 14 | AC30: 611 | AD30: =IF(AND(AA30=0,AC30=0),1,0) -> 0 | AE30: # | AF30: # | AG30: unknown | AH30: not vaccinated | AI30: # | AJ30: R-Biopharm | AK30: no | AL30: AN / MT | AM30: unclear | AN30: Home | AO30: Routine | AP30: =24/7 -> 3.4285714 | AQ30: 7 | AR30: =AQ30*AP30*M30 -> 15240 | AS30: # | AT30: 11385 | AU30: no | AV30: no | AW30: # | AX30: STOPP self-testing after positive RT-PCR | AY30: =SUM(AZ30:BC30) -> 11385 | AZ30: 21 | BA30: 11315 | BB30: 49 | BC30: # | BD30: RT-PCR | BE30: # | BF30: =SUM(BG30:BJ30) -> 21 | BG30: 5 | BH30: # | BI30: # | BJ30: 16 | BK30: =IFERROR(IF(BJ30<>"#",BJ30+BI30,"#"),"#") -> # | BL30: =SUM(BM30:BP30) -> 0 | BM30: # | BN30: # | BO30: # | BP30: # | BQ30: RT-PCR | BR30: # | BS30: =SUM(BT30:BW30) -> 4 | BT30: # | BU30: 4 | BV30: # | BW30: # | BX30: =IFERROR(IF(BU30<>"#",BU30+BT30,"#"),"#") -> # | BY30: # | BZ30: # | CA30: # | CB30: # | CC30: # | CD30: # | CE30: # | CF30: # | CG30: # | CH30: # | CI30: # | CJ30: # | CK30: 11.75-275.56 per week | CL30: # | CM30: # | CN30: # | CO30: # | CP30: # | CQ30: # | CR30: # | CS30: # | CT30: # | CU30: # | CV30: # | CW30: # | CX30: # | CY30: # | CZ30: # | DA30: # | DB30: # | DC30: # | DD30: # | DE30: # | DF30: # | DG30: # | DH30: # | DI30: #
A31: a39_0 | B31: Hogg, C., et al. | C31: retrosp. cohort | D31: 44317 | E31: 44439 | F31: United Kingdom | G31: UK; Staff members of care homes across Wales | H31: unclear | I31: 56660.868 | J31: unclear | K31: # | L31: # | M31: # | N31: # | O31: n/a | P31: # | Q31: # | R31: # | S31: # | T31: # | U31: # | V31: # | W31: # | X31: # | Y31: # | Z31: Healthcare Professionals | AA31: # | AB31: # | AC31: # | AD31: =IF(AND(AA31=0,AC31=0),1,0) -> 0 | AE31: # | AF31: # | AG31: unknown | AH31: # | AI31: # | AJ31: Innova LFD | AK31: no | AL31: Combined AN / OP | AM31: # | AN31: Unclear | AO31: Routine | AP31: Unclear | AQ31: =ROUND(('Data extracted'!E31-'Data extracted'!D31)/7,0) -> 17 | AR31: # | AS31: # | AT31: 115593 | AU31: no | AV31: no | AW31: weekly RT-PCR; routine surveillance and management of COVID-19 in care homes in Wales (UK) | AX31: CONTINUE | AY31: =SUM(AZ31:BA31) -> 115593 | AZ31: 229 | BA31: 115364 | BB31: 0 | BC31: 0 | BD31: RT-PCR | BE31: Combined nose and throat swabs or dry throat swabs | BF31: =SUM(BG31:BJ31) -> 115593 | BG31: 128 | BH31: 371 | BI31: 114993 | BJ31: 101 | BK31: =IFERROR(IF(BJ31<>"#",BJ31+BI31,"#"),"#") -> 115094 | BL31: =SUM(BM31:BP31) -> 0 | BM31: # | BN31: # | BO31: # | BP31: # | BQ31: # | BR31: # | BS31: =SUM(BT31:BW31) -> 0 | BT31: # | BU31: # | BV31: # | BW31: # | BX31: =IFERROR(IF(BU31<>"#",BU31+BT31,"#"),"#") -> # | BY31: RT-PCR | BZ31: # | CA31: 30 min. | CB31: # | CC31: # | CD31: Continue work | CE31: # | CF31: # | CG31: # | CH31: # | CI31: # | CJ31: # | CK31: # | CL31: # | CM31: # | CN31: # | CO31: # | CP31: # | CQ31: # | CR31: # | CS31: # | CT31: # | CU31: # | CV31: # | CW31: # | CX31: # | CY31: # | CZ31: # | DA31: # | DB31: # | DC31: # | DD31: # | DE31: include | DF31: # | DG31: # | DH31: # | DI31: #
A32: a40_0 | B32: Hu, Y., et al. | C32: prosp. cohort | D32: 44876 | E32: 44893 | F32: China | G32: AS; Residents of the Chongqing Medical University campus | H32: City | I32: 13806.031 | J32: unclear | K32: 17655 | L32: 17655 | M32: 17655 | N32: =MAX(K32:M32) -> 17655 | O32: Number of people eligible for self-testing | P32: # | Q32: # | R32: # | S32: # | T32: # | U32: # | V32: # | W32: # | X32: # | Y32: # | Z32: Unclear | AA32: # | AB32: # | AC32: # | AD32: =IF(AND(AA32=0,AC32=0),1,0) -> 0 | AE32: # | AF32: # | AG32: unknown | AH32: # | AI32: # | AJ32: M&D Covid-19 Antigen Rapid Test, Chongqing M&D Biotechnology, Chongqing, China | AK32: # | AL32: # | AM32: # | AN32: Home | AO32: Routine | AP32: 21 | AQ32: =ROUND(('Data extracted'!E32-'Data extracted'!D32)/7,0) -> 2 | AR32: =AQ32*AP32*M32 -> 741510 | AS32: # | AT32: # | AU32: no | AV32: no | AW32: Daily RT-PCR testing, self-isolation | AX32: CONTINUE | AY32: # | AZ32: # | BA32: # | BB32: # | BC32: # | BD32: # | BE32: # | BF32: =SUM(BG32:BJ32) -> 0 | BG32: # | BH32: # | BI32: # | BJ32: # | BK32: =IFERROR(IF(BJ32<>"#",BJ32+BI32,"#"),"#") -> # | BL32: =SUM(BM32:BP32) -> 17655 | BM32: 26 | BN32: 17629 | BO32: # | BP32: # | BQ32: RT-PCR | BR32: # | BS32: =SUM(BT32:BW32) -> 17655 | BT32: 26 | BU32: 0 | BV32: 17629 | BW32: 0 | BX32: =IFERROR(IF(BU32<>"#",BU32+BT32,"#"),"#") -> 26 | BY32: # | BZ32: "Among the 26 cases, 16 (61.5%) had positive RT-PCR results on average 3.81 h (SD: 3.33) before testing positive by Ag- RDT; four had positive Ag-RDT results while awaiting their RT-PCR results after having their sample collected, while six cases (23.1%) had positive Ag-RDT results before positive RT-PCR results. The mean time for having positive Ag-RDT results prior to positive RT-PCR results was 13.32 h (SD: 8.35)" | CA32: # | CB32: # | CC32: # | CD32: # | CE32: # | CF32: # | CG32: # | CH32: # | CI32: # | CJ32: # | CK32: # | CL32: # | CM32: # | CN32: # | CO32: # | CP32: # | CQ32: # | CR32: # | CS32: # | CT32: # | CU32: # | CV32: # | CW32: # | CX32: # | CY32: # | CZ32: # | DA32: # | DB32: # | DC32: # | DD32: # | DE32: # | DF32: include | DG32: include | DH32: include | DI32: #
A33: a41_1 | B33: Iftner, T., et al. | C33: prosp. cohort | D33: 44328 | E33: 44397 | F33: Germany | G33: EU; Employees of the University Hospital Thüringen | H33: City | I33: 59925.317 | J33: unclear | K33: # | L33: 1015 | M33: =1015-68 -> 947 | N33: =MAX(K33:M33) -> 1015 | O33: Number of people that collected self-tests | P33: # | Q33: # | R33: # | S33: # | T33: # | U33: # | V33: # | W33: # | X33: # | Y33: # | Z33: Healthcare Professionals | AA33: 0 | AB33: 1015 | AC33: 0 | AD33: =IF(AND(AA33=0,AC33=0),1,0) -> 1 | AE33: # | AF33: # | AG33: unknown | AH33: # | AI33: # | AJ33: Teda Laukoetter Technologie GmbH “COVID-19 Antigen Rapid Test (colloidal gold) ANBIO Corona Antigen Nasal Swab“ | AK33: no | AL33: AN / MT | AM33: # | AN33: Home | AO33: Single | AP33: # | AQ33: # | AR33: 505 | AS33: # | AT33: 468 | AU33: no | AV33: no | AW33: RT-PCR testing | AX33: # | AY33: =SUM(AZ33:BC33) -> 468 | AZ33: 1 | BA33: 462 | BB33: 5 | BC33: # | BD33: RT-PCR | BE33: OP | BF33: =SUM(BG33:BJ33) -> 463 | BG33: 0 | BH33: 0 | BI33: 462 | BJ33: 1 | BK33: =IFERROR(IF(BJ33<>"#",BJ33+BI33,"#"),"#") -> 463 | BL33: =SUM(BM33:BP33) -> 0 | BM33: # | BN33: # | BO33: # | BP33: # | BQ33: # | BR33: # | BS33: =SUM(BT33:BW33) -> 0 | BT33: # | BU33: # | BV33: # | BW33: # | BX33: =IFERROR(IF(BU33<>"#",BU33+BT33,"#"),"#") -> # | BY33: # | BZ33: # | CA33: # | CB33: # | CC33: # | CD33: # | CE33: # | CF33: # | CG33: # | CH33: # | CI33: # | CJ33: # | CK33: # | CL33: # | CM33: # | CN33: # | CO33: # | CP33: # | CQ33: # | CR33: # | CS33: # | CT33: # | CU33: # | CV33: # | CW33: # | CX33: # | CY33: # | CZ33: # | DA33: # | DB33: # | DC33: # | DD33: # | DE33: include | DF33: # | DG33: # | DH33: # | DI33: #
A34: a41_2 | B34: Iftner, T., et al. | C34: prosp. cohort | D34: 44328 | E34: 44397 | F34: Germany | G34: EU; Employees of the University Hospital Thüringen | H34: City | I34: 59925.317 | J34: unclear | K34: # | L34: # | M34: # | N34: # | O34: Number of people that collected self-tests | P34: # | Q34: # | R34: # | S34: # | T34: # | U34: # | V34: # | W34: # | X34: # | Y34: # | Z34: Healthcare Professionals | AA34: # | AB34: # | AC34: # | AD34: =IF(AND(AA34=0,AC34=0),1,0) -> 0 | AE34: # | AF34: # | AG34: unknown | AH34: # | AI34: # | AJ34: Hangzhou Clongene Biotech Co., Ltd. “COVID-19 Antigen Rapid Test” | AK34: no | AL34: AN / MT | AM34: # | AN34: Home | AO34: Single | AP34: # | AQ34: # | AR34: 512 | AS34: # | AT34: 479 | AU34: no | AV34: no | AW34: RT-PCR testing | AX34: # | AY34: =SUM(AZ34:BC34) -> 479 | AZ34: 10 | BA34: 466 | BB34: 3 | BC34: # | BD34: RT-PCR | BE34: OP | BF34: =SUM(BG34:BJ34) -> 476 | BG34: 0 | BH34: 0 | BI34: 466 | BJ34: 10 | BK34: =IFERROR(IF(BJ34<>"#",BJ34+BI34,"#"),"#") -> 476 | BL34: =SUM(BM34:BP34) -> 0 | BM34: # | BN34: # | BO34: # | BP34: # | BQ34: # | BR34: # | BS34: =SUM(BT34:BW34) -> 0 | BT34: # | BU34: # | BV34: # | BW34: # | BX34: =IFERROR(IF(BU34<>"#",BU34+BT34,"#"),"#") -> # | BY34: # | BZ34: # | CA34: # | CB34: # | CC34: # | CD34: # | CE34: # | CF34: # | CG34: # | CH34: # | CI34: # | CJ34: # | CK34: # | CL34: # | CM34: # | CN34: # | CO34: # | CP34: # | CQ34: # | CR34: # | CS34: # | CT34: # | CU34: # | CV34: # | CW34: # | CX34: # | CY34: # | CZ34: # | DA34: # | DB34: # | DC34: # | DD34: # | DE34: include | DF34: # | DG34: # | DH34: # | DI34: #
A35: a41_3 | B35: Iftner, T., et al. | C35: prosp. cohort | D35: 44328 | E35: 44397 | F35: Germany | G35: EU; Employees of the University Hospital Thüringen | H35: City | I35: 59925.317 | J35: unclear | K35: # | L35: # | M35: # | N35: # | O35: Number of people that collected self-tests | P35: # | Q35: # | R35: # | S35: # | T35: # | U35: # | V35: # | W35: # | X35: # | Y35: # | Z35: Healthcare Professionals | AA35: # | AB35: # | AC35: # | AD35: =IF(AND(AA35=0,AC35=0),1,0) -> 0 | AE35: # | AF35: # | AG35: unknown | AH35: # | AI35: # | AJ35: Beijing Hotgen Biotech Co., Ltd. “Corona Lay Test, Home Self-Test. Coronavirus (2019-nCoV) Antigen Test” | AK35: no | AL35: AN / MT | AM35: # | AN35: Home | AO35: Single | AP35: # | AQ35: # | AR35: 502 | AS35: # | AT35: 464 | AU35: no | AV35: no | AW35: RT-PCR testing | AX35: # | AY35: =SUM(AZ35:BC35) -> 464 | AZ35: 1 | BA35: 453 | BB35: 10 | BC35: # | BD35: RT-PCR | BE35: OP | BF35: =SUM(BG35:BJ35) -> 454 | BG35: 0 | BH35: 0 | BI35: 453 | BJ35: 1 | BK35: =IFERROR(IF(BJ35<>"#",BJ35+BI35,"#"),"#") -> 454 | BL35: =SUM(BM35:BP35) -> 0 | BM35: # | BN35: # | BO35: # | BP35: # | BQ35: # | BR35: # | BS35: =SUM(BT35:BW35) -> 0 | BT35: # | BU35: # | BV35: # | BW35: # | BX35: =IFERROR(IF(BU35<>"#",BU35+BT35,"#"),"#") -> # | BY35: # | BZ35: # | CA35: # | CB35: # | CC35: # | CD35: # | CE35: # | CF35: # | CG35: # | CH35: # | CI35: # | CJ35: # | CK35: # | CL35: # | CM35: # | CN35: # | CO35: # | CP35: # | CQ35: # | CR35: # | CS35: # | CT35: # | CU35: # | CV35: # | CW35: # | CX35: # | CY35: # | CZ35: # | DA35: # | DB35: # | DC35: # | DD35: # | DE35: include | DF35: # | DG35: # | DH35: # | DI35: #
A36: a41_4 | B36: Iftner, T., et al. | C36: prosp. cohort | D36: 44328 | E36: 44397 | F36: Germany | G36: EU; Employees of the University Hospital Thüringen | H36: City | I36: 59925.317 | J36: unclear | K36: # | L36: # | M36: # | N36: # | O36: Number of people that collected self-tests | P36: # | Q36: # | R36: # | S36: # | T36: # | U36: # | V36: # | W36: # | X36: # | Y36: # | Z36: Healthcare Professionals | AA36: # | AB36: # | AC36: # | AD36: =IF(AND(AA36=0,AC36=0),1,0) -> 0 | AE36: # | AF36: # | AG36: unknown | AH36: # | AI36: # | AJ36: Mexacare GmbH “MEXACARE Corona Home-Test “Antigen” Rapid Test for self-testing” | AK36: no | AL36: AN / MT | AM36: # | AN36: Home | AO36: Single | AP36: # | AQ36: # | AR36: 511 | AS36: # | AT36: 481 | AU36: no | AV36: no | AW36: RT-PCR testing | AX36: # | AY36: =SUM(AZ36:BC36) -> 481 | AZ36: 1 | BA36: 462 | BB36: 18 | BC36: # | BD36: RT-PCR | BE36: OP | BF36: =SUM(BG36:BJ36) -> 463 | BG36: 0 | BH36: 0 | BI36: 462 | BJ36: 1 | BK36: =IFERROR(IF(BJ36<>"#",BJ36+BI36,"#"),"#") -> 463 | BL36: =SUM(BM36:BP36) -> 0 | BM36: # | BN36: # | BO36: # | BP36: # | BQ36: # | BR36: # | BS36: =SUM(BT36:BW36) -> 0 | BT36: # | BU36: # | BV36: # | BW36: # | BX36: =IFERROR(IF(BU36<>"#",BU36+BT36,"#"),"#") -> # | BY36: # | BZ36: # | CA36: # | CB36: # | CC36: # | CD36: # | CE36: # | CF36: # | CG36: # | CH36: # | CI36: # | CJ36: # | CK36: # | CL36: # | CM36: # | CN36: # | CO36: # | CP36: # | CQ36: # | CR36: # | CS36: # | CT36: # | CU36: # | CV36: # | CW36: # | CX36: # | CY36: # | CZ36: # | DA36: # | DB36: # | DC36: # | DD36: # | DE36: include | DF36: # | DG36: # | DH36: # | DI36: #
A37: a42_0 | B37: Kheiroddin, P., et al | C37: prosp. cohort | D37: 44298 | E37: 44339 | F37: Germany | G37: EU; School students across the state Baden-Wuerttemberg | H37: City; semi-dense | I37: 59925.317 | J37: unclear | K37: # | L37: # | M37: # | N37: # | O37: Number of people eligible for self-testing | P37: # | Q37: # | R37: # | S37: # | T37: # | U37: # | V37: # | W37: # | X37: # | Y37: # | Z37: K-12 students and staff | AA37: # | AB37: # | AC37: # | AD37: =IF(AND(AA37=0,AC37=0),1,0) -> 0 | AE37: # | AF37: # | AG37: unknown | AH37: # | AI37: # | AJ37: Unclear | AK37: no | AL37: # | AM37: School | AN37: School | AO37: Routine | AP37: 1 | AQ37: =ROUND(('Data extracted'!E37-'Data extracted'!D37)/7,0) -> 6 | AR37: # | AS37: # | AT37: # | AU37: # | AV37: # | AW37: Gargle pool RT-PCR testing 2 to 3 times / week | AX37: STOPP self-testing after positive RT-PCR | AY37: =SUM(AZ37:BC37) -> 11 | AZ37: 2 | BA37: 9 | BB37: 0 | BC37: 0 | BD37: RT-PCR | BE37: gargle lavage | BF37: =SUM(BG37:BJ37) -> 11 | BG37: 2 | BH37: 9 | BI37: 0 | BJ37: 0 | BK37: =IFERROR(IF(BJ37<>"#",BJ37+BI37,"#"),"#") -> 0 | BL37: =SUM(BM37:BP37) -> 11 | BM37: 2 | BN37: 9 | BO37: # | BP37: # | BQ37: RT-PCR | BR37: gargle lavage | BS37: =SUM(BT37:BW37) -> 11 | BT37: 2 | BU37: 9 | BV37: # | BW37: 0 | BX37: =IFERROR(IF(BU37<>"#",BU37+BT37,"#"),"#") -> 11 | BY37: gargle RT-PCR | BZ37: same day | CA37: # | CB37: # | CC37: # | CD37: # | CE37: # | CF37: # | CG37: # | CH37: # | CI37: # | CJ37: # | CK37: 100–250/100 000 per week | CL37: # | CM37: # | CN37: # | CO37: # | CP37: # | CQ37: # | CR37: # | CS37: # | CT37: # | CU37: # | CV37: # | CW37: # | CX37: # | CY37: # | CZ37: # | DA37: # | DB37: # | DC37: # | DD37: # | DE37: # | DF37: # | DG37: # | DH37: # | DI37: #
A38: a43_0 | B38: Kiene, S.M., et al. | C38: prosp. cohort | D38: 44507 | E38: 44647 | F38: United States | G38: NA; Sweetwater Union High School District, San Diego, CA | H38: City | I38: 89598.86 | J38: unclear | K38: 761 | L38: 264 | M38: 233 | N38: =MAX(K38:M38) -> 761 | O38: Number of people that collected / were sent self-tests | P38: 20.4 | Q38: 14.8 | R38: # | S38: # | T38: # | U38: # | V38: # | W38: 165 | X38: 95 | Y38: 4 | Z38: K-12 students and staff | AA38: # | AB38: # | AC38: # | AD38: =IF(AND(AA38=0,AC38=0),1,0) -> 0 | AE38: # | AF38: # | AG38: unknown | AH38: 171 individuals received ≥ 2 doses of vaccines, 7 received 1 dosis, and 86 were unvaccinated | AI38: # | AJ38: QuickVue At-Home OTC COVID-19 Tests | AK38: no | AL38: # | AM38: School | AN38: Home | AO38: Routine | AP38: 1 | AQ38: =ROUND(('Data extracted'!E38-'Data extracted'!D38)/7,0) -> 20 | AR38: # | AS38: # | AT38: # | AU38: no | AV38: no | AW38: Individuals were contacted by study staff if they did not pick-up their self-test or did not report self-testing results | AX38: # | AY38: # | AZ38: # | BA38: # | BB38: # | BC38: # | BD38: # | BE38: # | BF38: =SUM(BG38:BJ38) -> 0 | BG38: # | BH38: # | BI38: # | BJ38: # | BK38: =IFERROR(IF(BJ38<>"#",BJ38+BI38,"#"),"#") -> # | BL38: =SUM(BM38:BP38) -> 0 | BM38: # | BN38: # | BO38: # | BP38: # | BQ38: # | BR38: # | BS38: =SUM(BT38:BW38) -> 0 | BT38: # | BU38: # | BV38: # | BW38: # | BX38: =IFERROR(IF(BU38<>"#",BU38+BT38,"#"),"#") -> # | BY38: # | BZ38: # | CA38: 30 min. | CB38: Self-isolate | CC38: # | CD38: Continue work / school | CE38: # | CF38: # | CG38: # | CH38: # | CI38: # | CJ38: # | CK38: # | CL38: # | CM38: # | CN38: # | CO38: # | CP38: # | CQ38: # | CR38: # | CS38: # | CT38: # | CU38: # | CV38: # | CW38: # | CX38: # | CY38: # | CZ38: Routine school-based testing provided parents with comfort, at-home testing provided participants with peace of mind and a sense of safety and security, especially during testing shortages in the community | DA38: # | DB38: # | DC38: # | DD38: # | DE38: # | DF38: # | DG38: # | DH38: # | DI38: • School staff showed higher testing partici-pation and adherence to the testing sched-ule under at-home C19ST (0.286 [SE 0.040] and 0.470 [SE 0.054], respectively) compared to professional testing on-site (0.132 [SE 0.021] and 0.222 [SE 0.029], re-spectively). For school students, participa-tion and adherence rates were similar for at-home C19ST (0.091 [SE 0.012] and 0.380 [SE 0.036], respectively) and receiv-ing testing by trained staff (0.105 [SE 0.012] and 0.400 [SE 0.030], respectively).
A39: a44_0 | B39: Kim, A.E., et al. | C39: prosp. cohort | D39: 44615 | E39: 44909 | F39: United States | G39: NA; Students, faculty, and staff of the University of Washington | H39: City | I39: 89598.86 | J39: unclear | K39: # | L39: # | M39: 5575 | N39: =MAX(K39:M39) -> 5575 | O39: Number of people that reported self-testing results | P39: 33.9 | Q39: 15 | R39: 29 | S39: # | T39: # | U39: 18 | V39: 82.1 | W39: 3708 | X39: 1830 | Y39: 37 | Z39: University students and staff | AA39: # | AB39: # | AC39: # | AD39: =IF(AND(AA39=0,AC39=0),1,0) -> 0 | AE39: # | AF39: # | AG39: unknown | AH39: 4332 (77.7) fully vaccinated and boosted; 800 (14.4) fully vaccinated; 39 (0.7) unvaccinated; 404 (7.3) unknown | AI39: # | AJ39: Unclear | AK39: # | AL39: # | AM39: unclear | AN39: Unclear | AO39: Unclear | AP39: # | AQ39: # | AR39: # | AS39: # | AT39: 17572 | AU39: no | AV39: no | AW39: Walk-in RT-PCR testing available at all times; invitation to conduct RT-PCR testing in case of outbreak; invitation to self-test after out-of-state travel, exposure to a known SARS-CoV-2 case, and new or worsening COVID-19 symptoms | AX39: CONTINUE | AY39: # | AZ39: 1350 | BA39: # | BB39: # | BC39: # | BD39: RT-PCR | BE39: Anterior nasal | BF39: =SUM(BG39:BJ39) -> 7300 | BG39: 456 | BH39: # | BI39: 6762 | BJ39: 82 | BK39: =IFERROR(IF(BJ39<>"#",BJ39+BI39,"#"),"#") -> 6844 | BL39: =SUM(BM39:BP39) -> 0 | BM39: # | BN39: # | BO39: # | BP39: # | BQ39: # | BR39: # | BS39: =SUM(BT39:BW39) -> 0 | BT39: # | BU39: # | BV39: # | BW39: # | BX39: =IFERROR(IF(BU39<>"#",BU39+BT39,"#"),"#") -> # | BY39: RT-PCR | BZ39: # | CA39: # | CB39: # | CC39: # | CD39: # | CE39: # | CF39: # | CG39: # | CH39: # | CI39: # | CJ39: # | CK39: # | CL39: # | CM39: # | CN39: # | CO39: # | CP39: # | CQ39: # | CR39: # | CS39: # | CT39: # | CU39: # | CV39: # | CW39: # | CX39: # | CY39: # | CZ39: # | DA39: # | DB39: # | DC39: # | DD39: # | DE39: # | DF39: # | DG39: # | DH39: # | DI39: #
A40: a45_0 | B40: Koirala, A., et al. | C40: prosp. cohort | D40: 44506 | E40: 44551 | F40: Australia | G40: Other; Schools across New South Wales | H40: unclear | I40: 63279.351 | J40: free | K40: # | L40: # | M40: 9887 | N40: =MAX(K40:M40) -> 9887 | O40: Number of people that reported self-testing results | P40: # | Q40: # | R40: # | S40: # | T40: # | U40: # | V40: # | W40: 1323 | X40: 1409 | Y40: 7155 | Z40: K-12 students and staff | AA40: # | AB40: # | AC40: # | AD40: =IF(AND(AA40=0,AC40=0),1,0) -> 0 | AE40: # | AF40: Close contact | AG40: unknown | AH40: # | AI40: # | AJ40: Unclear | AK40: # | AL40: # | AM40: Government | AN40: Home | AO40: Routine | AP40: 7 | AQ40: 1 | AR40: =AQ40*AP40*M40 -> 69209 | AS40: # | AT40: 35438 | AU40: no | AV40: no | AW40: "obtain a SARS-CoV-2 NAAT upon notification of being a close contact of a SARS-CoV-2-positive student or staff member who attended school while infectious, and again on Day 6 and Day 10–12 post exposure" | AX40: # | AY40: # | AZ40: # | BA40: # | BB40: # | BC40: # | BD40: # | BE40: # | BF40: =SUM(BG40:BJ40) -> 0 | BG40: # | BH40: # | BI40: # | BJ40: # | BK40: =IFERROR(IF(BJ40<>"#",BJ40+BI40,"#"),"#") -> # | BL40: =SUM(BM40:BP40) -> 70 | BM40: 70 | BN40: # | BO40: # | BP40: # | BQ40: RT-PCR | BR40: # | BS40: =SUM(BT40:BW40) -> 856 | BT40: 2 | BU40: 4 | BV40: 844 | BW40: 6 | BX40: =IFERROR(IF(BU40<>"#",BU40+BT40,"#"),"#") -> 6 | BY40: RT-PCR | BZ40: # | CA40: 30 min. | CB40: Continue home isolation and confirm their result via NAAT testing | CC40: compulsory (by goverment guidance) | CD40: excemption from self-isolation if also asymptomatic and previous RT-PCR tests were negative | CE40: # | CF40: # | CG40: # | CH40: # | CI40: # | CJ40: # | CK40: # | CL40: # | CM40: # | CN40: # | CO40: # | CP40: # | CQ40: # | CR40: # | CS40: # | CT40: # | CU40: # | CV40: # | CW40: # | CX40: reduced self-isolation by 30,465 days | CY40: reduced self-isolation by 30,465 days | CZ40: # | DA40: reduced 30,465 days of school absenteeism | DB40: # | DC40: # | DD40: # | DE40: # | DF40: # | DG40: # | DH40: # | DI40: #
A41: a46_0 | B41: Kwan, T.H., et al. | C41: retrosp. cohort | D41: 44668 | E41: 44676 | F41: Hong Kong | G41: AS; Adults across Hong Kong | H41: City | I41: 56843.908 | J41: unclear | K41: # | L41: 21769 | M41: 17096 | N41: =MAX(K41:M41) -> 21769 | O41: Number of people that collected / were sent self-tests | P41: # | Q41: # | R41: 56 | S41: 38 | T41: 65 | U41: # | V41: # | W41: # | X41: # | Y41: # | Z41: General population | AA41: # | AB41: # | AC41: # | AD41: =IF(AND(AA41=0,AC41=0),1,0) -> 0 | AE41: # | AF41: # | AG41: unknown | AH41: # | AI41: # | AJ41: Unclear | AK41: # | AL41: # | AM41: Government (HongKong) | AN41: Home | AO41: Routine | AP41: 3 | AQ41: 1 | AR41: # | AS41: # | AT41: # | AU41: # | AV41: # | AW41: Local infection control measures | AX41: # | AY41: # | AZ41: # | BA41: # | BB41: # | BC41: # | BD41: # | BE41: # | BF41: =SUM(BG41:BJ41) -> 0 | BG41: # | BH41: # | BI41: # | BJ41: # | BK41: =IFERROR(IF(BJ41<>"#",BJ41+BI41,"#"),"#") -> # | BL41: =SUM(BM41:BP41) -> 162 | BM41: 162 | BN41: # | BO41: # | BP41: # | BQ41: # | BR41: # | BS41: =SUM(BT41:BW41) -> 0 | BT41: # | BU41: # | BV41: # | BW41: # | BX41: =IFERROR(IF(BU41<>"#",BU41+BT41,"#"),"#") -> # | BY41: # | BZ41: # | CA41: # | CB41: # | CC41: # | CD41: # | CE41: # | CF41: # | CG41: # | CH41: # | CI41: # | CJ41: # | CK41: # | CL41: # | CM41: # | CN41: # | CO41: # | CP41: # | CQ41: # | CR41: # | CS41: # | CT41: # | CU41: # | CV41: # | CW41: # | CX41: # | CY41: # | CZ41: # | DA41: # | DB41: # | DC41: # | DD41: # | DE41: # | DF41: # | DG41: # | DH41: # | DI41: #
A42: a47_0 | B42: Lamb, G., et al. | C42: prosp. cohort | D42: 44153 | E42: 44217 | F42: United Kingdom | G42: UK; Chelsea and Westminster NHS Foundation Trust | H42: City | I42: 56660.868 | J42: unclear | K42: 6702 | L42: # | M42: 5076 | N42: =MAX(K42:M42) -> 6702 | O42: Number of people eligible for self-testing | P42: # | Q42: # | R42: # | S42: # | T42: # | U42: # | V42: # | W42: # | X42: # | Y42: # | Z42: Healthcare Professionals | AA42: 95 | AB42: 50 | AC42: 4931 | AD42: =IF(AND(AA42=0,AC42=0),1,0) -> 0 | AE42: # | AF42: # | AG42: unknown | AH42: # | AI42: unclear | AJ42: Innova LFD | AK42: no | AL42: AN / MT | AM42: Employer | AN42: Home | AO42: Routine | AP42: 2 | AQ42: =ROUND(('Data extracted'!E42-'Data extracted'!D42)/7,0) -> 9 | AR42: =AQ42*AP42*M42 -> 91368 | AS42: # | AT42: 45022 | AU42: no | AV42: no | AW42: RT-PCR testing for symptomatic persons | AX42: Unclear | AY42: =SUM(AZ42:BC42) -> 45022 | AZ42: 284 | BA42: 44676 | BB42: 35 | BC42: 27 | BD42: RT-PCR | BE42: NP | BF42: =SUM(BG42:BJ42) -> 259 | BG42: 244 | BH42: # | BI42: # | BJ42: 15 | BK42: =IFERROR(IF(BJ42<>"#",BJ42+BI42,"#"),"#") -> # | BL42: =SUM(BM42:BP42) -> 5076 | BM42: 284 | BN42: =5076-BM42-BO42-BP42 -> 4730 | BO42: 35 | BP42: 27 | BQ42: RT-PCR | BR42: NP | BS42: =SUM(BT42:BW42) -> 295 | BT42: 244 | BU42: 36 | BV42: # | BW42: 15 | BX42: =IFERROR(IF(BU42<>"#",BU42+BT42,"#"),"#") -> 280 | BY42: RT-PCR | BZ42: 1-3 days | CA42: 30 min. | CB42: PCR confirmatory testing, self-isolate | CC42: compulsory (by goverment guidance) | CD42: # | CE42: # | CF42: # | CG42: # | CH42: # | CI42: # | CJ42: # | CK42: # | CL42: 0,74-3,5% | CM42: # | CN42: # | CO42: # | CP42: # | CQ42: # | CR42: # | CS42: # | CT42: # | CU42: # | CV42: # | CW42: # | CX42: # | CY42: # | CZ42: # | DA42: # | DB42: # | DC42: # | DD42: # | DE42: # | DF42: # | DG42: # | DH42: # | DI42: #
A43: a48_0 | B43: Lau, C.S., et al. | C43: prosp. cohort | D43: 44331 | E43: 44635 | F43: Singapore | G43: AS; Laboratory staff at the Changi General Hospital | H43: City | I43: 94480.797 | J43: unclear | K43: 161 | L43: 161 | M43: 161 | N43: =MAX(K43:M43) -> 161 | O43: Number of people that reported self-testing results | P43: # | Q43: # | R43: # | S43: # | T43: # | U43: # | V43: # | W43: # | X43: # | Y43: # | Z43: General population | AA43: # | AB43: # | AC43: # | AD43: =IF(AND(AA43=0,AC43=0),1,0) -> 0 | AE43: # | AF43: # | AG43: unknown | AH43: # | AI43: # | AJ43: SD Biosensor Standard Q & Abbott Panbio COVID-19 Ag Rapid Tests | AK43: no | AL43: AN / MT | AM43: Employer | AN43: Home | AO43: Routine | AP43: Unclear | AQ43: =ROUND(('Data extracted'!E43-'Data extracted'!D43)/7,0) -> 43 | AR43: # | AS43: # | AT43: # | AU43: no | AV43: no | AW43: RT-PCR every three days for the first two weeks of the study (afterwards discontinued) | AX43: Unclear | AY43: 0 | AZ43: 0 | BA43: # | BB43: # | BC43: # | BD43: # | BE43: # | BF43: # | BG43: # | BH43: # | BI43: # | BJ43: # | BK43: =IFERROR(IF(BJ43<>"#",BJ43+BI43,"#"),"#") -> # | BL43: =SUM(BM43:BP43) -> 161 | BM43: 0 | BN43: 161 | BO43: # | BP43: # | BQ43: RT-PCR | BR43: # | BS43: =SUM(BT43:BW43) -> 160 | BT43: 0 | BU43: 0 | BV43: 160 | BW43: 0 | BX43: =IFERROR(IF(BU43<>"#",BU43+BT43,"#"),"#") -> 0 | BY43: # | BZ43: # | CA43: # | CB43: # | CC43: # | CD43: # | CE43: # | CF43: # | CG43: # | CH43: # | CI43: # | CJ43: # | CK43: # | CL43: # | CM43: # | CN43: # | CO43: # | CP43: # | CQ43: # | CR43: # | CS43: # | CT43: # | CU43: # | CV43: # | CW43: # | CX43: # | CY43: # | CZ43: # | DA43: # | DB43: # | DC43: # | DD43: # | DE43: # | DF43: # | DG43: include | DH43: include | DI43: #
A44: a49_0 | B44: Love, N.K., et al. (a) | C44: prosp. cohort | D44: 44315 | E44: 44405 | F44: United Kingdom | G44: UK; Contacts across UK; NHS Test and Trace | H44: unclear | I44: 56660.868 | J44: unclear | K44: # | L44: 26123 | M44: =26123-5328 -> 20795 | N44: =MAX(K44:M44) -> 26123 | O44: Number of people eligible for self-testing | P44: # | Q44: # | R44: 43 | S44: 29 | T44: 53 | U44: # | V44: # | W44: 14000 | X44: 12113 | Y44: # | Z44: General population | AA44: 0 | AB44: 26123 | AC44: 0 | AD44: =IF(AND(AA44=0,AC44=0),1,0) -> 1 | AE44: # | AF44: # | AG44: unknown | AH44: 3390 unvaccinated, 6343 had 1 dose, 16103 had 2 doses | AI44: # | AJ44: Innova LFD | AK44: no | AL44: AN / MT | AM44: Study | AN44: Home | AO44: Routine | AP44: 7 | AQ44: 1 | AR44: =AQ44*AP44*M44 -> 145565 | AS44: # | AT44: 124010 | AU44: no | AV44: no | AW44: Local infection control measures | AX44: # | AY44: # | AZ44: # | BA44: # | BB44: # | BC44: # | BD44: # | BE44: # | BF44: =SUM(BG44:BJ44) -> 0 | BG44: # | BH44: # | BI44: # | BJ44: # | BK44: =IFERROR(IF(BJ44<>"#",BJ44+BI44,"#"),"#") -> # | BL44: =SUM(BM44:BP44) -> 20765 | BM44: 1132 | BN44: 19633 | BO44: # | BP44: # | BQ44: # | BR44: # | BS44: =SUM(BT44:BW44) -> 0 | BT44: # | BU44: # | BV44: # | BW44: # | BX44: =IFERROR(IF(BU44<>"#",BU44+BT44,"#"),"#") -> # | BY44: RT-PCR | BZ44: # | CA44: 30 min. | CB44: PCR swab to study team for confirmatory testing; self-isolation | CC44: compulsory (by study design) | CD44: exemption from isolation for 24h, then test again | CE44: # | CF44: # | CG44: # | CH44: # | CI44: # | CJ44: # | CK44: # | CL44: # | CM44: # | CN44: 327 | CO44: 5191 | CP44: 319 | CQ44: 5129 | CR44: 2.2 per secondary case, with 1.93 of these being household contacts | CS44: # | CT44: # | CU44: # | CV44: # | CW44: # | CX44: self-testing enabled a mean of 5.9 days [SD 1.79] per participant who worked outside of the home | CY44: none if test negative | CZ44: # | DA44: self-testing enabled a mean of 5.9 days [SD 1.79] per participant who worked outside of the home | DB44: # | DC44: # | DD44: # | DE44: # | DF44: # | DG44: # | DH44: # | DI44: • The study observed that 82% of the study participants in the self-isolation group and 84% in the C19ST subgroup significantly reduced contact with non-household mem-bers. Conversely, in the antigen no-positive-test subgroup, only 57% reported reduced contact, with 11% reporting in-creased contact. • The study suggests that individuals receiv-ing negative antigen test results may per-ceive themselves as less infectious, lead-ing to greater social interaction, whereas positive results lead to self-isolation
A45: a50_0 | B45: Love, N.K., et al. (b) | C45: prosp. cohort | D45: 44176 | E45: 44208 | F45: United Kingdom | G45: UK; Contacts across UK; NHS Test and Trace | H45: City; rural | I45: 56660.868 | J45: free | K45: 1760 | L45: 812 | M45: 570 | N45: =MAX(K45:M45) -> 1760 | O45: Number of people invited to self-test | P45: # | Q45: # | R45: # | S45: # | T45: # | U45: # | V45: # | W45: 864 | X45: 896 | Y45: # | Z45: General population | AA45: 0 | AB45: 1760 | AC45: 0 | AD45: =IF(AND(AA45=0,AC45=0),1,0) -> 1 | AE45: # | AF45: contact with a confirmed COVID-19 case | AG45: unknown | AH45: # | AI45: # | AJ45: Innova LFD | AK45: no | AL45: AN / MT | AM45: Public Heath Authority | AN45: Home | AO45: Routine | AP45: 6 | AQ45: =ROUND(('Data extracted'!E45-'Data extracted'!D45)/7,0) -> 5 | AR45: =1*AP45*M45 -> 3420 | AS45: # | AT45: 2505 | AU45: no | AV45: no | AW45: # | AX45: STOPP self-testing since rt-pcr was done at the end of the study | AY45: # | AZ45: # | BA45: # | BB45: # | BC45: # | BD45: # | BE45: # | BF45: =SUM(BG45:BJ45) -> 0 | BG45: # | BH45: # | BI45: # | BJ45: # | BK45: =IFERROR(IF(BJ45<>"#",BJ45+BI45,"#"),"#") -> # | BL45: =SUM(BM45:BP45) -> 578 | BM45: 102 | BN45: 464 | BO45: 4 | BP45: 8 | BQ45: RT-PCR | BR45: AN / MT | BS45: =SUM(BT45:BW45) -> 346 | BT45: 53 | BU45: 11 | BV45: 281 | BW45: 1 | BX45: =IFERROR(IF(BU45<>"#",BU45+BT45,"#"),"#") -> 64 | BY45: RT-PCR | BZ45: # | CA45: 30 min. | CB45: PCR swab to study team for confirmatory testing; self-isolation | CC45: compulsory (by study design) | CD45: exemption from isolation for 24h, then test again | CE45: # | CF45: # | CG45: # | CH45: # | CI45: # | CJ45: # | CK45: # | CL45: # | CM45: # | CN45: 10 | CO45: 160 | CP45: # | CQ45: # | CR45: # | CS45: # | CT45: # | CU45: # | CV45: # | CW45: # | CX45: # | CY45: none if test negative | CZ45: # | DA45: # | DB45: # | DC45: # | DD45: # | DE45: # | DF45: # | DG45: # | DH45: # | DI45: • 84 individuals who had chosen daily C19ST instead of self-isolation were eventually confirmed for a SARS-CoV-2 infection. 64 of those reported that they had been in contact with other individuals prior to this diagnosis, which they would not have been if they had self-isolated.
A46: a51_1 | B46: Marbán‐Castro, E., et al. | C46: prosp. cohort | D46: 44727 | E46: 44910 | F46: Georgia | G46: EU; Staff of health-facilities in Tibilisi and Kutaisi and of public Schools in Svanteni | H46: City; rural | I46: 10125.977 | J46: free | K46: 2180 | L46: 2156 | M46: # | N46: =MAX(K46:M46) -> 2180 | O46: Number of people that collected / were sent self-tests | P46: # | Q46: # | R46: # | S46: # | T46: # | U46: # | V46: # | W46: # | X46: # | Y46: # | Z46: Unclear | AA46: # | AB46: # | AC46: # | AD46: =IF(AND(AA46=0,AC46=0),1,0) -> 0 | AE46: 271 | AF46: # | AG46: unknown | AH46: 404 unvaccinated; 38 had received 1 dose; 559 had received 2 doses; 304 had received ≥ 3 doses | AI46: 923 had a previous COVID-19 diagnosis | AJ46: OnSite COVID-19 Ag Self-Test | AK46: no | AL46: AN / MT | AM46: Study | AN46: Home / Office | AO46: Routine | AP46: 1 | AQ46: 26 | AR46: # | AS46: # | AT46: 51912 | AU46: no | AV46: no | AW46: Ag-RDT training at begin of the study; satisfaction surveys | AX46: # | AY46: 51912 | AZ46: 289 | BA46: 51569 | BB46: 54 | BC46: # | BD46: # | BE46: # | BF46: =SUM(BG46:BJ46) -> 0 | BG46: # | BH46: # | BI46: # | BJ46: # | BK46: =IFERROR(IF(BJ46<>"#",BJ46+BI46,"#"),"#") -> # | BL46: =SUM(BM46:BP46) -> 282 | BM46: 282 | BN46: # | BO46: # | BP46: # | BQ46: # | BR46: # | BS46: =SUM(BT46:BW46) -> 0 | BT46: # | BU46: # | BV46: # | BW46: # | BX46: =IFERROR(IF(BU46<>"#",BU46+BT46,"#"),"#") -> # | BY46: C19ST | BZ46: 15 min. | CA46: 30 min. | CB46: Follow national COVID-19 guidelines including self-isolation; report own result and those of household-members to study staff | CC46: # | CD46: Continue work / school; repeat the self-test after three days if at the time of the negative results, symptoms were also present; report own result and those of household-members to study staff | CE46: # | CF46: # | CG46: # | CH46: # | CI46: # | CJ46: # | CK46: # | CL46: # | CM46: # | CN46: # | CO46: # | CP46: # | CQ46: # | CR46: # | CS46: # | CT46: # | CU46: # | CV46: # | CW46: # | CX46: Less self-isolation among staff | CY46: Less self-isolation among staff | CZ46: Increased "feeling of peace" | DA46: Less self-isolation among staff | DB46: # | DC46: # | DD46: # | DE46: # | DF46: # | DG46: # | DH46: # | DI46: #
A47: a51_2 | B47: Marbán‐Castro, E., et al. | C47: prosp. cohort | D47: 44727 | E47: 44910 | F47: Georgia | G47: EU; Household members of the staff of health-facilities in Tibilisi and Kutaisi and of public Schools in Svanteni | H47: City; rural | I47: 10125.977 | J47: free | K47: # | L47: 582 | M47: # | N47: =MAX(K47:M47) -> 582 | O47: Number of people that collected / were sent self-tests | P47: # | Q47: # | R47: # | S47: # | T47: # | U47: # | V47: # | W47: # | X47: # | Y47: # | Z47: General population | AA47: # | AB47: # | AC47: # | AD47: =IF(AND(AA47=0,AC47=0),1,0) -> 0 | AE47: # | AF47: # | AG47: unknown | AH47: # | AI47: # | AJ47: OnSite COVID-19 Ag Self-Test | AK47: no | AL47: AN / MT | AM47: Household member | AN47: Home / Office | AO47: Routine | AP47: Unclear | AQ47: 26 | AR47: # | AS47: # | AT47: 1073 | AU47: no | AV47: no | AW47: # | AX47: # | AY47: 1073 | AZ47: 333 | BA47: 734 | BB47: 6 | BC47: # | BD47: # | BE47: # | BF47: =SUM(BG47:BJ47) -> 0 | BG47: # | BH47: # | BI47: # | BJ47: # | BK47: =IFERROR(IF(BJ47<>"#",BJ47+BI47,"#"),"#") -> # | BL47: =SUM(BM47:BP47) -> 319 | BM47: 319 | BN47: # | BO47: # | BP47: # | BQ47: # | BR47: # | BS47: =SUM(BT47:BW47) -> 0 | BT47: # | BU47: # | BV47: # | BW47: # | BX47: =IFERROR(IF(BU47<>"#",BU47+BT47,"#"),"#") -> # | BY47: C19ST | BZ47: 15 min. | CA47: 30 min. | CB47: Follow national COVID-19 guidelines including self-isolation; report own result and those of household-members to study staff | CC47: # | CD47: Continue work / school; repeat the self-test after three days if at the time of the negative results, symptoms were also present | CE47: # | CF47: # | CG47: # | CH47: # | CI47: # | CJ47: # | CK47: # | CL47: # | CM47: # | CN47: # | CO47: # | CP47: # | CQ47: # | CR47: # | CS47: # | CT47: # | CU47: # | CV47: # | CW47: # | CX47: # | CY47: # | CZ47: # | DA47: # | DB47: # | DC47: # | DD47: # | DE47: # | DF47: # | DG47: # | DH47: # | DI47: #
A48: a52_0 | B48: McDaniels-Davidson, C., et al. | C48: prosp. cohort | D48: 44500 | E48: 44584 | F48: United States | G48: NA; Students in the San Diego Sweetwater Union High School District | H48: City | I48: 89598.86 | J48: unclear | K48: # | L48: 159 | M48: 93 | N48: =MAX(K48:M48) -> 159 | O48: Number of people that reported self-testing results | P48: # | Q48: # | R48: # | S48: # | T48: # | U48: # | V48: # | W48: # | X48: # | Y48: # | Z48: K-12 students and staff | AA48: # | AB48: # | AC48: # | AD48: =IF(AND(AA48=0,AC48=0),1,0) -> 0 | AE48: # | AF48: # | AG48: unknown | AH48: # | AI48: # | AJ48: Unclear | AK48: # | AL48: # | AM48: # | AN48: Home | AO48: Routine | AP48: 1 | AQ48: =ROUND(('Data extracted'!E48-'Data extracted'!D48)/7,0) -> 12 | AR48: =8+47+55+62+69+78+98+105+108+111+117+144+159 -> 1161 | AS48: # | AT48: =5+26+37+27+48+45+45+34+43+52+73+88+93 -> 616 | AU48: no | AV48: no | AW48: Weekly email to remind individuals of testing, support telephone hotline, instructional materal | AX48: # | AY48: # | AZ48: # | BA48: # | BB48: # | BC48: # | BD48: # | BE48: # | BF48: =SUM(BG48:BJ48) -> 0 | BG48: # | BH48: # | BI48: # | BJ48: # | BK48: =IFERROR(IF(BJ48<>"#",BJ48+BI48,"#"),"#") -> # | BL48: # | BM48: # | BN48: # | BO48: # | BP48: # | BQ48: # | BR48: # | BS48: =SUM(BT48:BW48) -> 0 | BT48: # | BU48: # | BV48: # | BW48: # | BX48: =IFERROR(IF(BU48<>"#",BU48+BT48,"#"),"#") -> # | BY48: # | BZ48: # | CA48: # | CB48: Perform either a second C19ST or RT-PCR confirmatory testing (as per study design) | CC48: mixed - perform either a second C19ST or a RT-PCR (as per study design) | CD48: # | CE48: # | CF48: # | CG48: # | CH48: # | CI48: # | CJ48: # | CK48: # | CL48: # | CM48: # | CN48: # | CO48: # | CP48: # | CQ48: # | CR48: # | CS48: # | CT48: # | CU48: # | CV48: # | CW48: # | CX48: # | CY48: # | CZ48: # | DA48: # | DB48: # | DC48: # | DD48: # | DE48: # | DF48: # | DG48: # | DH48: # | DI48: #
A49: a53_0 | B49: Moonan, P.K., et al. | C49: prosp. cohort | D49: 44197 | E49: 44651 | F49: United States | G49: NA; Representative sampling across the United States | H49: unclear | I49: 89598.86 | J49: unclear | K49: 15923 | L49: # | M49: # | N49: =MAX(K49:M49) -> 15923 | O49: Number of people eligible for self-testing | P49: # | Q49: # | R49: # | S49: # | T49: # | U49: # | V49: # | W49: # | X49: # | Y49: # | Z49: General population | AA49: # | AB49: # | AC49: # | AD49: =IF(AND(AA49=0,AC49=0),1,0) -> 0 | AE49: # | AF49: # | AG49: unknown | AH49: # | AI49: # | AJ49: Unclear | AK49: no | AL49: # | AM49: # | AN49: Unclear | AO49: Unclear | AP49: # | AQ49: =ROUND(('Data extracted'!E49-'Data extracted'!D49)/7,0) -> 65 | AR49: # | AS49: # | AT49: # | AU49: no | AV49: no | AW49: # | AX49: # | AY49: # | AZ49: # | BA49: # | BB49: # | BC49: # | BD49: # | BE49: # | BF49: =SUM(BG49:BJ49) -> 0 | BG49: # | BH49: # | BI49: # | BJ49: # | BK49: =IFERROR(IF(BJ49<>"#",BJ49+BI49,"#"),"#") -> # | BL49: =SUM(BM49:BP49) -> 0 | BM49: # | BN49: # | BO49: # | BP49: # | BQ49: # | BR49: # | BS49: =SUM(BT49:BW49) -> 0 | BT49: # | BU49: # | BV49: # | BW49: # | BX49: =IFERROR(IF(BU49<>"#",BU49+BT49,"#"),"#") -> # | BY49: # | BZ49: # | CA49: 30 min. | CB49: Follow CDC COIVD-19 guidelines, i.e., self-isolate for 10 days (when testing posiitive during 1/1/21-12/31/21) or 5 days (when testing posiitive during 1/1/22-3/31/22) | CC49: # | CD49: # | CE49: # | CF49: # | CG49: # | CH49: # | CI49: # | CJ49: # | CK49: # | CL49: # | CM49: # | CN49: # | CO49: # | CP49: # | CQ49: # | CR49: Participants who home tested also had decreased odds of self-notifying their contacts; however, that association was not statistically significant (78% vs. 84%; aOR 0.79 [95% CI 0.53–1.18]) | CS49: # | CT49: # | CU49: # | CV49: # | CW49: # | CX49: # | CY49: Persons who received results from home-based tests were significantly less likely to isolate for any duration compared with those who received provider- administered tests (78% vs. 84%; aOR 0.72 [95% CI 0.57–0.89]); Odds that their isolation met contempo- rary guidelines were significantly lower among per- sons who received results from home-based tests than among those with provider-administered tests (64% vs, 73%; aOR 0.71 [95% CI 0.53–0.95] => adjusted mean duration of isolation was 2 (95% CI 1.59–2.45) days shorter among persons with results from home- based tests than those with provider-administered tests (p<0.001) | CZ49: # | DA49: # | DB49: # | DC49: # | DD49: # | DE49: # | DF49: # | DG49: # | DH49: # | DI49: • Compared to individuals who received a COVID-19 diagnosis through testing by trained staff, individuals who conducted C19ST were less likely to self-isolate (aOR 0.72 [95% CI 0.57–0.89]), had a lower chance of being compliant with local guide-lines if they were isolating (aOR 0.71 [95% CI 0.53–0.95]), and were less likely to in-form their contacts about their SARS-CoV-2 diagnosis (aOR 0.79 [95% CI 0.53–1.18]).
A50: a54_0 | B50: Nagasawa, M., et al. | C50: prosp. cohort | D50: 44824 | E50: 45223 | F50: Japan | G50: AS; Employees of the Musashino Red Cross Hospital | H50: City | I50: 34713.248 | J50: unclear | K50: 1481 | L50: # | M50: # | N50: =MAX(K50:M50) -> 1481 | O50: Number of people invited to self-test | P50: # | Q50: # | R50: # | S50: # | T50: # | U50: # | V50: # | W50: # | X50: # | Y50: # | Z50: Healthcare Professionals | AA50: # | AB50: # | AC50: # | AD50: =IF(AND(AA50=0,AC50=0),1,0) -> 0 | AE50: # | AF50: # | AG50: unknown | AH50: # | AI50: # | AJ50: Panbio COVID-19 Antigen Rapid Test; Rapid COVID-19 Antigen Self-Test; SARS-CoV-2 Rapid Antigen Test | AK50: no | AL50: # | AM50: # | AN50: Home | AO50: Routine | AP50: Unclear | AQ50: =ROUND(('Data extracted'!E50-'Data extracted'!D50)/7,0)-1 -> 56 | AR50: # | AS50: # | AT50: # | AU50: no | AV50: no | AW50: self-isolate after close contact or infection | AX50: # | AY50: # | AZ50: # | BA50: # | BB50: # | BC50: # | BD50: # | BE50: # | BF50: =SUM(BG50:BJ50) -> 0 | BG50: # | BH50: # | BI50: # | BJ50: # | BK50: =IFERROR(IF(BJ50<>"#",BJ50+BI50,"#"),"#") -> # | BL50: =SUM(BM50:BP50) -> 0 | BM50: # | BN50: # | BO50: # | BP50: # | BQ50: unclear | BR50: unclear | BS50: unclear | BT50: # | BU50: # | BV50: # | BW50: # | BX50: =IFERROR(IF(BU50<>"#",BU50+BT50,"#"),"#") -> # | BY50: # | BZ50: # | CA50: 30 min. | CB50: Continue / start self-isolation | CC50: # | CD50: return to work either three days after contact or 5 days after infection (given that the person testing negative is also fever-free for 14h) | CE50: # | CF50: # | CG50: # | CH50: # | CI50: # | CJ50: # | CK50: # | CL50: # | CM50: # | CN50: # | CO50: # | CP50: # | CQ50: # | CR50: # | CS50: # | CT50: # | CU50: # | CV50: # | CW50: # | CX50: after close contact: individuals could continue working if C19ST was negative (testing required for the first 3 days after contact) after confirmed infection: return to work on day 5 after infection instead of day 10 if C19ST negative on day 5 (and fever-free for at least 24h) | CY50: # | CZ50: # | DA50: after close contact: individuals could continue working if C19ST was negative (testing required for the first 3 days after contact) after confirmed infection: return to work on day 5 after infection instead of day 10 if C19ST negative on day 5 (and fever-free for at least 24h) | DB50: # | DC50: # | DD50: # | DE50: # | DF50: # | DG50: # | DH50: # | DI50: #
A51: a55_0 | B51: Nakgul, L., et al. | C51: prosp. cohort | D51: 44545 | E51: 44635 | F51: Thailand | G51: AS; Anubansamsen School | H51: City | I51: 7942.299 | J51: unclear | K51: 164 | L51: 133 | M51: 133 | N51: =MAX(K51:M51) -> 164 | O51: Number of people that collected / were sent self-tests | P51: # | Q51: # | R51: # | S51: # | T51: # | U51: # | V51: # | W51: 66 | X51: 67 | Y51: # | Z51: K-12 students and staff | AA51: # | AB51: # | AC51: # | AD51: =IF(AND(AA51=0,AC51=0),1,0) -> 0 | AE51: # | AF51: # | AG51: unknown | AH51: 19 adults (100%) had two doses; 13 children (11.4%) had one dosis and all other children were unvaccinated | AI51: # | AJ51: saliva lollipop rapid antigen lateral flow test (Hangzhou Testsea Biotechnology, Hangzhou, China) | AK51: no | AL51: Saliva | AM51: School | AN51: School | AO51: Routine | AP51: 2 | AQ51: 13 | AR51: =AQ51*AP51*M51 -> 3458 | AS51: 1095 | AT51: 1095 | AU51: no | AV51: yes | AW51: wastewater surveillance; additional measures: (1) each class was split into two groups, in which the students went to school on alternate days, (2) temperature screening before entering the school, (3) mask worn throughout the day, (4) maintaining physical distancing, (5) hygiene and cleanliness mea- sures implementation, and (6) COVID-19 vaccination in all teachers and eligible students | AX51: # | AY51: 1095 | AZ51: 0 | BA51: 1095 | BB51: # | BC51: # | BD51: # | BE51: # | BF51: =SUM(BG51:BJ51) -> 0 | BG51: # | BH51: # | BI51: # | BJ51: # | BK51: =IFERROR(IF(BJ51<>"#",BJ51+BI51,"#"),"#") -> # | BL51: =SUM(BM51:BP51) -> 133 | BM51: 0 | BN51: 133 | BO51: # | BP51: # | BQ51: Nasal-swab self-test | BR51: Nasal | BS51: =SUM(BT51:BW51) -> 2 | BT51: # | BU51: 2 | BV51: # | BW51: # | BX51: =IFERROR(IF(BU51<>"#",BU51+BT51,"#"),"#") -> # | BY51: RT-PCR | BZ51: # | CA51: # | CB51: Provide saliva sample for RT-PCR confirmatory testing; in case of confirmed case (definition unclear) entire class closed for one week by government guidelines | CC51: compulsory (by study design) | CD51: Continue routine testing | CE51: # | CF51: # | CG51: # | CH51: # | CI51: # | CJ51: # | CK51: # | CL51: # | CM51: # | CN51: # | CO51: # | CP51: # | CQ51: # | CR51: # | CS51: # | CT51: # | CU51: # | CV51: # | CW51: # | CX51: # | CY51: # | CZ51: # | DA51: # | DB51: # | DC51: # | DD51: # | DE51: # | DF51: # | DG51: # | DH51: include | DI51: #
A52: a56_0 | B52: Nodora, J.N., et al. | C52: prosp. cohort | D52: 44737 | E52: 45046 | F52: United States | G52: NA; Community Health Centers, San Diego County, CA | H52: unclear | I52: 89598.86 | J52: unclear | K52: 2189 | L52: 1013 | M52: 367 | N52: =MAX(K52:M52) -> 2189 | O52: Number of people that collected / were sent self-tests | P52: 42.9 | Q52: 13.3 | R52: # | S52: # | T52: # | U52: # | V52: # | W52: 792 | X52: 167 | Y52: 54 | Z52: General population | AA52: # | AB52: # | AC52: # | AD52: =IF(AND(AA52=0,AC52=0),1,0) -> 0 | AE52: # | AF52: # | AG52: unknown | AH52: 851 | AI52: # | AJ52: FlowFlex SARS-CoV-2 antigen rapid test | AK52: no | AL52: AN / MT | AM52: Study | AN52: Home | AO52: Unclear | AP52: # | AQ52: =ROUND(('Data extracted'!E52-'Data extracted'!D52)/7,0) -> 44 | AR52: # | AS52: # | AT52: 676 | AU52: no | AV52: no | AW52: Study personnel explained IFUs to participants. Also explained when to test | AX52: # | AY52: # | AZ52: # | BA52: # | BB52: # | BC52: # | BD52: # | BE52: # | BF52: =SUM(BG52:BJ52) -> 0 | BG52: # | BH52: # | BI52: # | BJ52: # | BK52: =IFERROR(IF(BJ52<>"#",BJ52+BI52,"#"),"#") -> # | BL52: =SUM(BM52:BP52) -> 0 | BM52: # | BN52: # | BO52: # | BP52: # | BQ52: # | BR52: # | BS52: =SUM(BT52:BW52) -> 0 | BT52: # | BU52: # | BV52: # | BW52: # | BX52: =IFERROR(IF(BU52<>"#",BU52+BT52,"#"),"#") -> # | BY52: # | BZ52: # | CA52: # | CB52: Follow national COVID-19 guideline | CC52: # | CD52: # | CE52: # | CF52: # | CG52: # | CH52: # | CI52: # | CJ52: # | CK52: # | CL52: # | CM52: # | CN52: # | CO52: # | CP52: # | CQ52: # | CR52: # | CS52: # | CT52: # | CU52: # | CV52: # | CW52: # | CX52: Missing work or school; undergoing self-isolation | CY52: Missing work or school; undergoind self-isolation | CZ52: # | DA52: Missing work or school; undergoind self-isolation | DB52: # | DC52: # | DD52: # | DE52: # | DF52: # | DG52: # | DH52: # | DI52: #
A53: a57_0 | B53: Papenburg, J., et al. | C53: prosp. cohort | D53: 44384 | E53: 44477 | F53: Canada | G53: NA; Businesses in Montreal | H53: City | I53: 54934.843 | J53: unclear | K53: 647 | L53: 278 | M53: 278 | N53: =MAX(K53:M53) -> 647 | O53: Number of people that reported self-testing results | P53: # | Q53: # | R53: 43 | S53: 31 | T53: 55 | U53: # | V53: # | W53: 109 | X53: 156 | Y53: 13 | Z53: Unclear | AA53: # | AB53: 199 | AC53: # | AD53: =IF(AND(AA53=0,AC53=0),1,0) -> 0 | AE53: # | AF53: # | AG53: unknown | AH53: 237 | AI53: # | AJ53: Panbio COVID-19 Ag Rapid Test Device (Abbott Laboratories) | AK53: no | AL53: AN / MT | AM53: Testing Site | AN53: Testing Site | AO53: Routine | AP53: 2 | AQ53: # | AR53: =278*2 -> 556 | AS53: # | AT53: 451 | AU53: no | AV53: yes | AW53: PCR if Ag Test positive | AX53: # | AY53: # | AZ53: # | BA53: # | BB53: # | BC53: # | BD53: # | BE53: # | BF53: =SUM(BG53:BJ53) -> 0 | BG53: # | BH53: # | BI53: # | BJ53: # | BK53: =IFERROR(IF(BJ53<>"#",BJ53+BI53,"#"),"#") -> # | BL53: =SUM(BM53:BP53) -> 0 | BM53: # | BN53: # | BO53: # | BP53: # | BQ53: # | BR53: # | BS53: =SUM(BT53:BW53) -> 0 | BT53: # | BU53: # | BV53: # | BW53: # | BX53: =IFERROR(IF(BU53<>"#",BU53+BT53,"#"),"#") -> # | BY53: # | BZ53: # | CA53: # | CB53: # | CC53: # | CD53: # | CE53: # | CF53: # | CG53: # | CH53: # | CI53: # | CJ53: # | CK53: # | CL53: # | CM53: # | CN53: # | CO53: # | CP53: # | CQ53: # | CR53: # | CS53: # | CT53: # | CU53: # | CV53: # | CW53: # | CX53: # | CY53: # | CZ53: # | DA53: # | DB53: # | DC53: # | DD53: # | DE53: # | DF53: # | DG53: # | DH53: include | DI53: #
A54: a58_0 | B54: Pudasaini, S., et al. | C54: prosp. cohort | D54: 44420 | E54: 44433 | F54: Germany | G54: EU; School within Germany (exact location unclear) | H54: unclear | I54: 59925.317 | J54: unclear | K54: 130 | L54: 126 | M54: 126 | N54: =MAX(K54:M54) -> 130 | O54: Number of people that reported self-testing results | P54: # | Q54: # | R54: # | S54: # | T54: # | U54: # | V54: # | W54: 64 | X54: 59 | Y54: 3 | Z54: K-12 students and staff | AA54: 36 | AB54: # | AC54: =90 -> 90 | AD54: =IF(AND(AA54=0,AC54=0),1,0) -> 0 | AE54: # | AF54: 3 | AG54: unknown | AH54: 49 individuals had received two doses of vaccination | AI54: # | AJ54: Unclear | AK54: # | AL54: # | AM54: # | AN54: Unclear | AO54: Routine | AP54: 3.5 | AQ54: # | AR54: # | AS54: # | AT54: # | AU54: no | AV54: no | AW54: pooled RT-PCR at the d = 0 and d = 13 of the study period | AX54: # | AY54: # | AZ54: 0 | BA54: # | BB54: # | BC54: # | BD54: # | BE54: # | BF54: =SUM(BG54:BJ54) -> 0 | BG54: # | BH54: # | BI54: # | BJ54: # | BK54: =IFERROR(IF(BJ54<>"#",BJ54+BI54,"#"),"#") -> # | BL54: =SUM(BM54:BP54) -> 124 | BM54: 0 | BN54: 124 | BO54: # | BP54: # | BQ54: # | BR54: # | BS54: =SUM(BT54:BW54) -> 0 | BT54: # | BU54: # | BV54: # | BW54: # | BX54: =IFERROR(IF(BU54<>"#",BU54+BT54,"#"),"#") -> # | BY54: # | BZ54: # | CA54: 30 min. | CB54: # | CC54: # | CD54: Continue school music trip | CE54: # | CF54: # | CG54: # | CH54: # | CI54: # | CJ54: # | CK54: # | CL54: # | CM54: # | CN54: # | CO54: # | CP54: # | CQ54: # | CR54: # | CS54: # | CT54: # | CU54: # | CV54: # | CW54: # | CX54: allowed school field trip to take place | CY54: # | CZ54: some students had less anxiety after trip, teachers had less fear of infection | DA54: # | DB54: # | DC54: # | DD54: # | DE54: # | DF54: # | DG54: # | DH54: # | DI54: #
A55: a59_0 | B55: Ryan, F., et al. | C55: retrosp. Cohort | D55: 44189 | E55: 44314 | F55: United Kingdom | G55: UK; Adult care home staff across UK | H55: unclear | I55: 56660.868 | J55: unclear | K55: # | L55: # | M55: 189364 | N55: =MAX(K55:M55) -> 189364 | O55: Number of people that collected / were sent self-tests | P55: # | Q55: # | R55: 45 | S55: 33 | T55: 55 | U55: 18 | V55: 65 | W55: # | X55: # | Y55: # | Z55: Healthcare Professionals | AA55: 0 | AB55: 189364 | AC55: 0 | AD55: =IF(AND(AA55=0,AC55=0),1,0) -> 1 | AE55: # | AF55: # | AG55: unknown | AH55: # | AI55: # | AJ55: Innova COVID-19 self-test | AK55: no | AL55: Nose-throat | AM55: Unclear | AN55: Unclear | AO55: Routine | AP55: 2 | AQ55: =ROUND(('Data extracted'!E55-'Data extracted'!D55)/7,0) -> 18 | AR55: =AQ55*AP55*M55 -> 6817104 | AS55: # | AT55: 1094413 | AU55: no | AV55: no | AW55: Weekly RT-PCR testing | AX55: CONTINUE | AY55: 1094413 | AZ55: 1142 | BA55: =AY55-AZ55 -> 1093271 | BB55: # | BC55: # | BD55: RT-PCR | BE55: Combined nose and throat | BF55: =SUM(BG55:BJ55) -> 644480 | BG55: 440 | BH55: 1053 | BI55: 642672 | BJ55: 315 | BK55: =IFERROR(IF(BJ55<>"#",BJ55+BI55,"#"),"#") -> 642987 | BL55: =SUM(BM55:BP55) -> 0 | BM55: # | BN55: # | BO55: # | BP55: # | BQ55: # | BR55: # | BS55: =SUM(BT55:BW55) -> 0 | BT55: # | BU55: # | BV55: # | BW55: # | BX55: =IFERROR(IF(BU55<>"#",BU55+BT55,"#"),"#") -> # | BY55: RT-PCR | BZ55: # | CA55: 30 min. | CB55: Do not to attend work / immediately leave the workplace and remain at home in self-isolation for 10 days (as per UK Government requirements at the time) and take a confirmatory PCR test | CC55: compulsory (by government guidelines) for the first test of every week | CD55: Continue work and routine testing | CE55: # | CF55: # | CG55: # | CH55: # | CI55: # | CJ55: # | CK55: # | CL55: # | CM55: # | CN55: # | CO55: # | CP55: # | CQ55: # | CR55: # | CS55: # | CT55: # | CU55: # | CV55: # | CW55: # | CX55: # | CY55: # | CZ55: # | DA55: # | DB55: # | DC55: # | DD55: # | DE55: # | DF55: # | DG55: # | DH55: # | DI55: #
A56: a60_0 | B56: Smit, T., et al. | C56: prosp. cohort | D56: 44837 | E56: 45067 | F56: Netherlands | G56: EU; Adults across Netherlands | H56: unclear | I56: 73173.715 | J56: unclear | K56: # | L56: 17030 | M56: # | N56: =MAX(K56:M56) -> 17030 | O56: Number of people that collected / were sent self-tests | P56: # | Q56: # | R56: # | S56: # | T56: # | U56: # | V56: # | W56: 9726 | X56: 7271 | Y56: 33 | Z56: General population | AA56: # | AB56: # | AC56: # | AD56: =IF(AND(AA56=0,AC56=0),1,0) -> 0 | AE56: # | AF56: # | AG56: unknown | AH56: # | AI56: # | AJ56: MP Biomedicals | AK56: no | AL56: # | AM56: Study | AN56: Home | AO56: Routine | AP56: Unclear | AQ56: =ROUND(('Data extracted'!E56-'Data extracted'!D56)/7,0) -> 33 | AR56: # | AS56: # | AT56: # | AU56: no | AV56: no | AW56: # | AX56: CONTINUE | AY56: 5571 | AZ56: 1475 | BA56: 4096 | BB56: # | BC56: # | BD56: RT-PCR | BE56: Nose and throat | BF56: =SUM(BG56:BJ56) -> 5571 | BG56: 1417 | BH56: 295 | BI56: 3801 | BJ56: 58 | BK56: =IFERROR(IF(BJ56<>"#",BJ56+BI56,"#"),"#") -> 3859 | BL56: =SUM(BM56:BP56) -> 0 | BM56: # | BN56: # | BO56: # | BP56: # | BQ56: # | BR56: # | BS56: =SUM(BT56:BW56) -> 0 | BT56: # | BU56: # | BV56: # | BW56: # | BX56: =IFERROR(IF(BU56<>"#",BU56+BT56,"#"),"#") -> # | BY56: RT-PCR | BZ56: # | CA56: # | CB56: Send swab for confirmatory testing to study personnel | CC56: compulsory (by study design) | CD56: Random sample of symptomatic individuals were to send in nose + throat swab for RT-PCR testing despite negative self-test result | CE56: # | CF56: # | CG56: # | CH56: # | CI56: # | CJ56: # | CK56: # | CL56: # | CM56: # | CN56: # | CO56: # | CP56: # | CQ56: # | CR56: # | CS56: # | CT56: # | CU56: # | CV56: # | CW56: # | CX56: # | CY56: # | CZ56: # | DA56: # | DB56: # | DC56: # | DD56: # | DE56: include | DF56: # | DG56: # | DH56: # | DI56: #
A57: a61_0 | B57: Soni, A., et al. (a) | C57: prosp. cohort | D57: 44351 | E57: 44419 | F57: United States | G57: NA; Ann Arbor and Ypsilanti, Washtenaw County, Michigan | H57: City; semi-dense | I57: 89598.86 | J57: unclear | K57: # | L57: # | M57: # | N57: # | O57: n/a | P57: # | Q57: # | R57: # | S57: # | T57: # | U57: # | V57: # | W57: # | X57: # | Y57: # | Z57: General population | AA57: # | AB57: # | AC57: # | AD57: =IF(AND(AA57=0,AC57=0),1,0) -> 0 | AE57: # | AF57: # | AG57: unknown | AH57: # | AI57: # | AJ57: QuickVue | AK57: no | AL57: AN / MT | AM57: Study | AN57: Unclear | AO57: Routine | AP57: 3 | AQ57: =ROUND(('Data extracted'!E57-'Data extracted'!D57)/7,0) -> 10 | AR57: # | AS57: # | AT57: # | AU57: no | AV57: no | AW57: Recommendation to receive PCR test when developing symptoms | AX57: # | AY57: # | AZ57: # | BA57: # | BB57: # | BC57: # | BD57: # | BE57: # | BF57: =SUM(BG57:BJ57) -> 0 | BG57: # | BH57: # | BI57: # | BJ57: # | BK57: =IFERROR(IF(BJ57<>"#",BJ57+BI57,"#"),"#") -> # | BL57: =SUM(BM57:BP57) -> 0 | BM57: # | BN57: # | BO57: # | BP57: # | BQ57: # | BR57: # | BS57: =SUM(BT57:BW57) -> 0 | BT57: # | BU57: # | BV57: # | BW57: # | BX57: =IFERROR(IF(BU57<>"#",BU57+BT57,"#"),"#") -> # | BY57: # | BZ57: # | CA57: 15min. | CB57: Stop testing individual with positive result and give remaining test ot other household members; encouraged to report result to health authority | CC57: # | CD57: Continue at-home testing | CE57: # | CF57: # | CG57: # | CH57: # | CI57: # | CJ57: # | CK57: # | CL57: # | CM57: difference intervention versus control -0.016 cases per day (95% CI: -0.020 to -0.013) | CN57: # | CO57: # | CP57: # | CQ57: # | CR57: # | CS57: # | CT57: # | CU57: # | CV57: # | CW57: # | CX57: # | CY57: # | CZ57: # | DA57: # | DB57: # | DC57: # | DD57: # | DE57: # | DF57: # | DG57: # | DH57: # | DI57: #
A58: a62_0 | B58: Soni, A., et al. (b) | C58: prosp. cohort | D58: 44487 | E58: 44607 | F58: United States | G58: NA; Adults across the US | H58: unclear | I58: 89598.86 | J58: unclear | K58: # | L58: 7303 | M58: 6711 | N58: =MAX(K58:M58) -> 7303 | O58: Number of people eligible for self-testing | P58: # | Q58: # | R58: # | S58: # | T58: # | U58: # | V58: # | W58: # | X58: # | Y58: # | Z58: General population | AA58: 0 | AB58: 7303 | AC58: 0 | AD58: =IF(AND(AA58=0,AC58=0),1,0) -> 1 | AE58: # | AF58: # | AG58: unknown | AH58: # | AI58: # | AJ58: Quidel QuickVue At-Home OTC COVID-19 Test, Abbott BinaxNOW COVID-19 Antigen Self Test, or BD VeritorTM At-Home COVID-19 Test | AK58: yes | AL58: AN / MT | AM58: Study | AN58: Home | AO58: Routine | AP58: 3.5 | AQ58: 2.1428571 | AR58: =8*M58 -> 53688 | AS58: # | AT58: # | AU58: no | AV58: no | AW58: RT-PCR test every 48h (for every Ag-RDT self-test but the last) | AX58: CONTINUE | AY58: # | AZ58: # | BA58: # | BB58: # | BC58: # | BD58: RT-PCR | BE58: # | BF58: =SUM(BG58:BJ58) -> 0 | BG58: # | BH58: # | BI58: # | BJ58: # | BK58: =IFERROR(IF(BJ58<>"#",BJ58+BI58,"#"),"#") -> # | BL58: =SUM(BM58:BP58) -> 5989 | BM58: # | BN58: 5989 | BO58: # | BP58: # | BQ58: RT-PCR | BR58: # | BS58: =SUM(BT58:BW58) -> 5989 | BT58: # | BU58: # | BV58: 5989 | BW58: # | BX58: =IFERROR(IF(BU58<>"#",BU58+BT58,"#"),"#") -> # | BY58: # | BZ58: # | CA58: # | CB58: Contact health-care provider for any medical questions; continue routine testing | CC58: # | CD58: Continue routine testing | CE58: # | CF58: # | CG58: # | CH58: # | CI58: # | CJ58: # | CK58: # | CL58: # | CM58: # | CN58: # | CO58: # | CP58: # | CQ58: # | CR58: # | CS58: # | CT58: # | CU58: # | CV58: # | CW58: # | CX58: # | CY58: # | CZ58: # | DA58: # | DB58: "Throughout the study, there were 11,646 contacts between coordinators and 4,389 distinct participants. This accounted for 33,356 minutes of coordination time." | DC58: # | DD58: # | DE58: # | DF58: # | DG58: # | DH58: # | DI58: #
A59: a63_0 | B59: Stemler, J., et al. | C59: prosp. cohort | D59: 44735 | E59: 44750 | F59: Germany | G59: EU; Children (≥12 years) and adults across Germany | H59: unclear | I59: 59925.317 | J59: unclear | K59: 2400 | L59: 500 | M59: 419 | N59: =MAX(K59:M59) -> 2400 | O59: Number of people that collected self-tests | P59: # | Q59: # | R59: 44 | S59: 34 | T59: 57 | U59: 12 | V59: 80 | W59: 239 | X59: 180 | Y59: # | Z59: General population | AA59: # | AB59: # | AC59: # | AD59: =IF(AND(AA59=0,AC59=0),1,0) -> 0 | AE59: # | AF59: # | AG59: unknown | AH59: # | AI59: # | AJ59: Newgene COVID-19 Antigen Test Kit | AK59: no | AL59: # | AM59: Study | AN59: Home | AO59: Single | AP59: # | AQ59: # | AR59: 500 | AS59: # | AT59: 419 | AU59: no | AV59: no | AW59: # | AX59: # | AY59: =SUM(AZ59:BC59) -> 425 | AZ59: 7 | BA59: 412 | BB59: 6 | BC59: # | BD59: RT-PCR | BE59: # | BF59: =SUM(BG59:BJ59) -> 4 | BG59: 4 | BH59: # | BI59: # | BJ59: # | BK59: =IFERROR(IF(BJ59<>"#",BJ59+BI59,"#"),"#") -> # | BL59: =SUM(BM59:BP59) -> 425 | BM59: 7 | BN59: 412 | BO59: 6 | BP59: # | BQ59: RT-PCR | BR59: # | BS59: =SUM(BT59:BW59) -> 4 | BT59: 4 | BU59: # | BV59: # | BW59: # | BX59: =IFERROR(IF(BU59<>"#",BU59+BT59,"#"),"#") -> # | BY59: # | BZ59: # | CA59: # | CB59: # | CC59: # | CD59: # | CE59: # | CF59: # | CG59: # | CH59: # | CI59: # | CJ59: # | CK59: # | CL59: # | CM59: # | CN59: # | CO59: # | CP59: # | CQ59: # | CR59: # | CS59: # | CT59: # | CU59: # | CV59: # | CW59: # | CX59: # | CY59: # | CZ59: # | DA59: # | DB59: # | DC59: # | DD59: # | DE59: # | DF59: # | DG59: # | DH59: # | DI59: #
A60: a64_1 | B60: Stohr, J.J.J.M., et al. | C60: prosp. cohort | D60: 44188 | E60: 44213 | F60: Netherlands | G60: EU; Adults in Tilburg, Noord- Brabant | H60: City | I60: 73173.715 | J60: unclear | K60: # | L60: 1758 | M60: 1595 | N60: =MAX(K60:M60) -> 1758 | O60: Number of people that reported self-testing results | P60: # | Q60: # | R60: 41 | S60: 29 | T60: 54 | U60: # | V60: # | W60: 877 | X60: 718 | Y60: # | Z60: General population | AA60: 1114 | AB60: 481 | AC60: 0 | AD60: =IF(AND(AA60=0,AC60=0),1,0) -> 0 | AE60: # | AF60: # | AG60: unknown | AH60: # | AI60: # | AJ60: BD-RDT | AK60: no | AL60: AN / MT | AM60: Testing Site | AN60: Home | AO60: Single | AP60: # | AQ60: # | AR60: 1758 | AS60: # | AT60: 1595 | AU60: no | AV60: no | AW60: RT-PCR test for every Ag-RDT performed | AX60: STOPP self-testing since testing was only done once | AY60: =SUM(AZ60:BC60) -> 1595 | AZ60: 88 | BA60: 1476 | BB60: 31 | BC60: # | BD60: RT-PCR | BE60: NP / OP | BF60: =SUM(BG60:BJ60) -> 1556 | BG60: 86 | BH60: 89 | BI60: 1379 | BJ60: 2 | BK60: =IFERROR(IF(BJ60<>"#",BJ60+BI60,"#"),"#") -> 1381 | BL60: =SUM(BM60:BP60) -> 1595 | BM60: 88 | BN60: 1476 | BO60: 31 | BP60: # | BQ60: RT-PCR | BR60: NP / OP | BS60: =SUM(BT60:BW60) -> 1556 | BT60: 86 | BU60: 89 | BV60: 1379 | BW60: 2 | BX60: =IFERROR(IF(BU60<>"#",BU60+BT60,"#"),"#") -> 175 | BY60: RT-PCR | BZ60: # | CA60: # | CB60: # | CC60: # | CD60: # | CE60: # | CF60: # | CG60: # | CH60: # | CI60: # | CJ60: # | CK60: # | CL60: # | CM60: # | CN60: # | CO60: # | CP60: # | CQ60: # | CR60: # | CS60: # | CT60: # | CU60: # | CV60: # | CW60: # | CX60: # | CY60: # | CZ60: # | DA60: # | DB60: # | DC60: # | DD60: # | DE60: include | DF60: include | DG60: # | DH60: # | DI60: #
A61: a64_2 | B61: Stohr, J.J.J.M., et al. | C61: prosp. cohort | D61: 44188 | E61: 44213 | F61: Netherlands | G61: EU; Adults in Tilburg, Noord- Brabant | H61: City | I61: 73173.715 | J61: unclear | K61: # | L61: 1771 | M61: 1606 | N61: =MAX(K61:M61) -> 1771 | O61: Number of people that reported self-testing results | P61: # | Q61: # | R61: 41 | S61: 29 | T61: 54 | U61: # | V61: # | W61: 918 | X61: 688 | Y61: # | Z61: General population | AA61: 1102 | AB61: 504 | AC61: 0 | AD61: =IF(AND(AA61=0,AC61=0),1,0) -> 0 | AE61: # | AF61: # | AG61: unknown | AH61: # | AI61: # | AJ61: Roche RDT | AK61: no | AL61: AN / MT | AM61: Testing Site | AN61: Home | AO61: Single | AP61: # | AQ61: # | AR61: 1771 | AS61: # | AT61: 1606 | AU61: no | AV61: no | AW61: RT-PCR test for every Ag-RDT performed | AX61: STOPP self-testing since testing was only done once | AY61: =SUM(AZ61:BC61) -> 1606 | AZ61: 122 | BA61: 1467 | BB61: 17 | BC61: # | BD61: RT-PCR | BE61: NP / OP | BF61: =SUM(BG61:BJ61) -> 1583 | BG61: 118 | BH61: 74 | BI61: 1387 | BJ61: 4 | BK61: =IFERROR(IF(BJ61<>"#",BJ61+BI61,"#"),"#") -> 1391 | BL61: =SUM(BM61:BP61) -> 1606 | BM61: 122 | BN61: 1467 | BO61: 17 | BP61: # | BQ61: RT-PCR | BR61: NP / OP | BS61: =SUM(BT61:BW61) -> 1583 | BT61: 118 | BU61: 74 | BV61: 1387 | BW61: 4 | BX61: =IFERROR(IF(BU61<>"#",BU61+BT61,"#"),"#") -> 192 | BY61: RT-PCR | BZ61: # | CA61: # | CB61: # | CC61: # | CD61: # | CE61: # | CF61: # | CG61: # | CH61: # | CI61: # | CJ61: # | CK61: # | CL61: # | CM61: # | CN61: # | CO61: # | CP61: # | CQ61: # | CR61: # | CS61: # | CT61: # | CU61: # | CV61: # | CW61: # | CX61: # | CY61: # | CZ61: # | DA61: # | DB61: # | DC61: # | DD61: # | DE61: include | DF61: include | DG61: # | DH61: # | DI61: #
A62: a65_0 | B62: Tinker, S.C., et al. | C62: prosp. cohort | D62: 44249 | E62: 44306 | F62: United States | G62: NA; Students and staff of a residential college in Georgia | H62: City | I62: 89598.86 | J62: unclear | K62: # | L62: # | M62: 1347 | N62: =MAX(K62:M62) -> 1347 | O62: Number of people that reported self-testing results | P62: # | Q62: # | R62: # | S62: # | T62: # | U62: # | V62: # | W62: 955 | X62: 392 | Y62: # | Z62: University students and staff | AA62: 0 | AB62: 1347 | AC62: 0 | AD62: =IF(AND(AA62=0,AC62=0),1,0) -> 1 | AE62: # | AF62: # | AG62: unknown | AH62: # | AI62: 371 seropositive | AJ62: Quidel QuickVue At-Home COVID-19 Test | AK62: no | AL62: AN / MT | AM62: unclear | AN62: Home | AO62: Routine | AP62: 2 | AQ62: 7 | AR62: =AQ62*AP62*M62 -> 18858 | AS62: # | AT62: 9971 | AU62: no | AV62: no | AW62: one-time PCR during week 3 of the study, mass vacination events, local COVID-19 prevention strategies | AX62: Unclear | AY62: =SUM(AZ62:BC62) -> 2 | AZ62: 2 | BA62: # | BB62: # | BC62: # | BD62: RT-PCR | BE62: # | BF62: =SUM(BG62:BJ62) -> 663 | BG62: 2 | BH62: # | BI62: 661 | BJ62: 0 | BK62: =IFERROR(IF(BJ62<>"#",BJ62+BI62,"#"),"#") -> 661 | BL62: =SUM(BM62:BP62) -> 11 | BM62: 11 | BN62: # | BO62: 0 | BP62: # | BQ62: RT-PCR and antibody testing | BR62: unclear | BS62: =SUM(BT62:BW62) -> 332 | BT62: 3 | BU62: 4 | BV62: =324-3-4 -> 317 | BW62: 8 | BX62: =IFERROR(IF(BU62<>"#",BU62+BT62,"#"),"#") -> 7 | BY62: PCR | BZ62: # | CA62: 10 min. | CB62: PCR confirmatory testing, self-isolate | CC62: compulsory (by study design) | CD62: continue college life and to test twice-weekly until end of study | CE62: # | CF62: # | CG62: # | CH62: # | CI62: # | CJ62: # | CK62: # | CL62: # | CM62: # | CN62: # | CO62: # | CP62: # | CQ62: # | CR62: # | CS62: # | CT62: # | CU62: # | CV62: # | CW62: # | CX62: # | CY62: # | CZ62: # | DA62: # | DB62: # | DC62: # | DD62: # | DE62: # | DF62: # | DG62: # | DH62: # | DI62: #
A63: a66_0 | B63: Tsang, N.N.Y., et al. | C63: prosp. cohort | D63: 44621 | E63: 44666 | F63: Hong Kong | G63: AS; Children and adults across Hong Kong | H63: City | I63: 56843.908 | J63: unclear | K63: 8636 | L63: 8636 | M63: 8636 | N63: =MAX(K63:M63) -> 8636 | O63: Number of people eligible for self-testing | P63: # | Q63: # | R63: # | S63: # | T63: # | U63: # | V63: # | W63: 4723 | X63: 3913 | Y63: # | Z63: General population | AA63: 632 | AB63: # | AC63: # | AD63: =IF(AND(AA63=0,AC63=0),1,0) -> 0 | AE63: 1783 chronic illness | AF63: # | AG63: unknown | AH63: Unvaccinated: 764 individuals; One dose: 639 individuals; Two doses: 3,240 individuals; Three doses: 3,993 individuals | AI63: # | AJ63: INDICAID; PHASE Scientific, Hong Kong | AK63: no | AL63: Nose-throat | AM63: Study | AN63: Unclear | AO63: Routine | AP63: 1 | AQ63: =ROUND(('Data extracted'!E63-'Data extracted'!D63)/7,0) -> 6 | AR63: =AQ63*AP63*M63 -> 51816 | AS63: # | AT63: # | AU63: no | AV63: no | AW63: Evaluation of vaccination efficacy | AX63: # | AY63: # | AZ63: # | BA63: # | BB63: # | BC63: # | BD63: # | BE63: # | BF63: =SUM(BG63:BJ63) -> 0 | BG63: # | BH63: # | BI63: # | BJ63: # | BK63: =IFERROR(IF(BJ63<>"#",BJ63+BI63,"#"),"#") -> # | BL63: =SUM(BM63:BP63) -> 8636 | BM63: 903 | BN63: 7733 | BO63: # | BP63: # | BQ63: # | BR63: # | BS63: =SUM(BT63:BW63) -> 0 | BT63: # | BU63: # | BV63: # | BW63: # | BX63: =IFERROR(IF(BU63<>"#",BU63+BT63,"#"),"#") -> # | BY63: C19ST | BZ63: # | CA63: # | CB63: Report result to study team and exit study | CC63: # | CD63: Report result to study team and continue routine testing | CE63: # | CF63: # | CG63: # | CH63: # | CI63: # | CJ63: # | CK63: # | CL63: # | CM63: # | CN63: # | CO63: # | CP63: # | CQ63: # | CR63: # | CS63: # | CT63: # | CU63: # | CV63: # | CW63: # | CX63: # | CY63: # | CZ63: # | DA63: # | DB63: # | DC63: # | DD63: # | DE63: # | DF63: # | DG63: include | DH63: include | DI63: #
A64: a67_0 | B64: Tsao, J., et al. | C64: prosp. cohort | D64: 44562 | E64: 44572 | F64: United States | G64: NA; Student athletes at Stanford University | H64: City | I64: 89598.86 | J64: unclear | K64: 723 | L64: 723 | M64: 723 | N64: =MAX(K64:M64) -> 723 | O64: Number of people eligible for self-testing | P64: # | Q64: # | R64: # | S64: # | T64: # | U64: 17 | V64: 23 | W64: 376 | X64: # | Y64: 347 | Z64: University students and staff | AA64: 45 | AB64: 28 | AC64: 650 | AD64: =IF(AND(AA64=0,AC64=0),1,0) -> 0 | AE64: # | AF64: # | AG64: unknown | AH64: 709 vaccinated (2-dose Pfizer or Moderna or 1-dose Johnson & Johnson vaccines) | AI64: # | AJ64: BinaxNOW; Abbott Laboratories | AK64: no | AL64: AN / MT | AM64: # | AN64: Unclear | AO64: Single | AP64: # | AQ64: # | AR64: # | AS64: 723 | AT64: 723 | AU64: no | AV64: no | AW64: # | AX64: # | AY64: =SUM(AZ64:BA64) -> 723 | AZ64: 47 | BA64: 676 | BB64: # | BC64: # | BD64: RT-PCR | BE64: # | BF64: =SUM(BG64:BJ64) -> 700 | BG64: 23 | BH64: 27 | BI64: 649 | BJ64: 1 | BK64: =IFERROR(IF(BJ64<>"#",BJ64+BI64,"#"),"#") -> 650 | BL64: =SUM(BM64:BN64) -> 723 | BM64: 47 | BN64: 676 | BO64: # | BP64: # | BQ64: RT-PCR | BR64: # | BS64: =SUM(BT64:BW64) -> 700 | BT64: 23 | BU64: 27 | BV64: 649 | BW64: 1 | BX64: =IFERROR(IF(BU64<>"#",BU64+BT64,"#"),"#") -> 50 | BY64: C19ST (for symptomatic individuals) | BZ64: 30 min. (for symptomatic individuals) | CA64: 30 min. | CB64: RT-PCR confirmatory testing if asymptomatic; isolate if symptomatic ("presumed positive") | CC64: mixed - compulsory (by study design) only if C19ST positive and asymptomatic | CD64: # | CE64: # | CF64: # | CG64: # | CH64: # | CI64: # | CJ64: # | CK64: # | CL64: # | CM64: # | CN64: # | CO64: # | CP64: # | CQ64: # | CR64: # | CS64: # | CT64: # | CU64: # | CV64: # | CW64: # | CX64: # | CY64: # | CZ64: # | DA64: # | DB64: # | DC64: # | DD64: # | DE64: # | DF64: include | DG64: include | DH64: include | DI64: #
A65: a68_0 | B65: Tulloch, J.S.P., et al. | C65: prosp. cohort | D65: 44166 | E65: 44206 | F65: United Kingdom | G65: UK; Liverpool; staff of 11 care-homes | H65: City | I65: 56660.868 | J65: unclear | K65: 498 | L65: 407 | M65: # | N65: =MAX(K65:M65) -> 498 | O65: Number of people eligible for self-testing | P65: # | Q65: # | R65: # | S65: # | T65: # | U65: # | V65: # | W65: # | X65: # | Y65: # | Z65: Healthcare Professionals | AA65: # | AB65: # | AC65: # | AD65: =IF(AND(AA65=0,AC65=0),1,0) -> 0 | AE65: # | AF65: # | AG65: unknown | AH65: # | AI65: # | AJ65: Innova LFD | AK65: no | AL65: # | AM65: Employer | AN65: Work | AO65: Routine | AP65: 2 | AQ65: =ROUND(('Data extracted'!E65-'Data extracted'!D65)/7,0) -> 6 | AR65: 4884 | AS65: # | AT65: 1638 | AU65: no | AV65: no | AW65: Weekly RT-PCR testing | AX65: # | AY65: =SUM(AZ65:BC65) -> 1638 | AZ65: 5 | BA65: 1633 | BB65: 0 | BC65: 0 | BD65: RT-PCR | BE65: # | BF65: =SUM(BG65:BJ65) -> 828 | BG65: 5 | BH65: # | BI65: 823 | BJ65: 0 | BK65: =IFERROR(IF(BJ65<>"#",BJ65+BI65,"#"),"#") -> 823 | BL65: =SUM(BM65:BP65) -> 0 | BM65: # | BN65: # | BO65: # | BP65: # | BQ65: # | BR65: # | BS65: =SUM(BT65:BW65) -> 0 | BT65: # | BU65: # | BV65: # | BW65: # | BX65: =IFERROR(IF(BU65<>"#",BU65+BT65,"#"),"#") -> # | BY65: # | BZ65: # | CA65: # | CB65: # | CC65: # | CD65: # | CE65: # | CF65: # | CG65: # | CH65: # | CI65: # | CJ65: # | CK65: compared to other care homes, no difference in number proportion or size of outbreaks (all care homes were of comparable size) | CL65: 0.31 positive per 100 LFD performed | CM65: # | CN65: # | CO65: # | CP65: # | CQ65: # | CR65: # | CS65: # | CT65: # | CU65: # | CV65: # | CW65: # | CX65: # | CY65: # | CZ65: # | DA65: # | DB65: # | DC65: # | DD65: # | DE65: # | DF65: # | DG65: # | DH65: # | DI65: #
A66: a69_0 | B66: UK Health Security Agency | C66: prosp. cohort | D66: 44205 | E66: 44255 | F66: United Kingdom | G66: UK; Health care workers in NHS hospitals across the UK | H66: City | I66: 56660.868 | J66: unclear | K66: 138 | L66: 111 | M66: 111 | N66: =MAX(K66:M66) -> 138 | O66: Number of people eligible for self-testing | P66: # | Q66: # | R66: # | S66: # | T66: # | U66: # | V66: # | W66: 54 | X66: # | Y66: 84 | Z66: Healthcare Professionals | AA66: # | AB66: # | AC66: # | AD66: =IF(AND(AA66=0,AC66=0),1,0) -> 0 | AE66: # | AF66: Contact with a confirmed COVID-19 case | AG66: unknown | AH66: # | AI66: # | AJ66: Unclear | AK66: # | AL66: # | AM66: # | AN66: Home | AO66: Routine | AP66: 7 | AQ66: 1 | AR66: =AQ66*AP66*M66 -> 777 | AS66: # | AT66: 719 | AU66: no | AV66: no | AW66: RT-PCR on d5 and d8 in some NHS trusts | AX66: Unclear | AY66: =SUM(AZ66:BC66) -> 1 | AZ66: 1 | BA66: # | BB66: # | BC66: # | BD66: RT-PCR | BE66: # | BF66: =SUM(BG66:BJ66) -> 56 | BG66: 1 | BH66: # | BI66: 55 | BJ66: 0 | BK66: =IFERROR(IF(BJ66<>"#",BJ66+BI66,"#"),"#") -> 55 | BL66: 111 | BM66: 1 | BN66: 110 | BO66: # | BP66: # | BQ66: # | BR66: # | BS66: =SUM(BT66:BW66) -> 0 | BT66: # | BU66: # | BV66: # | BW66: # | BX66: =IFERROR(IF(BU66<>"#",BU66+BT66,"#"),"#") -> # | BY66: RT-PCR | BZ66: # | CA66: 30 min. | CB66: Confirmatory PCR test; self-isolate until PCR result available and when positive; identify close contacts and offer daily testing or self-isolation | CC66: compulsory (by study design) | CD66: Continue work and routine testing | CE66: # | CF66: # | CG66: # | CH66: # | CI66: # | CJ66: # | CK66: # | CL66: # | CM66: # | CN66: # | CO66: # | CP66: # | CQ66: # | CR66: # | CS66: # | CT66: # | CU66: # | CV66: # | CW66: # | CX66: 729 workdays lost averted | CY66: 729 days of self-isolation averted | CZ66: # | DA66: 729 workdays lost averted | DB66: high burden of initial setup, £67 per potential work absence averted (range: £33 to £140) | DC66: # | DD66: # | DE66: # | DF66: # | DG66: # | DH66: # | DI66: #
A67: a70_1 | B67: U. o. Liverpool | C67: prosp. cohort | D67: 44168 | E67: 44408 | F67: United Kingdom | G67: UK; Liverpool; inhabitants of the city region | H67: City; semi-dense | I67: 56660.868 | J67: unclear | K67: # | L67: # | M67: 321884 | N67: =MAX(K67:M67) -> 321884 | O67: Number of people that reported self-testing results | P67: # | Q67: # | R67: # | S67: # | T67: # | U67: # | V67: # | W67: # | X67: # | Y67: # | Z67: General population | AA67: # | AB67: # | AC67: # | AD67: =IF(AND(AA67=0,AC67=0),1,0) -> 0 | AE67: # | AF67: # | AG67: unknown | AH67: # | AI67: # | AJ67: Innova LFD | AK67: no | AL67: # | AM67: # | AN67: Home | AO67: Unclear | AP67: # | AQ67: # | AR67: # | AS67: # | AT67: 1900302 | AU67: no | AV67: no | AW67: City-wide Ag-RDT testing at testing centers; RT-PCR testing for symptomatic persons | AX67: # | AY67: =SUM(AZ67:BC67) -> 13942 | AZ67: 13942 | BA67: # | BB67: 0 | BC67: # | BD67: RT-PCR | BE67: # | BF67: =SUM(BG67:BJ67) -> 9809 | BG67: 8495 | BH67: # | BI67: # | BJ67: 1314 | BK67: =IFERROR(IF(BJ67<>"#",BJ67+BI67,"#"),"#") -> # | BL67: =SUM(BM67:BP67) -> 0 | BM67: # | BN67: # | BO67: # | BP67: # | BQ67: # | BR67: # | BS67: =SUM(BT67:BW67) -> 0 | BT67: # | BU67: # | BV67: # | BW67: # | BX67: =IFERROR(IF(BU67<>"#",BU67+BT67,"#"),"#") -> # | BY67: # | BZ67: # | CA67: # | CB67: Invitation to book a confirmatory PCR test | CC67: voluntary (invitation to do so) | CD67: # | CE67: # | CF67: # | CG67: # | CH67: # | CI67: # | CJ67: # | CK67: # | CL67: # | CM67: # | CN67: # | CO67: # | CP67: # | CQ67: # | CR67: # | CS67: # | CT67: # | CU67: # | CV67: # | CW67: # | CX67: # | CY67: # | CZ67: # | DA67: # | DB67: # | DC67: # | DD67: # | DE67: # | DF67: # | DG67: # | DH67: # | DI67: #
A68: a70_2 | B68: U. o. Liverpool | C68: prosp. cohort | D68: 44228 | E68: 44424 | F68: United Kingdom | G68: UK; Liverpool; city region | H68: City; semi-dense | I68: 56660.868 | J68: unclear | K68: # | L68: # | M68: # | N68: # | O68: n/a | P68: # | Q68: # | R68: # | S68: # | T68: # | U68: # | V68: # | W68: # | X68: # | Y68: # | Z68: Healthcare Professionals | AA68: # | AB68: # | AC68: # | AD68: =IF(AND(AA68=0,AC68=0),1,0) -> 0 | AE68: # | AF68: contact with a confirmed COVID-19 case | AG68: unknown | AH68: # | AI68: # | AJ68: Innova LFD | AK68: no | AL68: # | AM68: # | AN68: Home | AO68: Unclear | AP68: # | AQ68: # | AR68: # | AS68: # | AT68: # | AU68: no | AV68: no | AW68: City-wide Ag-RDT testing at testing centers; RT-PCR testing for symptomatic persons | AX68: # | AY68: # | AZ68: # | BA68: # | BB68: # | BC68: # | BD68: # | BE68: # | BF68: =SUM(BG68:BJ68) -> 0 | BG68: # | BH68: # | BI68: # | BJ68: # | BK68: =IFERROR(IF(BJ68<>"#",BJ68+BI68,"#"),"#") -> # | BL68: =SUM(BM68:BP68) -> 0 | BM68: # | BN68: # | BO68: # | BP68: # | BQ68: # | BR68: # | BS68: =SUM(BT68:BW68) -> 0 | BT68: # | BU68: # | BV68: # | BW68: # | BX68: =IFERROR(IF(BU68<>"#",BU68+BT68,"#"),"#") -> # | BY68: # | BZ68: # | CA68: # | CB68: # | CC68: # | CD68: exemption from isolation for 24h (go to work), then test again | CE68: # | CF68: # | CG68: # | CH68: # | CI68: # | CJ68: # | CK68: # | CL68: # | CM68: # | CN68: # | CO68: # | CP68: # | CQ68: # | CR68: # | CS68: # | CT68: # | CU68: # | CV68: # | CW68: # | CX68: continue work after a negative C19ST result despite recent contact to confimred SARS-CoV-2 case (Alerdly Hey workers) | CY68: none if test negative (for Alderly Hey workers) | CZ68: # | DA68: reduced | DB68: # | DC68: # | DD68: # | DE68: # | DF68: # | DG68: # | DH68: # | DI68: #
A69: a71_1 | B69: Wachinger, J., et al. | C69: prosp. cohort | D69: 44277 | E69: 44337 | F69: Germany | G69: EU; Teachers in southwestern Germany | H69: Semi-dense | I69: 59925.317 | J69: unclear | K69: 34 | L69: 21 | M69: # | N69: =MAX(K69:M69) -> 34 | O69: n/a | P69: # | Q69: # | R69: # | S69: # | T69: # | U69: # | V69: # | W69: # | X69: # | Y69: # | Z69: K-12 students and staff | AA69: # | AB69: # | AC69: # | AD69: =IF(AND(AA69=0,AC69=0),1,0) -> 0 | AE69: # | AF69: # | AG69: unknown | AH69: # | AI69: # | AJ69: Standard Q | AK69: no | AL69: AN / MT | AM69: School | AN69: Home | AO69: Routine | AP69: 3 | AQ69: =ROUND(('Data extracted'!E69-'Data extracted'!D69)/7,0) -> 9 | AR69: # | AS69: # | AT69: # | AU69: no | AV69: no | AW69: School safety measures (e.g., mask wearing) | AX69: # | AY69: 0 | AZ69: 0 | BA69: # | BB69: # | BC69: # | BD69: # | BE69: # | BF69: =SUM(BG69:BJ69) -> 0 | BG69: # | BH69: # | BI69: # | BJ69: # | BK69: =IFERROR(IF(BJ69<>"#",BJ69+BI69,"#"),"#") -> # | BL69: =SUM(BM69:BP69) -> 0 | BM69: 0 | BN69: # | BO69: # | BP69: # | BQ69: RT-PCR | BR69: # | BS69: =SUM(BT69:BW69) -> 0 | BT69: 0 | BU69: # | BV69: # | BW69: 0 | BX69: =IFERROR(IF(BU69<>"#",BU69+BT69,"#"),"#") -> # | BY69: # | BZ69: # | CA69: 15-30 min. | CB69: Notify school and local public health authority, self-isolate | CC69: # | CD69: Go to school, retest with the next interval | CE69: # | CF69: # | CG69: # | CH69: # | CI69: # | CJ69: # | CK69: General population: 54,3-154.1/100 000 | CL69: # | CM69: # | CN69: # | CO69: # | CP69: # | CQ69: # | CR69: # | CS69: # | CT69: # | CU69: # | CV69: # | CW69: # | CX69: # | CY69: # | CZ69: increased sense of safety | DA69: # | DB69: # | DC69: # | DD69: # | DE69: # | DF69: # | DG69: # | DH69: # | DI69: • A riskier behavior, e.g., less mask wearing than prior to implementing C19ST, compared to before the implementation of self-testing was not reported by any of the study participants
A70: a71_2 | B70: Wachinger, J., et al. | C70: prosp. cohort | D70: 44277 | E70: 44337 | F70: Germany | G70: EU; School students and their parents in southwestern Germany | H70: Semi-dense | I70: 59925.317 | J70: unclear | K70: 186 | L70: 109 | M70: # | N70: =MAX(K70:M70) -> 186 | O70: n/a | P70: # | Q70: # | R70: # | S70: # | T70: # | U70: # | V70: # | W70: # | X70: # | Y70: # | Z70: K-12 students and staff | AA70: # | AB70: # | AC70: # | AD70: =IF(AND(AA70=0,AC70=0),1,0) -> 0 | AE70: # | AF70: # | AG70: unknown | AH70: # | AI70: # | AJ70: Standard Q | AK70: no | AL70: AN / MT | AM70: School | AN70: Home | AO70: Routine | AP70: 3 | AQ70: =ROUND(('Data extracted'!E70-'Data extracted'!D70)/7,0) -> 9 | AR70: # | AS70: # | AT70: # | AU70: no | AV70: unclear | AW70: School safety measures (e.g., mask wearing) | AX70: Unclear | AY70: 0 | AZ70: 0 | BA70: # | BB70: # | BC70: # | BD70: # | BE70: # | BF70: =SUM(BG70:BJ70) -> 0 | BG70: # | BH70: # | BI70: # | BJ70: # | BK70: =IFERROR(IF(BJ70<>"#",BJ70+BI70,"#"),"#") -> # | BL70: =SUM(BM70:BP70) -> 0 | BM70: 0 | BN70: # | BO70: # | BP70: # | BQ70: RT-PCR | BR70: # | BS70: =SUM(BT70:BW70) -> 1 | BT70: 0 | BU70: 1 | BV70: # | BW70: 0 | BX70: =IFERROR(IF(BU70<>"#",BU70+BT70,"#"),"#") -> 1 | BY70: # | BZ70: # | CA70: 15-30 min. | CB70: Notify school and local public health authority, self-isolate | CC70: # | CD70: Go to school / send child to school, retest with the next interval | CE70: # | CF70: # | CG70: # | CH70: # | CI70: # | CJ70: # | CK70: General population: 54,3-154.1/100 000 | CL70: # | CM70: # | CN70: # | CO70: # | CP70: # | CQ70: # | CR70: # | CS70: # | CT70: # | CU70: # | CV70: # | CW70: # | CX70: # | CY70: # | CZ70: increased sense of safety | DA70: # | DB70: # | DC70: # | DD70: # | DE70: # | DF70: # | DG70: # | DH70: # | DI70: • A riskier behavior, e.g., less mask wearing than prior to implementing C19ST, compared to before the implementation of self-testing was not reported by any of the study participants
A71: a72_1 | B71: Willeit, P., et al. | C71: prosp. cohort | D71: 44256 | E71: 44273 | F71: Austria | G71: EU; Primary school students across Austria | H71: unclear | I71: 61694.026 | J71: free | K71: # | L71: # | M71: 360948 | N71: =MAX(K71:M71) -> 360948 | O71: Number of people that reported self-testing results | P71: # | Q71: # | R71: # | S71: # | T71: # | U71: # | V71: # | W71: # | X71: # | Y71: # | Z71: K-12 students and staff | AA71: 0 | AB71: 360948 | AC71: 0 | AD71: =IF(AND(AA71=0,AC71=0),1,0) -> 1 | AE71: # | AF71: # | AG71: unknown | AH71: not vaccinated | AI71: # | AJ71: Lepu Medical Sars-Cov-2 RDT; Flowflex Sars-Cov-2 RDT | AK71: no | AL71: AN / MT | AM71: School | AN71: School | AO71: Routine | AP71: 2 | AQ71: 3 | AR71: =AQ71*AP71*M71 -> 2165688 | AS71: # | AT71: 2133203 | AU71: no | AV71: yes | AW71: Self-isolation of symptomatic persons; gargle pool RT-PCR testing of 1% of the study population every 3 to 5 week | AX71: # | AY71: # | AZ71: # | BA71: # | BB71: # | BC71: # | BD71: # | BE71: # | BF71: =SUM(BG71:BJ71) -> 0 | BG71: # | BH71: # | BI71: # | BJ71: # | BK71: =IFERROR(IF(BJ71<>"#",BJ71+BI71,"#"),"#") -> # | BL71: =SUM(BM71:BP71) -> 1148 | BM71: 1148 | BN71: # | BO71: 0 | BP71: # | BQ71: "Further testing" | BR71: gargle lavage | BS71: =SUM(BT71:BW71) -> 0 | BT71: # | BU71: # | BV71: # | BW71: # | BX71: =IFERROR(IF(BU71<>"#",BU71+BT71,"#"),"#") -> # | BY71: # | BZ71: # | CA71: 30 min. | CB71: Leave school immediately and refer to local health authorities | CC71: # | CD71: continue in-class and repeat testing with the next interval | CE71: # | CF71: # | CG71: # | CH71: # | CI71: # | CJ71: # | CK71: General population: 198/100,000 | CL71: # | CM71: # | CN71: # | CO71: # | CP71: # | CQ71: # | CR71: # | CS71: # | CT71: # | CU71: # | CV71: # | CW71: # | CX71: # | CY71: # | CZ71: # | DA71: # | DB71: # | DC71: # | DD71: # | DE71: # | DF71: # | DG71: # | DH71: # | DI71: #
A72: a72_2 | B72: Willeit, P., et al. | C72: prosp. cohort | D72: 44256 | E72: 44273 | F72: Austria | G72: EU; Secondary school students across Austria | H72: unclear | I72: 61694.026 | J72: free | K72: # | L72: # | M72: 319672 | N72: =MAX(K72:M72) -> 319672 | O72: Number of people that reported self-testing results | P72: # | Q72: # | R72: # | S72: # | T72: # | U72: # | V72: # | W72: # | X72: # | Y72: # | Z72: K-12 students and staff | AA72: 0 | AB72: 319672 | AC72: 0 | AD72: =IF(AND(AA72=0,AC72=0),1,0) -> 1 | AE72: # | AF72: # | AG72: unknown | AH72: not vaccinated | AI72: # | AJ72: Lepu Medical Sars-Cov-2 RDT; Flowflex Sars-Cov-2 RDT | AK72: no | AL72: AN / MT | AM72: School | AN72: School | AO72: Routine | AP72: 1 | AQ72: 3 | AR72: =AQ72*AP72*M72 -> 959016 | AS72: # | AT72: 944631 | AU72: no | AV72: yes | AW72: Self-isolation of symptomatic persons; gargle pool RT-PCR testing of 1% of the study population every 3 to 5 week | AX72: # | AY72: # | AZ72: # | BA72: # | BB72: # | BC72: # | BD72: # | BE72: # | BF72: =SUM(BG72:BJ72) -> 0 | BG72: # | BH72: # | BI72: # | BJ72: # | BK72: =IFERROR(IF(BJ72<>"#",BJ72+BI72,"#"),"#") -> # | BL72: =SUM(BM72:BP72) -> 598 | BM72: 598 | BN72: # | BO72: 0 | BP72: # | BQ72: "Further testing" | BR72: gargle lavage | BS72: =SUM(BT72:BW72) -> 0 | BT72: # | BU72: # | BV72: # | BW72: # | BX72: =IFERROR(IF(BU72<>"#",BU72+BT72,"#"),"#") -> # | BY72: # | BZ72: # | CA72: 30 min. | CB72: Leave school immediately and refer to local health authorities | CC72: # | CD72: continue in-class and repeat testing with the next interval | CE72: # | CF72: # | CG72: # | CH72: # | CI72: # | CJ72: # | CK72: General population: 198/100,000 | CL72: # | CM72: # | CN72: # | CO72: # | CP72: # | CQ72: # | CR72: # | CS72: # | CT72: # | CU72: # | CV72: # | CW72: # | CX72: # | CY72: # | CZ72: # | DA72: # | DB72: # | DC72: # | DD72: # | DE72: # | DF72: # | DG72: # | DH72: # | DI72: #
A73: a72_3 | B73: Willeit, P., et al. | C73: prosp. cohort | D73: 44256 | E73: 44273 | F73: Austria | G73: EU; Schools teachers across Austria | H73: unclear | I73: 61694.026 | J73: free | K73: # | L73: # | M73: 104087 | N73: =MAX(K73:M73) -> 104087 | O73: Number of people that reported self-testing results | P73: # | Q73: # | R73: # | S73: # | T73: # | U73: # | V73: # | W73: # | X73: # | Y73: # | Z73: K-12 students and staff | AA73: 0 | AB73: 104087 | AC73: 0 | AD73: =IF(AND(AA73=0,AC73=0),1,0) -> 1 | AE73: # | AF73: # | AG73: unknown | AH73: unclear | AI73: # | AJ73: Lepu Medical Sars-Cov-2 RDT; Flowflex Sars-Cov-2 RDT | AK73: no | AL73: AN / MT | AM73: Employer | AN73: School | AO73: Routine | AP73: Unclear | AQ73: # | AR73: # | AS73: # | AT73: # | AU73: no | AV73: no | AW73: Self-isolation of symptomatic persons; gargle pool RT-PCR testing of 1% of the study population every 3 to 5 week | AX73: # | AY73: # | AZ73: # | BA73: # | BB73: # | BC73: # | BD73: # | BE73: # | BF73: =SUM(BG73:BJ73) -> 0 | BG73: # | BH73: # | BI73: # | BJ73: # | BK73: =IFERROR(IF(BJ73<>"#",BJ73+BI73,"#"),"#") -> # | BL73: =SUM(BM73:BP73) -> 912 | BM73: 912 | BN73: # | BO73: 0 | BP73: # | BQ73: "Further testing" | BR73: gargle lavage | BS73: =SUM(BT73:BW73) -> 0 | BT73: # | BU73: # | BV73: # | BW73: # | BX73: =IFERROR(IF(BU73<>"#",BU73+BT73,"#"),"#") -> # | BY73: # | BZ73: # | CA73: 30 min. | CB73: Leave school immediately and refer to local health authorities | CC73: # | CD73: continue in-class and repeat testing with the next interval | CE73: # | CF73: # | CG73: # | CH73: # | CI73: # | CJ73: # | CK73: General population: 198/100,000 | CL73: # | CM73: # | CN73: # | CO73: # | CP73: # | CQ73: # | CR73: # | CS73: # | CT73: # | CU73: # | CV73: # | CW73: # | CX73: # | CY73: # | CZ73: # | DA73: # | DB73: # | DC73: # | DD73: # | DE73: # | DF73: # | DG73: # | DH73: # | DI73: #
A74: a73_0 | B74: Wong, S.C., et al. | C74: retrosp. Cohort | D74: 44613 | E74: 44712 | F74: Hong Kong | G74: AS; Health-care workers in the Queen Mary Hospital | H74: City | I74: 56843.908 | J74: unclear | K74: 6452 | L74: # | M74: # | N74: =MAX(K74:M74) -> 6452 | O74: Number of people eligible for self-testing | P74: # | Q74: # | R74: # | S74: # | T74: # | U74: # | V74: # | W74: # | X74: # | Y74: # | Z74: Healthcare Professionals | AA74: 1050 | AB74: # | AC74: # | AD74: =IF(AND(AA74=0,AC74=0),1,0) -> 0 | AE74: # | AF74: 671 reported exposure (541 through contact with infected houshold member; 130 to exposure to patients / staff) | AG74: unknown | AH74: Healthcareworkers were required to receive a second dose of vaccination by 2/16/22, but it was not reported whether all healthcare Workers actually did so | AI74: # | AJ74: GLINE- 2019-nCoV Ag, BGI, China | AK74: no | AL74: Nasal | AM74: # | AN74: Home | AO74: Routine | AP74: Unclear | AQ74: =ROUND(('Data extracted'!E74-'Data extracted'!D74)/7,0) -> 14 | AR74: # | AS74: # | AT74: # | AU74: no | AV74: no | AW74: Refrain from work in case of fever or respiratory symptoms; perform RT-PCR in case of symptoms or contact with a case; hospital rooms with COVID-19 patients were turned into negative-pressure wards | AX74: # | AY74: # | AZ74: # | BA74: # | BB74: # | BC74: # | BD74: # | BE74: # | BF74: =SUM(BG74:BJ74) -> 0 | BG74: # | BH74: # | BI74: # | BJ74: # | BK74: =IFERROR(IF(BJ74<>"#",BJ74+BI74,"#"),"#") -> # | BL74: =SUM(BM74:BP74) -> 0 | BM74: # | BN74: # | BO74: # | BP74: # | BQ74: # | BR74: # | BS74: =SUM(BT74:BW74) -> 0 | BT74: # | BU74: # | BV74: # | BW74: # | BX74: =IFERROR(IF(BU74<>"#",BU74+BT74,"#"),"#") -> # | BY74: RT-PCR | BZ74: # | CA74: 30 min. | CB74: Perform another rapid test to ensure consistent results; if repeated test is also positive: proceed to RT-PCR confirmatory testing and be interviewed by infection control nurse | CC74: mixed - compulsory (by study design) if repeated C19ST is also positive | CD74: Continue work and routine testing | CE74: # | CF74: # | CG74: # | CH74: # | CI74: # | CJ74: # | CK74: # | CL74: # | CM74: # | CN74: # | CO74: # | CP74: # | CQ74: # | CR74: # | CS74: # | CT74: # | CU74: # | CV74: # | CW74: # | CX74: # | CY74: # | CZ74: # | DA74: # | DB74: # | DC74: # | DD74: # | DE74: # | DF74: # | DG74: # | DH74: # | DI74: #
A75: a74_0 | B75: Wu, S., et al. | C75: prosp. cohort | D75: 44407 | E75: 44460 | F75: Singapore | G75: AS; Staff of The National University Hospital | H75: City | I75: 94480.797 | J75: unclear | K75: 8000 | L75: 8000 | M75: 8000 | N75: =MAX(K75:M75) -> 8000 | O75: Number of people that collected self-tests | P75: # | Q75: # | R75: # | S75: # | T75: # | U75: # | V75: # | W75: # | X75: # | Y75: # | Z75: Healthcare Professionals | AA75: # | AB75: # | AC75: # | AD75: =IF(AND(AA75=0,AC75=0),1,0) -> 0 | AE75: # | AF75: # | AG75: unknown | AH75: # | AI75: # | AJ75: QuickVue | AK75: no | AL75: AN / MT | AM75: # | AN75: Home | AO75: Routine | AP75: 2 | AQ75: =ROUND(('Data extracted'!E75-'Data extracted'!D75)/7,0) -> 8 | AR75: # | AS75: # | AT75: 156000 | AU75: no | AV75: no | AW75: RT-PCR testing if symptomatic | AX75: # | AY75: =SUM(AZ75:BC75) -> 31 | AZ75: 31 | BA75: # | BB75: # | BC75: # | BD75: RT-PCR | BE75: # | BF75: =SUM(BG75:BJ75) -> 31 | BG75: 20 | BH75: # | BI75: # | BJ75: 11 | BK75: =IFERROR(IF(BJ75<>"#",BJ75+BI75,"#"),"#") -> # | BL75: =SUM(BM75:BP75) -> 0 | BM75: # | BN75: # | BO75: # | BP75: # | BQ75: # | BR75: # | BS75: =SUM(BT75:BW75) -> 0 | BT75: # | BU75: # | BV75: # | BW75: # | BX75: =IFERROR(IF(BU75<>"#",BU75+BT75,"#"),"#") -> # | BY75: # | BZ75: # | CA75: allmost immediate results | CB75: Report result to reporting officer and occupational health clinic; promptly repeat ART and perform a fast-tracked rt-PCR test for confirmatory testing while being held in isolation | CC75: compulsory (by study design) | CD75: # | CE75: # | CF75: # | CG75: # | CH75: # | CI75: # | CJ75: # | CK75: # | CL75: # | CM75: # | CN75: # | CO75: # | CP75: # | CQ75: # | CR75: # | CS75: # | CT75: # | CU75: # | CV75: # | CW75: # | CX75: "shortened the window of contact tracing" | CY75: # | CZ75: # | DA75: "reduced the number of staff under quarantine" | DB75: estimated to cost US$100,000 per week per 8,000 people | DC75: # | DD75: # | DE75: # | DF75: # | DG75: include | DH75: include | DI75: #
A76: a75_1 | B76: Yun, G., et al. | C76: prosp. cohort | D76: 44622 | E76: 44682 | F76: Republic of Korea | G76: AS; Schools and kindergarden across the entire country | H76: unclear | I76: 35962.344 | J76: unclear | K76: # | L76: # | M76: 1039087 | N76: =MAX(K76:M76) -> 1039087 | O76: Number of people that reported self-testing results | P76: # | Q76: # | R76: # | S76: # | T76: # | U76: # | V76: # | W76: # | X76: # | Y76: # | Z76: K-12 students and staff | AA76: 1039087 | AB76: 0 | AC76: 0 | AD76: =IF(AND(AA76=0,AC76=0),1,0) -> 0 | AE76: # | AF76: # | AG76: unknown | AH76: # | AI76: # | AJ76: Unclear | AK76: # | AL76: AN / MT | AM76: # | AN76: Unclear | AO76: Routine | AP76: 2 | AQ76: =ROUND(('Data extracted'!E76-'Data extracted'!D76)/7,0) -> 9 | AR76: # | AS76: # | AT76: 3017696 | AU76: no | AV76: no | AW76: # | AX76: # | AY76: =SUM(AZ76:BC76) -> 3017696 | AZ76: 1134765 | BA76: 1882931 | BB76: # | BC76: # | BD76: # | BE76: # | BF76: =SUM(BG76:BJ76) -> 0 | BG76: # | BH76: # | BI76: # | BJ76: # | BK76: =IFERROR(IF(BJ76<>"#",BJ76+BI76,"#"),"#") -> # | BL76: =SUM(BM76:BP76) -> 1039087 | BM76: 803163 | BN76: =N76-BM76 -> 235924 | BO76: # | BP76: # | BQ76: RT-PCR / professional Ag-RDT | BR76: # | BS76: =SUM(BT76:BW76) -> 803163 | BT76: 754548 | BU76: # | BV76: # | BW76: 48615 | BX76: =IFERROR(IF(BU76<>"#",BU76+BT76,"#"),"#") -> # | BY76: RT-PCR / professional Ag-RDT | BZ76: # | CA76: 30 min. | CB76: Confirm result through RT-PCR or professional Ag-RDT; do not go to school | CC76: mixed - compulsory (by government guidance) either RT-PCR or professional Ag-RDT test | CD76: resume school; continue to test twice weekly and after contact | CE76: # | CF76: # | CG76: # | CH76: # | CI76: # | CJ76: # | CK76: # | CL76: # | CM76: # | CN76: # | CO76: # | CP76: # | CQ76: # | CR76: # | CS76: # | CT76: # | CU76: # | CV76: # | CW76: # | CX76: # | CY76: # | CZ76: # | DA76: # | DB76: # | DC76: # | DD76: # | DE76: # | DF76: # | DG76: # | DH76: # | DI76: #
A77: a75_2 | B77: Yun, G., et al. | C77: prosp. cohort | D77: 44622 | E77: 44682 | F77: Republic of Korea | G77: AS; Schools and kindergarden across the entire country | H77: unclear | I77: 35962.344 | J77: unclear | K77: # | L77: # | M77: 16139251 | N77: =MAX(K77:M77) -> 16139251 | O77: Number of people that reported self-testing results | P77: # | Q77: # | R77: # | S77: # | T77: # | U77: # | V77: # | W77: # | X77: # | Y77: # | Z77: K-12 students and staff | AA77: 0 | AB77: 16139251 | AC77: 0 | AD77: =IF(AND(AA77=0,AC77=0),1,0) -> 1 | AE77: # | AF77: # | AG77: unknown | AH77: # | AI77: # | AJ77: Unclear | AK77: # | AL77: AN / MT | AM77: # | AN77: Unclear | AO77: Routine | AP77: 2 | AQ77: =ROUND(('Data extracted'!E77-'Data extracted'!D77)/7,0) -> 9 | AR77: # | AS77: # | AT77: 43263650 | AU77: no | AV77: no | AW77: # | AX77: # | AY77: =SUM(AZ77:BC77) -> 43263650 | AZ77: 207905 | BA77: 43055745 | BB77: # | BC77: # | BD77: # | BE77: # | BF77: =SUM(BG77:BJ77) -> 0 | BG77: # | BH77: # | BI77: # | BJ77: # | BK77: =IFERROR(IF(BJ77<>"#",BJ77+BI77,"#"),"#") -> # | BL77: =SUM(BM77:BP77) -> 16139251 | BM77: 146197 | BN77: =N77-BM77 -> 15993054 | BO77: # | BP77: # | BQ77: RT-PCR / professional Ag-RDT | BR77: # | BS77: =SUM(BT77:BW77) -> 146197 | BT77: 122119 | BU77: # | BV77: # | BW77: 24078 | BX77: =IFERROR(IF(BU77<>"#",BU77+BT77,"#"),"#") -> # | BY77: RT-PCR / professional Ag-RDT | BZ77: # | CA77: 30 min. | CB77: Confirm result through RT-PCR or professional Ag-RDT; do not go to school | CC77: mixed - compulsory (by government guidance) either RT-PCR or professional Ag-RDT test | CD77: resume school; continue to test twice weekly and after contact | CE77: # | CF77: # | CG77: # | CH77: # | CI77: # | CJ77: # | CK77: # | CL77: # | CM77: # | CN77: # | CO77: # | CP77: # | CQ77: # | CR77: # | CS77: # | CT77: # | CU77: # | CV77: # | CW77: # | CX77: # | CY77: # | CZ77: # | DA77: # | DB77: # | DC77: # | DD77: # | DE77: # | DF77: # | DG77: # | DH77: # | DI77: #
A78: a75_3 | B78: Yun, G., et al. | C78: prosp. cohort | D78: 44622 | E78: 44682 | F78: Republic of Korea | G78: AS; Schools and kindergarden across the entire country | H78: unclear | I78: 35962.344 | J78: unclear | K78: # | L78: # | M78: 87387 | N78: =MAX(K78:M78) -> 87387 | O78: Number of people that reported self-testing results | P78: # | Q78: # | R78: # | S78: # | T78: # | U78: # | V78: # | W78: # | X78: # | Y78: # | Z78: K-12 students and staff | AA78: 87387 | AB78: 0 | AC78: 0 | AD78: =IF(AND(AA78=0,AC78=0),1,0) -> 0 | AE78: # | AF78: # | AG78: unknown | AH78: # | AI78: # | AJ78: Unclear | AK78: # | AL78: AN / MT | AM78: # | AN78: Unclear | AO78: Routine | AP78: 2 | AQ78: =ROUND(('Data extracted'!E78-'Data extracted'!D78)/7,0) -> 9 | AR78: # | AS78: # | AT78: 206799 | AU78: no | AV78: no | AW78: # | AX78: # | AY78: =SUM(AZ78:BC78) -> 206799 | AZ78: 96411 | BA78: 110388 | BB78: # | BC78: # | BD78: # | BE78: # | BF78: =SUM(BG78:BJ78) -> 0 | BG78: # | BH78: # | BI78: # | BJ78: # | BK78: =IFERROR(IF(BJ78<>"#",BJ78+BI78,"#"),"#") -> # | BL78: =SUM(BM78:BP78) -> 87387 | BM78: 74520 | BN78: =N78-BM78 -> 12867 | BO78: # | BP78: # | BQ78: RT-PCR / professional Ag-RDT | BR78: # | BS78: =SUM(BT78:BW78) -> 74520 | BT78: 61168 | BU78: # | BV78: # | BW78: 13352 | BX78: =IFERROR(IF(BU78<>"#",BU78+BT78,"#"),"#") -> # | BY78: RT-PCR / professional Ag-RDT | BZ78: # | CA78: 30 min. | CB78: Confirm result through RT-PCR or professional Ag-RDT; do not go to school | CC78: mixed - compulsory (by government guidance) either RT-PCR or professional Ag-RDT test | CD78: resume school; continue to test once weekly and after contact | CE78: # | CF78: # | CG78: # | CH78: # | CI78: # | CJ78: # | CK78: # | CL78: # | CM78: # | CN78: # | CO78: # | CP78: # | CQ78: # | CR78: # | CS78: # | CT78: # | CU78: # | CV78: # | CW78: # | CX78: # | CY78: # | CZ78: # | DA78: # | DB78: # | DC78: # | DD78: # | DE78: # | DF78: # | DG78: # | DH78: # | DI78: #
A79: a75_4 | B79: Yun, G., et al. | C79: prosp. cohort | D79: 44622 | E79: 44682 | F79: Republic of Korea | G79: AS; Schools and kindergarden across the entire country | H79: unclear | I79: 35962.344 | J79: unclear | K79: # | L79: # | M79: 2192850 | N79: =MAX(K79:M79) -> 2192850 | O79: Number of people that reported self-testing results | P79: # | Q79: # | R79: # | S79: # | T79: # | U79: # | V79: # | W79: # | X79: # | Y79: # | Z79: K-12 students and staff | AA79: 0 | AB79: 2192850 | AC79: 0 | AD79: =IF(AND(AA79=0,AC79=0),1,0) -> 1 | AE79: # | AF79: # | AG79: unknown | AH79: # | AI79: # | AJ79: Unclear | AK79: # | AL79: AN / MT | AM79: # | AN79: Unclear | AO79: Routine | AP79: 2 | AQ79: =ROUND(('Data extracted'!E79-'Data extracted'!D79)/7,0) -> 9 | AR79: # | AS79: # | AT79: 4187241 | AU79: no | AV79: no | AW79: # | AX79: # | AY79: =SUM(AZ79:BC79) -> 4187241 | AZ79: 10226 | BA79: 4177015 | BB79: # | BC79: # | BD79: # | BE79: # | BF79: =SUM(BG79:BJ79) -> 0 | BG79: # | BH79: # | BI79: # | BJ79: # | BK79: =IFERROR(IF(BJ79<>"#",BJ79+BI79,"#"),"#") -> # | BL79: =SUM(BM79:BP79) -> 2192850 | BM79: 7969 | BN79: =N79-BM79 -> 2184881 | BO79: # | BP79: # | BQ79: RT-PCR / professional Ag-RDT | BR79: # | BS79: =SUM(BT79:BW79) -> 7969 | BT79: 5507 | BU79: # | BV79: # | BW79: 2462 | BX79: =IFERROR(IF(BU79<>"#",BU79+BT79,"#"),"#") -> # | BY79: RT-PCR / professional Ag-RDT | BZ79: # | CA79: 30 min. | CB79: Confirm result through RT-PCR or professional Ag-RDT; do not go to school | CC79: mixed - compulsory (by government guidance) either RT-PCR or professional Ag-RDT test | CD79: resume school; continue to test once weekly and after contact | CE79: # | CF79: # | CG79: # | CH79: # | CI79: # | CJ79: # | CK79: # | CL79: # | CM79: # | CN79: # | CO79: # | CP79: # | CQ79: # | CR79: # | CS79: # | CT79: # | CU79: # | CV79: # | CW79: # | CX79: # | CY79: # | CZ79: # | DA79: # | DB79: # | DC79: # | DD79: # | DE79: # | DF79: # | DG79: # | DH79: # | DI79: #
A80: a76_0 | B80: Davies, M. et al. | C80: prosp. cohort | D80: 44348 | E80: 44435 | F80: United Kingdom | G80: UK; athletes and key event staff across the country | H80: unclear | I80: 56660.868 | J80: unclear | K80: 105 | L80: # | M80: # | N80: =MAX(K80:M80) -> 105 | O80: Number of people that reported self-testing results | P80: # | Q80: # | R80: # | S80: # | T80: # | U80: # | V80: # | W80: # | X80: # | Y80: # | Z80: Unclear | AA80: 0 | AB80: 105 | AC80: 0 | AD80: 1 | AE80: # | AF80: Low-risk contact to a SARS-CoV-2 case | AG80: unknown | AH80: # | AI80: # | AJ80: Unclear | AK80: # | AL80: # | AM80: # | AN80: Unclear | AO80: Routine | AP80: 7 | AQ80: 1 | AR80: # | AS80: 280 | AT80: 280 | AU80: no | AV80: yes | AW80: Daily symptom monitoring; COVID-19 transmission mitigation measures at the workplace | AX80: # | AY80: =SUM(AZ80:BC80) -> 280 | AZ80: 0 | BA80: 280 | BB80: 0 | BC80: # | BD80: # | BE80: # | BF80: # | BG80: # | BH80: # | BI80: # | BJ80: # | BK80: # | BL80: # | BM80: 0 | BN80: # | BO80: 0 | BP80: # | BQ80: # | BR80: # | BS80: # | BT80: # | BU80: # | BV80: # | BW80: # | BX80: # | BY80: unclear | BZ80: # | CA80: # | CB80: # | CC80: # | CD80: Continue participating in training and competitions, continue working | CE80: # | CF80: # | CG80: # | CH80: # | CI80: # | CJ80: # | CK80: # | CL80: # | CM80: # | CN80: # | CO80: # | CP80: # | CQ80: # | CR80: # | CS80: # | CT80: # | CU80: # | CV80: # | CW80: # | CX80: Allowed to continue sport training and competitions as well as going to work despite low-risk SARS-CoV-2 contact | CY80: Partially avoided quarantine in low-risk contacts | CZ80: # | DA80: Allowed continuation of work despite low-risk SARS-CoV-2 contact | DB80: Implementing C19ST for individuals with low-risk contact (among other testing interventions) was described as labour-intensive by study authors | DC80: # | DD80: # | DE80: # | DF80: # | DG80: # | DH80: # | DI80: #
A81: a77_0 | B81: Del Fiol, G. et al. | C81: prosp. cohort | D81: 44914 | E81: 45166 | F81: United States | G81: NA; adults across Utah | H81: City; rural | I81: 89598.86 | J81: unclear | K81: 2117 | L81: 729 | M81: # | N81: =MAX(K81:M81) -> 2117 | O81: Number of people eligible for self-testing | P81: 49 | Q81: 14.6 | R81: # | S81: # | T81: # | U81: # | V81: # | W81: 1451 | X81: 665 | Y81: 1 | Z81: General population | AA81: # | AB81: # | AC81: # | AD81: 0 | AE81: # | AF81: # | AG81: unknown | AH81: # | AI81: # | AJ81: Unclear | AK81: # | AL81: # | AM81: Study via clinic | AN81: Unclear | AO81: Unclear | AP81: # | AQ81: =ROUND(('Data extracted'!E81-'Data extracted'!D81)/7,0) -> 36 | AR81: # | AS81: # | AT81: # | AU81: # | AV81: # | AW81: Patient navigation or none, reminders to test every 10 or 30 days through messaging or chatbot | AX81: # | AY81: # | AZ81: # | BA81: # | BB81: # | BC81: # | BD81: # | BE81: # | BF81: # | BG81: # | BH81: # | BI81: # | BJ81: # | BK81: # | BL81: # | BM81: # | BN81: # | BO81: # | BP81: # | BQ81: # | BR81: # | BS81: # | BT81: # | BU81: # | BV81: # | BW81: # | BX81: # | BY81: unclear | BZ81: # | CA81: # | CB81: # | CC81: # | CD81: # | CE81: # | CF81: # | CG81: # | CH81: # | CI81: # | CJ81: # | CK81: # | CL81: # | CM81: # | CN81: # | CO81: # | CP81: # | CQ81: # | CR81: # | CS81: # | CT81: # | CU81: # | CV81: # | CW81: # | CX81: # | CY81: # | CZ81: # | DA81: # | DB81: # | DC81: # | DD81: # | DE81: # | DF81: # | DG81: # | DH81: # | DI81: #
A82: a78_0 | B82: Mwangoka, G.W. et al. | C82: prosp. cohort | D82: 44757 | E82: 44849 | F82: Tanzania | G82: Other; Adults in Dar es Salaam, Ilala District; Dodoma Town; and Mara, Tarime District | H82: City | I82: 1301.737 | J82: unclear | K82: 517 | L82: 149 | M82: # | N82: =MAX(K82:M82) -> 517 | O82: Number of people that reported self-testing results | P82: # | Q82: # | R82: # | S82: # | T82: # | U82: # | V82: 18 | W82: 20 | X82: 129 | Y82: 0 | Z82: General population | AA82: # | AB82: # | AC82: 149 | AD82: 0 | AE82: # | AF82: # | AG82: unknown | AH82: # | AI82: # | AJ82: SARS-COV2 Ag-RDT Flowflex COVID-19 Antigen Home Test, ACON | AK82: no | AL82: AN / MT | AM82: Testing Site | AN82: Testing Site | AO82: Single | AP82: # | AQ82: =ROUND(('Data extracted'!E82-'Data extracted'!D82)/7,0) -> 13 | AR82: 149 | AS82: # | AT82: # | AU82: no | AV82: unclear | AW82: Survey on barriers to testing | AX82: # | AY82: # | AZ82: # | BA82: # | BB82: # | BC82: # | BD82: # | BE82: # | BF82: # | BG82: # | BH82: # | BI82: # | BJ82: # | BK82: # | BL82: # | BM82: # | BN82: # | BO82: # | BP82: # | BQ82: # | BR82: # | BS82: # | BT82: # | BU82: # | BV82: # | BW82: # | BX82: # | BY82: C19ST / professional Ag-RDT | BZ82: 20min | CA82: 20min | CB82: Education of COVID-19 interventions (self-isolation) and provision of masks and sanitizers for those who tested positive; further referral to healthcare facilities if also symptomatic | CC82: # | CD82: Receive COVID-19 vaccination or at least advised to do so | CE82: # | CF82: # | CG82: # | CH82: # | CI82: # | CJ82: # | CK82: # | CL82: # | CM82: # | CN82: # | CO82: # | CP82: # | CQ82: # | CR82: # | CS82: # | CT82: # | CU82: # | CV82: # | CW82: # | CX82: # | CY82: # | CZ82: # | DA82: # | DB82: # | DC82: # | DD82: # | DE82: # | DF82: # | DG82: # | DH82: # | DI82: #
A83: a79_1 | B83: Nacov, J. A. et al. | C83: prosp. cohort | D83: 44902 | E83: 45077 | F83: Germany | G83: EU; Adults across Germany | H83: unclear | I83: 59925.317 | J83: unclear | K83: # | L83: 1993 | M83: 1119 | N83: =MAX(K83:M83) -> 1993 | O83: Number of people that reported self-testing results | P83: # | Q83: # | R83: 46 | S83: 38 | T83: 57 | U83: 88 | V83: 3 | W83: # | X83: # | Y83: # | Z83: General population | AA83: 1119 | AB83: 0 | AC83: 0 | AD83: 0 | AE83: Individuals with: Hypertension - 147 Coronary heart disease - 12 Heart failure - 8 Asthma/COPD - 107 Chronic kidney disease - 11 ≥20 kg overweight - 104 Diabetes mellitus - 30 HIV - 13 Active cancer (≥2 yrs) - 17 Chronic GIT disease - 14 History of stroke - 10 | AF83: # | AG83: unknown | AH83: Median (IQR) number of vaccinations: 3 (3-4); 937 individuals with 2+ vaccines | AI83: 695 with history of COVID-19 infection, median (IQR) of 3 (3-4) vaccinations per study participant | AJ83: MAK 5, BioTeke Cooperation | AK83: no | AL83: AN / MT | AM83: Study | AN83: Unclear | AO83: Single | AP83: # | AQ83: =ROUND(('Data extracted'!E83-'Data extracted'!D83)/7,0) -> 25 | AR83: # | AS83: # | AT83: 1119 | AU83: no | AV83: no | AW83: Testing for RSV, Influenca A, Influenca B, Adenovirus | AX83: # | AY83: =SUM(AZ83:BC83) -> 1119 | AZ83: 178 | BA83: 928 | BB83: 13 | BC83: # | BD83: # | BE83: # | BF83: # | BG83: # | BH83: # | BI83: # | BJ83: # | BK83: # | BL83: =SUM(BM83:BP83) -> 1119 | BM83: 928 | BN83: 178 | BO83: 13 | BP83: # | BQ83: # | BR83: # | BS83: # | BT83: # | BU83: # | BV83: # | BW83: # | BX83: # | BY83: C19ST | BZ83: # | CA83: # | CB83: # | CC83: # | CD83: # | CE83: # | CF83: # | CG83: # | CH83: # | CI83: # | CJ83: # | CK83: # | CL83: # | CM83: # | CN83: # | CO83: # | CP83: # | CQ83: # | CR83: # | CS83: # | CT83: # | CU83: # | CV83: # | CW83: # | CX83: # | CY83: # | CZ83: # | DA83: # | DB83: # | DC83: # | DD83: # | DE83: # | DF83: # | DG83: # | DH83: # | DI83: #
A84: a79_2 | B84: Nacov, J. A. et al. | C84: prosp. cohort | D84: 45078 | E84: 45079 | F84: Germany | G84: EU; Adults across Germany | H84: unclear | I84: 59925.317 | J84: unclear | K84: # | L84: # | M84: 310 | N84: # | O84: Number of people that reported self-testing results | P84: # | Q84: # | R84: 48 | S84: 37 | T84: 58 | U84: 91 | V84: 20 | W84: # | X84: # | Y84: # | Z84: General population | AA84: 52 | AB84: 258 | AC84: 0 | AD84: 0 | AE84: Individuals with: Hypertension - 60 Coronary heart disease - 9 Heart failure - 2 Asthma/COPD - 36 Chronic kidney disease - 2 ≥20 kg overweight - 35 Diabetes mellitus - 13 HIV - 5 Active cancer (≥2 yrs) - 5 Chronic GIT disease - 2 History of stroke - 1 | AF84: # | AG84: unknown | AH84: Median (IQR) number of vaccinations: 3 (3-4) | AI84: 177 with history of COVID-19 infection, median (IQR) of 3 (3-4) vaccinations per study participant | AJ84: MAK 5, BioTeke Cooperation | AK84: no | AL84: AN / MT | AM84: Study | AN84: Unclear | AO84: Single | AP84: # | AQ84: =ROUND(('Data extracted'!E84-'Data extracted'!D84)/7,0) -> 0 | AR84: # | AS84: # | AT84: 310 | AU84: no | AV84: no | AW84: Testing for RSV, Influenca A, Influenca B, Adenovirus | AX84: # | AY84: =SUM(AZ84:BC84) -> 310 | AZ84: 2 | BA84: 302 | BB84: 6 | BC84: # | BD84: # | BE84: # | BF84: # | BG84: # | BH84: # | BI84: # | BJ84: # | BK84: # | BL84: =SUM(BM84:BP84) -> 310 | BM84: 302 | BN84: 2 | BO84: 6 | BP84: # | BQ84: # | BR84: # | BS84: # | BT84: # | BU84: # | BV84: # | BW84: # | BX84: # | BY84: C19ST | BZ84: # | CA84: # | CB84: # | CC84: # | CD84: # | CE84: # | CF84: # | CG84: # | CH84: # | CI84: # | CJ84: # | CK84: # | CL84: # | CM84: # | CN84: # | CO84: # | CP84: # | CQ84: # | CR84: # | CS84: # | CT84: # | CU84: # | CV84: # | CW84: # | CX84: # | CY84: # | CZ84: # | DA84: # | DB84: # | DC84: # | DD84: # | DE84: # | DF84: # | DG84: # | DH84: # | DI84: #
A85: a80_0 | B85: Qasmieh, S.A. et al. (a) | C85: prosp. cohort | D85: 44635 | E85: 45214 | F85: United States | G85: NA; adults across the United States | H85: unclear | I85: 89598.86 | J85: unclear | K85: 1918 | L85: # | M85: 623 | N85: =MAX(K85:M85) -> 1918 | O85: Number of people eligible for self-testing | P85: # | Q85: # | R85: # | S85: # | T85: # | U85: # | V85: # | W85: # | X85: # | Y85: # | Z85: General population | AA85: 1918 | AB85: 0 | AC85: 0 | AD85: 0 | AE85: # | AF85: # | AG85: unknown | AH85: 1335 individuals were vaccinated | AI85: # | AJ85: Unclear | AK85: # | AL85: # | AM85: # | AN85: Unclear | AO85: Unclear | AP85: # | AQ85: # | AR85: # | AS85: # | AT85: # | AU85: no | AV85: no | AW85: # | AX85: # | AY85: # | AZ85: # | BA85: # | BB85: # | BC85: # | BD85: # | BE85: # | BF85: # | BG85: # | BH85: # | BI85: # | BJ85: # | BK85: # | BL85: =SUM(BM85:BP85) -> 623 | BM85: 247 | BN85: 376 | BO85: # | BP85: # | BQ85: # | BR85: # | BS85: # | BT85: # | BU85: # | BV85: # | BW85: # | BX85: # | BY85: # | BZ85: # | CA85: # | CB85: # | CC85: # | CD85: # | CE85: # | CF85: # | CG85: # | CH85: # | CI85: # | CJ85: # | CK85: # | CL85: # | CM85: # | CN85: # | CO85: # | CP85: # | CQ85: # | CR85: # | CS85: # | CT85: # | CU85: # | CV85: # | CW85: # | CX85: # | CY85: # | CZ85: # | DA85: # | DB85: # | DC85: # | DD85: # | DE85: # | DF85: # | DG85: # | DH85: # | DI85: • Of the people who tested positive and had symptoms, 46% turned towards healthcare providers • Of the people who tested negative and had symptoms of ARI, 29% turned to healthcare providers
A86: a81_1 | B86: Stirrup, O. et al. | C86: prosp. cohort | D86: 44935 | E86: 45144 | F86: United Kingdom | G86: UK; care-home staff across the UK | H86: unclear | I86: 56660.868 | J86: unclear | K86: # | L86: # | M86: # | N86: # | O86: n/a | P86: # | Q86: # | R86: # | S86: # | T86: # | U86: # | V86: # | W86: # | X86: # | Y86: # | Z86: Healthcare Professionals | AA86: # | AB86: # | AC86: # | AD86: 0 | AE86: # | AF86: # | AG86: unknown | AH86: # | AI86: # | AJ86: Unclear | AK86: # | AL86: # | AM86: # | AN86: Unclear | AO86: Routine | AP86: 2 | AQ86: =ROUND(('Data extracted'!E86-'Data extracted'!D86)/7,0) -> 30 | AR86: # | AS86: # | AT86: # | AU86: no | AV86: no | AW86: Staff symptomatic testing and outbreak testing, accompanyed by support payments for paid sick-leave and agency-back fill for COVID-related sick leave; communication strategy to encourage testing | AX86: # | AY86: # | AZ86: # | BA86: # | BB86: # | BC86: # | BD86: # | BE86: # | BF86: # | BG86: # | BH86: # | BI86: # | BJ86: # | BK86: # | BL86: # | BM86: # | BN86: # | BO86: # | BP86: # | BQ86: # | BR86: # | BS86: # | BT86: # | BU86: # | BV86: # | BW86: # | BX86: # | BY86: # | BZ86: # | CA86: # | CB86: # | CC86: # | CD86: # | CE86: # | CF86: # | CG86: # | CH86: # | CI86: Incidence rate of all-cause hospital admissions per 1,000 care-home resident person-years [event-count]: 367.3 [204] | CJ86: # | CK86: # | CL86: # | CM86: # | CN86: # | CO86: # | CP86: # | CQ86: # | CR86: # | CS86: Incidence rate of COVID-19 mortality in residents per 1,000 care-home residents person-years [event-count]: 5.4 [3]; Incidence rate of all-cause mortality in residents per 1,000 care-home residents person-years [event-count]: 243.4 [136] | CT86: # | CU86: Incidence rate of COVID-19 hospital admissions per 1,000 care-home resident person-years [event-count]: 22.7 [13]; Incidence rate of all-cause hospital admissions per 1,000 care-home resident person-years [event-count]: 367.3 [204] | CV86: # | CW86: # | CX86: # | CY86: # | CZ86: # | DA86: No significant difference in proportion of staff with Covid-19, staff on sick leave or proportion of shifts filled by agency staff | DB86: # | DC86: # | DD86: # | DE86: # | DF86: # | DG86: # | DH86: # | DI86: #
A87: a81_2 | B87: Stirrup, O. et al. | C87: prosp. cohort | D87: 44935 | E87: 45144 | F87: United Kingdom | G87: UK; care-home staff across the UK | H87: unclear | I87: 56660.868 | J87: unclear | K87: # | L87: # | M87: # | N87: # | O87: n/a | P87: # | Q87: # | R87: # | S87: # | T87: # | U87: # | V87: # | W87: # | X87: # | Y87: # | Z87: Healthcare Professionals | AA87: # | AB87: # | AC87: # | AD87: 0 | AE87: # | AF87: # | AG87: unknown | AH87: # | AI87: # | AJ87: Unclear | AK87: # | AL87: # | AM87: # | AN87: Unclear | AO87: Routine | AP87: Unclear | AQ87: =ROUND(('Data extracted'!E87-'Data extracted'!D87)/7,0) -> 30 | AR87: # | AS87: # | AT87: # | AU87: no | AV87: no | AW87: # | AX87: # | AY87: # | AZ87: # | BA87: # | BB87: # | BC87: # | BD87: # | BE87: # | BF87: # | BG87: # | BH87: # | BI87: # | BJ87: # | BK87: # | BL87: # | BM87: # | BN87: # | BO87: # | BP87: # | BQ87: # | BR87: # | BS87: # | BT87: # | BU87: # | BV87: # | BW87: # | BX87: # | BY87: # | BZ87: # | CA87: # | CB87: # | CC87: # | CD87: # | CE87: # | CF87: # | CG87: # | CH87: # | CI87: Incidence rate of all-cause hospital admissions per 1,000 care-home resident person-years [event-count]: 506.6 [293] | CJ87: # | CK87: # | CL87: # | CM87: # | CN87: # | CO87: # | CP87: # | CQ87: # | CR87: # | CS87: Incidence rate of COVID-19 mortality in residents per 1,000 care-home residents person-years [event-count]: 8.4 [5]; Incidence rate of COVID-19 mortality in residents per 1,000 care-home residents person-years [event-count]: 225.9 [134] | CT87: # | CU87: Incidence rate of all-cause hospital admissions per 1,000 care-home resident person-years [event-count]: 15.0 [9]; Incidence rate of all-cause hospital admissions per 1,000 care-home resident person-years [event-count]: 506.6 [293] | CV87: # | CW87: # | CX87: # | CY87: # | CZ87: # | DA87: # | DB87: # | DC87: # | DD87: # | DE87: # | DF87: # | DG87: # | DH87: # | DI87: #
A88: a82_0 | B88: van Hagen, C.C.E. et al. | C88: prosp. cohort | D88: 44635 | E88: 45061 | F88: Netherlands | G88: EU; Adults across Netherlands | H88: unclear | I88: 73173.715 | J88: unclear | K88: 3152 | L88: =ROUND(2742*0.84,0) -> 2303 | M88: # | N88: =MAX(K88:M88) -> 3152 | O88: Number of people that collected / were sent self-tests | P88: # | Q88: # | R88: 53 | S88: 39 | T88: 67 | U88: # | V88: # | W88: 2025 | X88: # | Y88: # | Z88: General population | AA88: 3152 | AB88: 0 | AC88: # | AD88: 0 | AE88: # | AF88: # | AG88: unknown | AH88: 2189 individuals were vaccinated | AI88: # | AJ88: Unclear | AK88: # | AL88: # | AM88: # | AN88: Unclear | AO88: Unclear | AP88: # | AQ88: # | AR88: # | AS88: # | AT88: # | AU88: no | AV88: no | AW88: # | AX88: # | AY88: # | AZ88: # | BA88: # | BB88: # | BC88: # | BD88: # | BE88: # | BF88: # | BG88: # | BH88: # | BI88: # | BJ88: # | BK88: # | BL88: # | BM88: # | BN88: # | BO88: # | BP88: # | BQ88: # | BR88: # | BS88: # | BT88: # | BU88: # | BV88: # | BW88: # | BX88: # | BY88: # | BZ88: # | CA88: # | CB88: # | CC88: # | CD88: # | CE88: # | CF88: # | CG88: # | CH88: # | CI88: # | CJ88: # | CK88: # | CL88: # | CM88: # | CN88: # | CO88: # | CP88: # | CQ88: # | CR88: # | CS88: # | CT88: # | CU88: # | CV88: # | CW88: # | CX88: # | CY88: # | CZ88: # | DA88: # | DB88: # | DC88: # | DD88: # | DE88: # | DF88: # | DG88: # | DH88: # | DI88: #
A89: a83_0 | B89: Qasmieh, S.A. et al. (b) | C89: prosp. cohort | D89: 44678 | E89: 44689 | F89: United States | G89: NA; adults across New York City | H89: City | I89: 89598.86 | J89: unclear | K89: 1030 | L89: 497 | M89: # | N89: =MAX(K89:M89) -> 1030 | O89: Number of people eligible for self-testing | P89: # | Q89: # | R89: # | S89: # | T89: # | U89: # | V89: # | W89: 527 | X89: 471 | Y89: 32 | Z89: General population | AA89: # | AB89: # | AC89: # | AD89: 0 | AE89: 377 individuals with comorbidities; 653 without | AF89: # | AG89: unknown | AH89: Boosted: 691 individuals Fully vaccinated not boosted: 149 individuals Not vaccinated: 190 individuals | AI89: Prior COVID-19 infection Never: 390 individuals Confirmed: 375 individuals No positive test, but likely prior COVID-19: 265 individuals | AJ89: Unclear | AK89: # | AL89: # | AM89: # | AN89: Home | AO89: Unclear | AP89: # | AQ89: # | AR89: # | AS89: # | AT89: # | AU89: unclear | AV89: unclear | AW89: # | AX89: # | AY89: # | AZ89: # | BA89: # | BB89: # | BC89: # | BD89: # | BE89: # | BF89: # | BG89: # | BH89: # | BI89: # | BJ89: # | BK89: # | BL89: # | BM89: # | BN89: # | BO89: # | BP89: # | BQ89: # | BR89: # | BS89: # | BT89: # | BU89: # | BV89: # | BW89: # | BX89: # | BY89: # | BZ89: # | CA89: # | CB89: # | CC89: # | CD89: # | CE89: # | CF89: # | CG89: # | CH89: # | CI89: # | CJ89: # | CK89: # | CL89: # | CM89: # | CN89: # | CO89: # | CP89: # | CQ89: # | CR89: # | CS89: # | CT89: # | CU89: # | CV89: # | CW89: # | CX89: # | CY89: # | CZ89: # | DA89: # | DB89: # | DC89: # | DD89: # | DE89: # | DF89: # | DG89: # | DH89: # | DI89: #
A90: a84_0 | B90: Qasmieh, S.A. et al. (c) | C90: prosp. cohort | D90: 44728 | E90: 44744 | F90: United States | G90: NA; adults across the United States | H90: unclear | I90: 89598.86 | J90: unclear | K90: 3042 | L90: =389+829 -> 1218 | M90: # | N90: =MAX(K90:M90) -> 3042 | O90: Number of people eligible for self-testing | P90: # | Q90: # | R90: # | S90: # | T90: # | U90: # | V90: # | W90: 1516 | X90: 1443 | Y90: 82 | Z90: General population | AA90: # | AB90: # | AC90: # | AD90: 0 | AE90: 1104 individuals with comorbidities; 1938 without | AF90: # | AG90: unknown | AH90: Boosted: 1610 individuals Fully vaccinated not boosted: 476 individuals Not vaccinated: 957 individuals | AI90: SARS-CoV-2 immunity Vaccine- and infection-induced (hybrid): 987 individuals Vaccine-induced only: 1099 individuals Infection-induced only: 501 individuals No prior SARS-CoV-2 immunity: 456 individuals | AJ90: Unclear | AK90: # | AL90: # | AM90: # | AN90: Unclear | AO90: Unclear | AP90: # | AQ90: # | AR90: # | AS90: # | AT90: # | AU90: unclear | AV90: unclear | AW90: # | AX90: # | AY90: # | AZ90: # | BA90: # | BB90: # | BC90: # | BD90: # | BE90: # | BF90: # | BG90: # | BH90: # | BI90: # | BJ90: # | BK90: # | BL90: # | BM90: # | BN90: # | BO90: # | BP90: # | BQ90: # | BR90: # | BS90: # | BT90: # | BU90: # | BV90: # | BW90: # | BX90: # | BY90: # | BZ90: # | CA90: # | CB90: # | CC90: # | CD90: # | CE90: # | CF90: # | CG90: # | CH90: # | CI90: # | CJ90: # | CK90: # | CL90: # | CM90: # | CN90: # | CO90: # | CP90: # | CQ90: # | CR90: # | CS90: # | CT90: # | CU90: # | CV90: # | CW90: # | CX90: # | CY90: # | CZ90: # | DA90: # | DB90: # | DC90: # | DD90: # | DE90: # | DF90: # | DG90: # | DH90: # | DI90: #
AN93: Routine | AO93: =COUNTIF($AO$4:$AO$90,AN93) -> 52
F94: EU* | G94: =COUNTIF($G$4:$G$90,F94) -> 26 | M94: SUM | N94: =SUM(N4:N90) -> 25288225 | Z94: SUM | AA94: =SUM(AA4:AA90) -> 4333132 | AB94: =SUM(AB4:AB90) -> 19760579 | AC94: =SUM(N4:N90)-SUM(AA94:AB94) -> 1194514 | AN94: Single | AO94: =COUNTIF($AO$4:$AO$90,AN94) -> 16
F95: UK* | G95: =COUNTIF($G$4:$G$90,F95) -> 15 | Z95: Relative | AA95: =AA94/N94 -> 0.17134979 | AB95: =AB94/N94 -> 0.78141424 | AC95: =AC94/N94 -> 0.047235976 | AN95: Unclear | AO95: =COUNTIF($AO$4:$AO$90,AN95) -> 19
F96: NA* | G96: =COUNTIF($G$4:$G$90,F96) -> 23
F97: AS* | G97: =COUNTIF($G$4:$G$90,F97) -> 20 | Z97: Healthcare Professionals | AA97: =COUNTIF($Z$4:$Z$90,Z97) -> 17
F98: Other* | G98: =COUNTIF($G$4:$G$90,F98) -> 3 | Z98: University students and staff | AA98: =COUNTIF($Z$4:$Z$90,Z98) -> 5
Z99: K-12 students and staff | AA99: =COUNTIF($Z$4:$Z$90,Z99) -> 19
Z100: General population | AA100: =COUNTIF($Z$4:$Z$90,Z100) -> 41
Z101: Manufacturing employees | AA101: =COUNTIF($Z$4:$Z$90,Z101) -> 1
Z102: Unclear | AA102: =COUNTIF($Z$4:$Z$90,Z102) -> 4

Sheet Mapping
A1: Name | B1: Column_Data extraction (row 3) | D1: Please note
B2: Label | C2: Name
A3: Authors | B3: B | C3: Author
A4: StudyID | B4: A | C4: Study ID
A5: testingsite | B5: AN | C5: Testing site
A6: population | B6: Z | C6: Target population
A7: country | B7: F | C7: Location
A8: AgName | B8: AJ | C8: Ag-RDT name
A9: Testregime | B9: AO | C9: Frequency of Testing
A10: Testfrequency | B10: AP | C10: Times per week | D10: Please define in the code 1 = 'once', 2 = 'twice', and any number ≥ 3 = 'threemore'; 'unclear' and '#' can be used as is
A11: Sympstat | B11: AD | C11: Overview symptom status
A12: Uptake | B12: # | C12: #
A13: UptakeN | B13: L | C13: Number of people that collected / were sent self-tests
A14: UptakeD | B14: K | C14: Number of people eligible / invited for self-testing
A15: Report | B15: # | C15: #
A16: ReportN | B16: M | C16: Number of people that reported self-testing results
A17: ReportD | B17: L | C17: Number of people that collected / were sent self-tests
A18: Adherent | B18: # | C18: #
A19: AdherentN | B19: AT | C19: Number of results reported
A20: AdherentD | B20: AR | C20: Optimal # of tests performed as per testing scheme
A21: Ppositive | B21: # | C21: #
A22: PpositiveN | B22: BM | C22: Ag-RDT_n people_Positive | D22: Only analyse if SARS-CoV-2 status = 'unknown' (column AG)
A23: PpositiveD | B23: M | C23: Number of people that reported self-testing results | D23: Only analyse if SARS-CoV-2 status = 'unknown' (column AG)
A24: Tpositive | B24: # | C24: #
A25: TpositiveN | B25: AZ | C25: Ag-RDT_n tests_Positive | D25: Only analyse if SARS-CoV-2 status = 'unknown' (column AG)
A26: TpositiveD | B26: AT | C26: Number of results reported | D26: Only analyse if SARS-CoV-2 status = 'unknown' (column AG)
A27: FPR | B27: # | C27: #
A28: FPRN | B28: BJ | C28: Confirm_n tests_FP | D28: Only analyse if Label_FN_FP_analysis = 'include' (column DE)
A29: FPRD | B29: BK | C29: Confirm_n tests_FP_ref | D29: Only analyse if Label_FN_FP_analysis = 'include' (column DE)
A30: Missed | B30: # | C30: #
A31: MissedN | B31: BU | C31: Confirm_n people_FN | D31: Only analyse if Label_FN_FP_analysis = 'include' (column DE)
A32: MissedD | B32: BX | C32: Confirm_n people_FN_ref | D32: Only analyse if Label_FN_FP_analysis = 'include' (column DE)
A33: Invalid | B33: # | C33: #
A34: InvalidN | B34: BB | C34: Ag-RDT_n tests_Invalid
A35: InvalidD | B35: AT | C35: Number of results reported
